Workbook

Sheet 说明
A1: 爆破跑道 · 游戏配置表
A3: 怎么用
A4: 1. 修改各工作表里的数值和名称（蓝色字是数值，黑色字是文字，灰色字是 id，不要改 id）。
A5: 2. 每个工作表的第 2 行是游戏读取用的字段名，请不要修改、删除或调换列顺序以外的内容；可以调换列顺序。
A6: 3. 在 Excel 中保存为 .xlsx；如果用 Google Sheets，先把本文件上传到 Google 云端硬盘并用 Google 表格打开，改完后选「文件 → 下载 → Microsoft Excel (.xlsx)」。
A7: 4. 打开游戏页面，点「导入配置表 (.xlsx)」选择文件。游戏会立即按新配置重新开局；有问题的单元格会列在导入提示里，并自动使用默认值。
A8: 5. 点「恢复默认」可以回到内置配置。导入的配置只保存在当前浏览器里，换设备需要重新导入。
A10: 注意
A11: · 说明文字不会随数值自动变化。改了数值（比如冷却秒数），记得同步改对应的说明文字（三种语言）。
A12: · 名称、说明都有中文、English、Français 三列；某一列留空会使用原来的文字。
A13: · 斜体黑字的列（如「累计花费」「本波总人数」）是自动计算的参考列，游戏不读取。
A14: · 「波次」表的行数就是总波数，可以增删行；boss 列填 1 的波次会出现 Boss。
... A36: 数值体检·装置：每个升级和「同价多放几座基础装置」比谁更划算，含估算和实测两套数字

Sheet 全局
A1: 参数 | B1: 数值 | C1: 说明
A2: key | B2: value | C2: desc
A3: waves | B3: 15 | C3: 总波数（须与「波次」表行数一致）
A4: eliteAffixes | B4: 2 | C4: 精英波词缀数量
A5: startGold | B5: 300 | C5: 开局 GST
A6: startLives | B6: 20 | C6: 开局生命
A7: waveReward | B7: 30 | C7: 每波守住的基础 GST 奖励
A8: eliteReward | B8: 60 | C8: 精英波额外 GST 奖励
A9: eliteHpMult | B9: 1.4 | C9: 精英波对手体力倍率
A10: betweenTime | B10: 8 | C10: 两波之间的布置时间（秒）
A11: earlyBonusPerSec | B11: 5 | C11: 提前开波每剩 1 秒奖励的 GST
A12: rerollBase | B12: 20 | C12: 神秘箱重抽起始价格
A13: rerollStep | B13: 10 | C13: 每次重抽涨价
A14: sellRefund | B14: 0.6 | C14: 回收装置返还比例
... A96: scoreClean | B96: 100 | C96: 分数：无漏怪波数权重

Sheet 装置
A1: id | B1: 名称（中文） | C1: 名称（English） | D1: 名称（Français） | E1: 简称（中文） | F1: 简称（English） | G1: 简称（Français） | H1: 说明（中文） | I1: 说明（English） | J1: 说明（Français） | K1: 放置价格 | L1: 效果 | M1: 出手间隔（秒） | N1: 射程（999=全图） | O1: 范围半径 | P1: 减速比例 | Q1: 湿滑持续（秒） | R1: 传播人数 | S1: 传播衰减 | T1: 对耐力跑者效果 | U1: 对 Boss 效果 | V1: 颜色
A2: id | B2: name_zh | C2: name_en | D2: name_fr | E2: short_zh | F2: short_en | G2: short_fr | H2: desc_zh | I2: desc_en | J2: desc_fr | K2: cost | L2: dmg | M2: rate | N2: range | O2: rad | P2: slow | Q2: slowDur | R2: chain | S2: decay | T2: armor | U2: bossMul | V2: color
A3: dart | B3: 易拉罐投手 | C3: Can Thrower | D3: Lanceur de canettes | E3: 易拉罐 | F3: Can | G3: Canette | H3: 单体速投易拉罐；对耐力跑者只有 25% 效果，「铁罐」2 级后破甲 | I3: Rapid single-target cans; only 25% vs endurance runners until “Iron Can” tier 2 | J3: Canettes rapides sur une cible ; 25 % contre les coureurs endurants jusqu’à « Canette en fer » niv. 2 | K3: 100 | L3: 1 | M3: 0.5 | N3: 95 | O3: 0 | P3: 0 | Q3: 0 | R3: 0 | S3: 1 | T3: 0.25 | U3: 0.6 | V3: #ff6b6b
A4: bomb | B4: 香蕉皮投手 | C4: Banana Peeler | D4: Lanceur de peaux de banane | E4: 香蕉皮 | F4: Banana | G4: Banane | H4: 扔香蕉皮，一片跑者一起滑倒；耐力跑者的克星 | I4: Throws banana peels that trip a whole group; counters endurance runners | J4: Lance des peaux de banane qui font glisser un groupe ; contre les endurants | K4: 160 | L4: 3 | M4: 1.3 | N4: 82 | O4: 40 | P4: 0 | Q4: 0 | R4: 0 | S4: 1 | T4: 1 | U4: 1 | V4: #ffd84a
A5: frost | B5: 洒水器 | C5: Sprinkler | D5: Arroseur | E5: 洒水器 | F5: Sprinkler | G5: Arroseur | H5: 洒水让跑道湿滑，范围减速 | I5: Wets the track to slow an area | J5: Mouille la piste pour ralentir une zone | K5: 120 | L5: 0.5 | M5: 1.1 | N5: 72 | O5: 0 | P5: 0.35 | Q5: 1.5 | R5: 0 | S5: 1 | T5: 0.5 | U5: 1 | V5: #6fc3ff
A6: sniper | B6: 鞋盒无人机 | C6: Shoebox Drone | D6: Drone à boîtes | E6: 无人机 | F6: Drone | G6: Drone | H6: 全图空投鞋盒，专砸体力最多的跑者，无视耐力 | I6: Drops shoeboxes anywhere on the strongest runner, ignores endurance | J6: Largue des boîtes partout sur le coureur le plus endurant, ignore l’endurance | K6: 180 | L6: 6 | M6: 1.7 | N6: 999 | O6: 0 | P6: 0 | Q6: 0 | R6: 0 | S6: 1 | T6: 1 | U6: 1 | V6: #ff9d7a
A7: tesla | B7: 广场舞音响 | C7: Dance Speaker | D7: Enceinte de danse | E7: 音响 | F7: Speaker | G7: Enceinte | H7: 洗脑神曲在跑者之间传播，一次影响好几个 | I7: An earworm hops between runners, hitting several at once | J7: Un tube entêtant passe d’un coureur à l’autre | K7: 150 | L7: 2 | M7: 0.9 | N7: 88 | O7: 0 | P7: 0 | Q7: 0 | R7: 3 | S7: 0.85 | T7: 0.5 | U7: 1 | V7: #ff8fd0
A8: miner | B8: 矿机 | C8: Miner | D8: Mineur | E8: 矿机 | F8: Miner | G8: Mineur | H8: 不攻击，比赛中不停算题挖区块：挖到区块得聪和一次三选一 | I8: Doesn’t attack; keeps hashing during the race. Win a block for sats and a pick-one-of-three | J8: N’attaque pas ; calcule pendant la course. Bloc gagné : des sats et un choix parmi trois | K8: 120 | L8: 0 | M8: 1 | N8: 70 | O8: 0 | P8: 0 | Q8: 0 | R8: 0 | S8: 1 | T8: 1 | U8: 1 | V8: #f7931a
A9: gem | B9: 宝石发射器 | C9: Gem Launcher | D9: Lance-gemmes | E9: 宝石 | F9: Gems | G9: Gemmes | H9: 发射宝石：红宝石主攻暴击，黄宝石主攻连发和 GST，蓝宝石减速冻结 | I9: Fires gems: ruby for crits, topaz for multi-shot and GST, sapphire to slow and freeze | J9: Tire des gemmes : rubis pour les critiques, topaze pour les tirs multiples et le GST, saphir pour ralentir et geler | K9: 140 | L9: 1.5 | M9: 0.7 | N9: 100 | O9: 0 | P9: 0 | Q9: 0 | R9: 0 | S9: 1 | T9: 0.6 | U9: 1 | V9: #00a6f4

Sheet 升级路线
A1: 装置 id | B1: 路线 | C1: 路线名称（中文） | D1: 路线名称（English） | E1: 路线名称（Français）
A2: tower | B2: path | C2: name_zh | D2: name_en | E2: name_fr
A3: miner | B3: 1 | C3: 算力 | D3: Hash | E3: Puissance
A4: miner | B4: 2 | C4: 矿池 | D4: Pool | E4: Pool
A5: miner | B5: 3 | C5: 散热 | D5: Cooling | E5: Refroidissement
A6: gem | B6: 1 | C6: 红宝石 | D6: Ruby | E6: Rubis
A7: gem | B7: 2 | C7: 黄宝石 | D7: Topaz | E7: Topaze
A8: gem | B8: 3 | C8: 蓝宝石 | D8: Sapphire | E8: Saphir
A9: dart | B9: 1 | C9: 铁罐 | D9: Iron Can | E9: Canette en fer
A10: dart | B10: 2 | C10: 连投 | D10: Rapid Toss | E10: Lancers rapides
A11: dart | B11: 3 | C11: 瞄准 | D11: Aim | E11: Visée
A12: bomb | B12: 1 | C12: 大香蕉 | D12: Big Banana | E12: Grosse banane
A13: bomb | B13: 2 | C13: 一串香蕉 | D13: Banana Bunch | E13: Régime de bananes
A14: bomb | B14: 3 | C14: 辣椒油 | D14: Chili Oil | E14: Huile pimentée
... A23: tesla | B23: 3 | C23: 洗脑神曲 | D23: Earworm | E23: Tube entêtant

Sheet 升级
A1: 装置 id | B1: 路线 | C1: 等级 | D1: 名称（中文） | E1: 名称（English） | F1: 名称（Français） | G1: 价格 | H1: 说明（中文） | I1: 说明（English） | J1: 说明（Français） | K1: 效果（见「效果语法」） | L1: 本路线累计花费
A2: tower | B2: path | C2: tier | D2: name_zh | E2: name_en | F2: name_fr | G2: cost | H2: desc_zh | I2: desc_en | J2: desc_fr | K2: effect
A3: miner | B3: 1 | C3: 1 | D3: 超频 CPU | E3: Overclocked CPU | F3: CPU surcadencé | G3: 60 | H3: 算力 +50% | I3: Hash +50% | J3: Puissance +50 % | K3: hash*=1.5 | L3: =SUMIFS($G$3:$G$107,$A$3:$A$107,A3,$B$3:$B$107,B3,$C$3:$C$107,"<="&C3)
A4: miner | B4: 1 | C4: 2 | D4: 双核处理器 | E4: Dual-core CPU | F4: Processeur double cœur | G4: 120 | H4: 算力 +50% | I4: Hash +50% | J4: Puissance +50 % | K4: hash*=1.5 | L4: =SUMIFS($G$3:$G$107,$A$3:$A$107,A4,$B$3:$B$107,B4,$C$3:$C$107,"<="&C4)
A5: miner | B5: 1 | C5: 3 | D5: 显卡挖矿 | E5: GPU Mining | F5: Minage GPU | G5: 300 | H5: 算力 ×3（2010 年显卡挖矿开始流行） | I5: Hash ×3 (GPU mining took off in 2010) | J5: Puissance ×3 (le minage GPU décolle en 2010) | K5: hash*=3 | L5: =SUMIFS($G$3:$G$107,$A$3:$A$107,A5,$B$3:$B$107,B5,$C$3:$C$107,"<="&C5)
A6: miner | B6: 1 | C6: 4 | D6: 多卡矿机 | E6: Multi-GPU Rig | F6: Rig multi-GPU | G6: 700 | H6: 算力 ×2 | I6: Hash ×2 | J6: Puissance ×2 | K6: hash*=2 | L6: =SUMIFS($G$3:$G$107,$A$3:$A$107,A6,$B$3:$B$107,B6,$C$3:$C$107,"<="&C6)
A7: miner | B7: 1 | C7: 5 | D7: 显卡农场 | E7: GPU Farm | F7: Ferme GPU | G7: 1500 | H7: 算力 ×2.5 | I7: Hash ×2.5 | J7: Puissance ×2,5 | K7: hash*=2.5 | L7: =SUMIFS($G$3:$G$107,$A$3:$A$107,A7,$B$3:$B$107,B7,$C$3:$C$107,"<="&C7)
A8: miner | B8: 2 | C8: 1 | D8: 加入矿池 | E8: Join a Pool | F8: Rejoindre un pool | G8: 70 | H8: 出块奖励 +25% | I8: Block reward +25% | J8: Récompense de bloc +25 % | K8: blockBonus+=0.25 | L8: =SUMIFS($G$3:$G$107,$A$3:$A$107,A8,$B$3:$B$107,B8,$C$3:$C$107,"<="&C8)
A9: miner | B9: 2 | C9: 2 | D9: 矿池分成 | E9: Pool Payout | F9: Partage du pool | G9: 140 | H9: 射程内其他装置效果 +15% | I9: Other devices in range: effect +15% | J9: Autres dispositifs à portée : effet +15 % | K9: auraDmg=1.15 | L9: =SUMIFS($G$3:$G$107,$A$3:$A$107,A9,$B$3:$B$107,B9,$C$3:$C$107,"<="&C9)
A10: miner | B10: 2 | C10: 3 | D10: 稳定收益 | E10: Steady Income | F10: Revenu stable | G10: 320 | H10: 出块奖励再 +50% | I10: Block reward +50% more | J10: Récompense de bloc encore +50 % | K10: blockBonus+=0.5 | L10: =SUMIFS($G$3:$G$107,$A$3:$A$107,A10,$B$3:$B$107,B10,$C$3:$C$107,"<="&C10)
A11: miner | B11: 2 | C11: 4 | D11: 大矿池 | E11: Big Pool | F11: Gros pool | G11: 700 | H11: 射程内其他装置效果 +30%，射程 +30 | I11: Other devices in range: effect +30%; range +30 | J11: Autres dispositifs à portée : effet +30 % ; portée +30 | K11: auraDmg=1.3; range+=30 | L11: =SUMIFS($G$3:$G$107,$A$3:$A$107,A11,$B$3:$B$107,B11,$C$3:$C$107,"<="&C11)
A12: miner | B12: 2 | C12: 5 | D12: 算力联盟 | E12: Hash Alliance | F12: Alliance de puissance | G12: 1500 | H12: 出块奖励再 +100%，射程内装置出手间隔 −15% | I12: Block reward +100% more; devices in range: interval −15% | J12: Récompense encore +100 % ; dispositifs à portée : intervalle −15 % | K12: blockBonus+=1; auraRate=0.85 | L12: =SUMIFS($G$3:$G$107,$A$3:$A$107,A12,$B$3:$B$107,B12,$C$3:$C$107,"<="&C12)
A13: miner | B13: 3 | C13: 1 | D13: 风扇狂转 | E13: Fans Roaring | F13: Ventilos à fond | G13: 60 | H13: 吹出热风：射程内跑者每秒受 1 点效果并挂上“热” | I13: Blows hot air: runners in range take 1 effect per second and get “Heat” | J13: Souffle de l’air chaud : coureurs à portée subissent 1 effet par seconde et reçoivent « Chaleur » | K13: heat+=1 | L13: =SUMIFS($G$3:$G$107,$A$3:$A$107,A13,$B$3:$B$107,B13,$C$3:$C$107,"<="&C13)
A14: miner | B14: 3 | C14: 2 | D14: 机箱漏风 | E14: Leaky Case | F14: Boîtier qui fuit | G14: 120 | H14: 热风 +2 | I14: Heat +2 | J14: Chaleur +2 | K14: heat+=2 | L14: =SUMIFS($G$3:$G$107,$A$3:$A$107,A14,$B$3:$B$107,B14,$C$3:$C$107,"<="&C14)
... A107: tesla | B107: 3 | C107: 5 | D107: 广场舞女王 | E107: Dance Floor Queen | F107: Reine de la piste | G107: 1600 | H107: 出手间隔 −30%，多传 3 人 | I107: Interval −30%, chains 3 more | J107: Intervalle −30 %, 3 de plus en chaîne | K107: rate*=0.7; chain+=3 | L107: =SUMIFS($G$3:$G$107,$A$3:$A$107,A107,$B$3:$B$107,B107,$C$3:$C$107,"<="&C107)

Sheet 敌人
A1: id | B1: 名称（中文） | C1: 名称（English） | D1: 名称（Français） | E1: 体型半径 | F1: 移速 | G1: 劝退 GST | H1: 计分权重 | I1: 漏过扣能量
A2: id | B2: name_zh | C2: name_en | D2: name_fr | E2: radius | F2: speed | G2: gold | H2: value | I2: leak
A3: norm | B3: 慢跑者 | C3: Jogger | D3: Joggeur | E3: 9 | F3: 55 | G3: 6 | H3: 1 | I3: 1
A4: arm | B4: 耐力跑者 | C4: Endurance runner | D4: Coureur endurant | E4: 11 | F4: 42 | G4: 12 | H4: 2 | I4: 2
A5: boss | B5: 传奇跑者 | C5: Legendary runner | D5: Coureur légendaire | E5: 22 | F5: 26 | G5: 80 | H5: 15 | I5: 10
A6: rain | B6: 雨衣跑者 | C6: Raincoat Runner | D6: Coureur en ciré | E6: 9 | F6: 52 | G6: 8 | H6: 1 | I6: 1
A7: hop | B7: 弹簧鞋跑者 | C7: Spring-Shoe Runner | D7: Coureur à ressorts | E7: 9 | F7: 62 | G7: 8 | H7: 1 | I7: 1
A8: phones | B8: 降噪耳机跑者 | C8: Headphones Runner | D8: Coureur au casque | E8: 9 | F8: 55 | G8: 8 | H8: 1 | I8: 1
A9: whale | B9: 巨鲸 | C9: Whale | D9: Baleine | E9: 15 | F9: 30 | G9: 30 | H9: 4 | I9: 3
A11: ※ 体力按波次配置，见「波次」表。雨衣/弹簧鞋/降噪耳机跑者体力 = 慢跑者体力 × hpRain/hpHop/hpPhones，巨鲸 = 耐力跑者体力 × hpWhale（见「全局」）。克制：雨衣跑者不怕洒水器；弹簧鞋跑者跳过香蕉皮（懵时除外）；降噪耳机跑者不怕音响；巨鲸削弱单次效果低于 whaleMin 的攻击。

Sheet 波次
A1: 波次 | B1: 慢跑者人数 | C1: 耐力跑者人数 | D1: 慢跑者体力 | E1: 耐力跑者体力 | F1: 是否 Boss 波（1/0） | G1: Boss 体力 | H1: 词缀数量 | I1: 雨衣跑者 | J1: 弹簧鞋跑者 | K1: 降噪耳机跑者 | L1: 巨鲸 | M1: 本波总人数
A2: wave | B2: normals | C2: armored | D2: normHp | E2: armHp | F2: boss | G2: bossHp | H2: affixes | I2: rain | J2: hop | K2: phones | L2: whale
A3: 1 | B3: 30 | C3: 0 | D3: 3.2 | E3: 7.7 | F3: 0 | G3: 0 | H3: 0 | I3: 0 | J3: 0 | K3: 0 | L3: 0 | M3: =B3+C3+F3+SUM(I3:L3)
A4: 2 | B4: 36 | C4: 0 | D4: 4.4 | E4: 10.3 | F4: 0 | G4: 0 | H4: 0 | I4: 0 | J4: 0 | K4: 0 | L4: 0 | M4: =B4+C4+F4+SUM(I4:L4)
A5: 3 | B5: 39 | C5: 6 | D5: 5.8 | E5: 13.3 | F5: 0 | G5: 0 | H5: 0 | I5: 0 | J5: 0 | K5: 0 | L5: 0 | M5: =B5+C5+F5+SUM(I5:L5)
A6: 4 | B6: 45 | C6: 9 | D6: 7.4 | E6: 16.7 | F6: 0 | G6: 0 | H6: 1 | I6: 4 | J6: 0 | K6: 0 | L6: 0 | M6: =B6+C6+F6+SUM(I6:L6)
A7: 5 | B7: 51 | C7: 12 | D7: 9.2 | E7: 20.5 | F7: 1 | G7: 100 | H7: 1 | I7: 5 | J7: 0 | K7: 0 | L7: 0 | M7: =B7+C7+F7+SUM(I7:L7)
A8: 6 | B8: 57 | C8: 15 | D8: 11.2 | E8: 24.7 | F8: 0 | G8: 0 | H8: 1 | I8: 6 | J8: 5 | K8: 0 | L8: 0 | M8: =B8+C8+F8+SUM(I8:L8)
A9: 7 | B9: 60 | C9: 18 | D9: 13.4 | E9: 29.3 | F9: 0 | G9: 0 | H9: 1 | I9: 6 | J9: 5 | K9: 0 | L9: 0 | M9: =B9+C9+F9+SUM(I9:L9)
A10: 8 | B10: 66 | C10: 21 | D10: 15.8 | E10: 34.3 | F10: 0 | G10: 0 | H10: 1 | I10: 7 | J10: 5 | K10: 5 | L10: 0 | M10: =B10+C10+F10+SUM(I10:L10)
A11: 9 | B11: 72 | C11: 24 | D11: 19.5 | E11: 42.08 | F11: 0 | G11: 0 | H11: 1 | I11: 7 | J11: 6 | K11: 6 | L11: 0 | M11: =B11+C11+F11+SUM(I11:L11)
A12: 10 | B12: 78 | C12: 27 | D12: 23.74 | E12: 50.96 | F12: 1 | G12: 420 | H12: 2 | I12: 8 | J12: 6 | K12: 6 | L12: 1 | M12: =B12+C12+F12+SUM(I12:L12)
A13: 11 | B13: 81 | C13: 33 | D13: 28.56 | E13: 61.01 | F13: 0 | G13: 0 | H13: 1 | I13: 8 | J13: 6 | K13: 6 | L13: 1 | M13: =B13+C13+F13+SUM(I13:L13)
A14: 12 | B14: 87 | C14: 36 | D14: 33.98 | E14: 72.29 | F14: 0 | G14: 0 | H14: 1 | I14: 9 | J14: 7 | K14: 7 | L14: 2 | M14: =B14+C14+F14+SUM(I14:L14)
... A17: 15 | B17: 102 | C17: 45 | D17: 54.24 | E17: 114.31 | F17: 1 | G17: 1400 | H17: 2 | I17: 10 | J17: 8 | K17: 8 | L17: 3 | M17: =B17+C17+F17+SUM(I17:L17)
A19: ※ 行数就是总波数，可以增删行；精英小队的词缀数量见「全局」eliteAffixes。

Sheet Boss
A1: id | B1: 启用（1/0） | C1: 名字 | D1: 称号（中文） | E1: 称号（English） | F1: 称号（Français） | G1: 能力说明（中文） | H1: 能力说明（English） | I1: 能力说明（Français） | J1: p1 | K1: p2 | L1: p3 | M1: p4 | N1: p1–p4 含义
A2: id | B2: enabled | C2: name | D2: title_zh | E2: title_en | F2: title_fr | G2: ability_zh | H2: ability_en | I2: ability_fr | J2: p1 | K2: p2 | L2: p3 | M2: p4
A3: yawn | B3: 1 | C3: Nox | D3: 黑猫 | E3: Black Cat | F3: Chat noir | G3: 九命：第一次退赛会原地复活（40% 体力） | H3: Nine Lives: revives once on the spot (40% stamina) | I3: Neuf vies : revient une fois sur place (40 % d’endurance) | J3: 0.4 | K3: 1 | L3: 0 | M3: 0 | N3: p1 = 复活体力比例；p2 = 复活后无敌秒数
A4: gilg | B4: 1 | C4: Aurum | D4: 金王 | E4: Golden King | F4: Roi doré | G4: 王之宝库：每 4 秒召唤 2 名金甲跑者 | H4: Royal Treasury: summons 2 golden runners every 4 s | I4: Trésor royal : invoque 2 coureurs dorés toutes les 4 s | J4: 4 | K4: 2 | L4: 8 | M4: 0.8 | N4: p1 = 召唤间隔（秒）；p2 = 每次召唤人数；p3 = 最多召唤人数；p4 = 金甲跑者体力倍率
A5: king | B5: 1 | C5: Slimo | D5: 黏液国王 | E5: Slime King | F5: Roi visqueux | G5: 黏液王冠：身后留下黏液，踩到的跑者加速 30% 并回体力 | H5: Slime Crown: leaves a slime trail; runners on it get +30% speed and recover stamina | I5: Couronne visqueuse : laisse une traînée ; les coureurs dessus gagnent +30 % de vitesse et récupèrent | J5: 0.3 | K5: 1.3 | L5: 0.04 | M5: 5 | N5: p1 = 黏液间隔（秒）；p2 = 黏液上速度倍率；p3 = 黏液上每秒回复比例；p4 = 黏液持续（秒）
A6: lucas | B6: 1 | C6: Rocco | D6: 光头 | E6: Bald Dasher | F6: Crâne rasé | G6: 铁头冲刺：每 5 秒冲刺 1 秒，3 倍速 | H6: Headstrong Dash: every 5 s, sprints at ×3 speed for 1 s | I6: Charge tête baissée : toutes les 5 s, sprint ×3 pendant 1 s | J6: 5 | K6: 1 | L6: 3 | M6: 0 | N6: p1 = 冲刺间隔（秒）；p2 = 冲刺时长（秒）；p3 = 冲刺速度倍率
A7: shiti | B7: 1 | C7: Chuckles | D7: 笑声 | E7: Laughter | F7: Fou rire | G7: 开怀大笑：每 6 秒大笑一次，身边的装置停工 1.5 秒 | H7: Big Laugh: every 6 s, nearby devices stop for 1.5 s | I7: Fou rire : toutes les 6 s, les dispositifs proches s’arrêtent 1,5 s | J7: 6 | K7: 130 | L7: 1.5 | M7: 0 | N7: p1 = 大笑间隔（秒）；p2 = 影响半径；p3 = 装置停工（秒）
A8: pizza | B8: 1 | C8: Pizza Rider | D8: 披萨外卖员 | E8: Pizza courier | F8: Livreur de pizza | G8: 一万枚换两个披萨：体力掉到 2/3 和 1/3 时各扔下一盒披萨，冒出一群披萨跑者 | H8: 10,000 coins for two pizzas: at 2/3 and 1/3 stamina he drops a pizza box and a swarm of pizza runners pours out | I8: 10 000 pièces pour deux pizzas : à 2/3 et 1/3 d’endurance, il lâche une boîte et une nuée de coureurs-pizza en sort | J8: 5 | K8: 0.22 | L8: 0 | M8: 0 | N8: p1 = 每盒披萨冒出几个跑者；p2 = 披萨跑者体力占比
A9: overflow | B9: 1 | C9: Overflow | D9: 溢出怪 | E9: The Overflow | F9: Le Débordement | G9: 整数溢出：第一次倒下时分裂成两个，各带 60% 体力；几秒后“软分叉”修复，两个都掉一半体力 | H9: Integer overflow: the first time it falls it splits into two, each with 60% stamina; a few seconds later a “soft fork” patch halves both | I9: Dépassement d’entier : la première fois qu’il tombe, il se divise en deux, chacun à 60 % d’endurance ; quelques secondes plus tard, un « soft fork » coupe leur endurance de moitié | J9: 4 | K9: 0.5 | L9: 0 | M9: 0 | N9: p1 = 软分叉延迟（秒）；p2 = 软分叉扣除体力比例
A10: jerry | B10: 1 | C10: Datto | D10: 数据控 | E10: Data Nerd | F10: Fan de données | G10: 数据分析：每 3 秒对受到最多的装置类型产生 65% 抗性 | H10: Data Analysis: every 3 s gains 65% resistance to the device hitting him most | I10: Analyse de données : toutes les 3 s, résiste à 65 % au dispositif qui le touche le plus | J10: 3 | K10: 0.65 | L10: 0 | M10: 0 | N10: p1 = 统计间隔（秒）；p2 = 抗性比例

Sheet 词缀
A1: id | B1: 名称（中文） | C1: 名称（English） | D1: 名称（Français） | E1: 说明（中文） | F1: 说明（English） | G1: 说明（Français）
A2: id | B2: name_zh | C2: name_en | D2: name_fr | E2: desc_zh | F2: desc_en | G2: desc_fr
A3: swift | B3: 冲刺 | C3: Sprint | D3: Sprint | E3: 移速 +40% | F3: Speed +40% | G3: Vitesse +40 %
A4: regen | B4: 补给 | C4: Refuel | D4: Ravitaillement | E4: 1 秒没被干扰就回体力 | F4: Recovers stamina after 1 s undisturbed | G4: Récupère de l’endurance après 1 s sans gêne
A5: shield | B5: 能量盾 | C5: Energy Shield | D5: Bouclier d’énergie | E5: 额外 35% 能量护盾 | F5: Extra 35% energy shield | G5: Bouclier d’énergie +35 %
A6: split | B6: 跑团 | C6: Running Club | D6: Club de course | E6: 退赛时 2 名跟跑者接力 | F6: 2 pacers take over when one quits | G6: 2 meneurs prennent le relais à l’abandon
A8: ※ 词缀数值（冲刺倍率、补给回复、能量盾比例、跟跑者体力）在「全局」表。

Sheet 卡牌
A1: id | B1: 启用（1/0） | C1: 类别 | D1: 稀有度（C/R/L） | E1: 可重复（1/0） | F1: 名称（中文） | G1: 名称（English） | H1: 名称（Français） | I1: 说明（中文） | J1: 说明（English） | K1: 说明（Français） | L1: 数值 v1 | M1: 数值 v2 | N1: v1 / v2 含义
A2: id | B2: enabled | C2: tag | D2: rar | E2: stack | F2: name_zh | G2: name_en | H2: name_fr | I2: desc_zh | J2: desc_en | K2: desc_fr | L2: v1 | M2: v2
A3: u_bomb | B3: 1 | C3: 装置 | D3: C | E3: 0 | F3: 香蕉皮投手 | G3: Banana Peeler | H3: Lanceur de peaux de banane | I3: 解锁香蕉皮投手：一片跑者一起滑倒，专克耐力跑者 | J3: Unlock Banana Peeler: trips whole groups, counters endurance runners | K3: Débloque le Lanceur de peaux : fait glisser des groupes, contre les endurants | L3: 0 | M3: 0
A4: u_frost | B4: 1 | C4: 装置 | D4: C | E4: 0 | F4: 洒水器 | G4: Sprinkler | H4: Arroseur | I4: 解锁洒水器：跑道湿滑，范围减速 | J4: Unlock Sprinkler: wet track, area slow | K4: Débloque l’Arroseur : piste glissante, ralentit une zone | L4: 0 | M4: 0
A5: u_sniper | B5: 1 | C5: 装置 | D5: R | E5: 0 | F5: 鞋盒无人机 | G5: Shoebox Drone | H5: Drone à boîtes | I5: 解锁鞋盒无人机：全图空投鞋盒，无视耐力 | J5: Unlock Shoebox Drone: map-wide drops, ignores endurance | K5: Débloque le Drone à boîtes : largages partout, ignore l’endurance | L5: 0 | M5: 0
A6: u_tesla | B6: 1 | C6: 装置 | D6: R | E6: 0 | F6: 广场舞音响 | G6: Dance Speaker | H6: Enceinte de danse | I6: 解锁广场舞音响：洗脑神曲在跑者之间传播 | J6: Unlock Dance Speaker: an earworm hops between runners | K6: Débloque l’Enceinte de danse : un tube passe de coureur en coureur | L6: 0 | M6: 0
A7: u_miner | B7: 1 | C7: 装置 | D7: R | E7: 0 | F7: 矿机 | G7: Miner | H7: Mineur | I7: 解锁矿机：挖区块得聪，并触发区块奖励三选一 | J7: Unlock the Miner: mine blocks for sats and a block-reward pick | K7: Débloque le Mineur : mine des blocs pour des sats et un choix de récompense | L7: 0 | M7: 0
A8: u_gem | B8: 1 | C8: 装置 | D8: R | E8: 0 | F8: 宝石发射器 | G8: Gem Launcher | H8: Lance-gemmes | I8: 解锁宝石发射器：红、黄、蓝三种宝石对应三条路线 | J8: Unlock the Gem Launcher: ruby, topaz and sapphire are its three paths | K8: Débloque le Lance-gemmes : rubis, topaze et saphir sont ses trois voies | L8: 0 | M8: 0
A9: pad | B9: 1 | C9: 道具 | D9: R | E9: 1 | F9: 额外放置点 | G9: Extra Spot | H9: Emplacement bonus | I9: 获得 1 个放置点：点地图上跑道以外的空地，新增一个装置空位 | J9: Gain 1 spot: tap open ground off the track to add a new device spot | K9: Gagne 1 emplacement : touche un terrain libre hors de la piste pour créer un emplacement | L9: 1 | M9: 0 | N9: v1 = 放置点个数
A10: freeup | B10: 1 | C10: 道具 | D10: C | E10: 1 | F10: 鞋匠 | G10: Cobbler | H10: Cordonnier | I10: 场上一个装置沿主路线免费升 1 级（没有装置时改为 +100 GST） | J10: One device gets a free tier on its main path (+100 GST if you have none) | K10: Un dispositif gagne un niveau gratuit sur sa voie principale (+100 GST si aucun) | L10: 0 | M10: 0
A11: coupon | B11: 1 | C11: 道具 | D11: C | E11: 1 | F11: 升级卷轴 | G11: Level-up Scroll | H11: Parchemin d’amélioration | I11: 接下来 3 次路线升级半价 | J11: Next 3 path upgrades are half price | K11: Les 3 prochaines améliorations à moitié prix | L11: 3 | M11: 0 | N11: v1 = 半价次数
A12: m_dart | B12: 1 | C12: 徽章 | D12: R | E12: 0 | F12: （自动） | G12: （自动） | H12: （自动） | I12: （自动） | J12: （自动） | K12: （自动） | L12: 0 | M12: 0 | N12: 名称和说明自动生成
A13: m_bomb | B13: 1 | C13: 徽章 | D13: R | E13: 0 | F13: （自动） | G13: （自动） | H13: （自动） | I13: （自动） | J13: （自动） | K13: （自动） | L13: 0 | M13: 0 | N13: 名称和说明自动生成
A14: m_frost | B14: 1 | C14: 徽章 | D14: R | E14: 0 | F14: （自动） | G14: （自动） | H14: （自动） | I14: （自动） | J14: （自动） | K14: （自动） | L14: 0 | M14: 0 | N14: 名称和说明自动生成
A15: m_sniper | B15: 1 | C15: 徽章 | D15: R | E15: 0 | F15: （自动） | G15: （自动） | H15: （自动） | I15: （自动） | J15: （自动） | K15: （自动） | L15: 0 | M15: 0 | N15: 名称和说明自动生成
A16: m_tesla | B16: 1 | C16: 徽章 | D16: R | E16: 0 | F16: （自动） | G16: （自动） | H16: （自动） | I16: （自动） | J16: （自动） | K16: （自动） | L16: 0 | M16: 0 | N16: 名称和说明自动生成
A17: m_miner | B17: 1 | C17: 徽章 | D17: R | E17: 0 | F17: （自动） | G17: （自动） | H17: （自动） | I17: （自动） | J17: （自动） | K17: （自动） | L17: 0 | M17: 0 | N17: 名称和说明自动生成
A18: m_gem | B18: 1 | C18: 徽章 | D18: R | E18: 0 | F18: （自动） | G18: （自动） | H18: （自动） | I18: （自动） | J18: （自动） | K18: （自动） | L18: 0 | M18: 0 | N18: 名称和说明自动生成
A19: breaker | B19: 1 | C19: 道具 | D19: L | E19: 0 | F19: 创世鞋 | G19: Genesis Sneaker | H19: Sneaker Genesis | I19: 所有装置的次路线上限 2 级 → 3 级 | J19: Secondary path cap 2 → 3 for all devices | K19: Plafond de la voie secondaire 2 → 3 pour tous | L19: 0 | M19: 0 | N19: 上限见全局 secCapBreaker
A20: drill | B20: 1 | C20: 宝石 | D20: C | E20: 1 | F20: 效率宝石 | G20: Efficiency Gem | H20: Gemme d’efficacité | I20: 所有装置效果 +15%（可叠加） | J20: All devices +15% effect (stacks) | K20: Tous les dispositifs +15 % d’effet (cumulable) | L20: 0.15 | M20: 0 | N20: v1 = 效果加成
A21: crit | B21: 1 | C21: 宝石 | D21: C | E21: 1 | F21: 幸运宝石 | G21: Luck Gem | H21: Gemme de chance | I21: 暴击率 +10%（可叠加） | J21: Crit chance +10% (stacks) | K21: Chance de critique +10 % (cumulable) | L21: 0.1 | M21: 0 | N21: v1 = 暴击率加成
A22: heart | B22: 1 | C22: 宝石 | D22: C | E22: 1 | F22: 舒适宝石 | G22: Comfort Gem | H22: Gemme de confort | I22: 生命 +6 | J22: Lives +6 | K22: Vies +6 | L22: 6 | M22: 0 | N22: v1 = 生命
... A34: overclock | B34: 1 | C34: 道具 | D34: L | E34: 0 | F34: 马拉松模式 | G34: Marathon Mode | H34: Mode marathon | I34: 燃脂模式持续 10 秒，出手速度 ×2 | J34: Fat-burn mode lasts 10 s at ×2 speed | K34: Le mode brûle-graisse dure 10 s à vitesse ×2 | L34: 0 | M34: 0 | N34: 数值见全局
A36: ※ 徽章卡（m_ 开头）的名称和说明由装置简称自动生成，填写无效。稀有度权重在「全局」rarityC/R/L。

Sheet 跑道列表
A1: id | B1: 启用（1/0） | C1: 名称（中文） | D1: 名称（English） | E1: 名称（Français） | F1: 说明（中文） | G1: 说明（English） | H1: 说明（Français） | I1: 对手移速倍率 | J1: 对手体力倍率 | K1: 入口 / 出口 / 路线数
A2: id | B2: enabled | C2: name_zh | D2: name_en | E2: name_fr | F2: desc_zh | G2: desc_en | H2: desc_fr | I2: spdMult | J2: hpMult
A3: classic | B3: 1 | C3: 蛇形跑道 | D3: Serpentine | E3: Serpentin | F3: 1 进 1 出：一条长蛇形跑道，经典布局 | G3: 1 in, 1 out: one long winding track, the classic layout. | H3: 1 entrée, 1 sortie : une longue piste sinueuse, le tracé classique. | I3: 1 | J3: 1 | K3: 1 进 1 出 · 1 条路线
A4: twin | B4: 1 | C4: 双子跑道 | D4: Twin Tracks | E4: Pistes jumelles | F4: 2 进 2 出：两条互不相交的跑道，中间一列空位可以同时照顾两边 | G4: 2 in, 2 out: two separate tracks; the middle column of spots can cover both. | H4: 2 entrées, 2 sorties : deux pistes séparées ; la colonne centrale couvre les deux. | I4: 0.85 | J4: 1 | K4: 2 进 2 出 · 2 条路线
A5: fork | B5: 1 | C5: 分岔路口 | D5: The Fork | E5: La Fourche | F5: 1 进 2 出：跑者在路口分成左右两路，入口处是必争之地 | G5: 1 in, 2 out: runners split left and right at the junction, so the entrance is key. | H5: 1 entrée, 2 sorties : les coureurs se séparent au carrefour ; l’entrée est décisive. | I5: 0.85 | J5: 1 | K5: 1 进 2 出 · 2 条路线
A6: merge | B6: 1 | C6: 汇流跑道 | D6: Confluence | E6: Confluence | F6: 2 进 1 出：两路跑者从两侧进场，在中间汇合后一起冲向终点 | G6: 2 in, 1 out: runners enter from both sides, merge in the middle and rush the finish together. | H6: 2 entrées, 1 sortie : les coureurs arrivent des deux côtés, se rejoignent au centre et filent ensemble. | I6: 0.95 | J6: 1 | K6: 2 进 1 出 · 2 条路线
A7: cross | B7: 1 | C7: 十字路口 | D7: Crossroads | E7: Carrefour | F7: 2 进 2 出：一路从上到下、一路从左到右，两条跑道在右下交叉 | G7: 2 in, 2 out: one track runs top to bottom, the other left to right; they cross at the bottom right. | H7: 2 entrées, 2 sorties : une piste du haut vers le bas, l’autre de gauche à droite ; elles se croisent en bas à droite. | I7: 0.8 | J7: 1 | K7: 2 进 2 出 · 2 条路线
A8: trident | B8: 1 | C8: 三路汇聚 | D8: Trident | E8: Trident | F8: 3 进 1 出：左右两路绕远，中路直冲终点，要优先守住中路 | G8: 3 in, 1 out: the side tracks loop around while the middle one runs straight to the finish, so guard the middle first. | H8: 3 entrées, 1 sortie : les côtés font un détour, le centre file droit à l’arrivée ; protège le centre en priorité. | I8: 0.8 | J8: 1 | K8: 3 进 1 出 · 3 条路线
A10: ※ 每局开始时从启用的跑道里随机选一条（游戏里也可以手动指定）。新增跑道：在这里加一行 id，再到「地图」表填坐标。

Sheet 地图
A1: 跑道 id | B1: 类型（path=路线点，pad=空位） | C1: 路线编号 | D1: 顺序 | E1: x | F1: y
A2: map | B2: type | C2: route | D2: order | E2: x | F2: y
A3: classic | B3: path | C3: 1 | D3: 1 | E3: -24 | F3: 80
A4: classic | B4: path | C4: 1 | D4: 2 | E4: 300 | F4: 80
A5: classic | B5: path | C5: 1 | D5: 3 | E5: 300 | F5: 220
A6: classic | B6: path | C6: 1 | D6: 4 | E6: 60 | F6: 220
A7: classic | B7: path | C7: 1 | D7: 5 | E7: 60 | F7: 360
A8: classic | B8: path | C8: 1 | D8: 6 | E8: 300 | F8: 360
A9: classic | B9: path | C9: 1 | D9: 7 | E9: 300 | F9: 500
A10: classic | B10: path | C10: 1 | D10: 8 | E10: 180 | F10: 500
A11: classic | B11: path | C11: 1 | D11: 9 | E11: 180 | F11: 640
A12: classic | B12: pad | D12: 1 | E12: 40 | F12: 150
A13: classic | B13: pad | D13: 2 | E13: 120 | F13: 150
A14: classic | B14: pad | D14: 3 | E14: 200 | F14: 150
A15: classic | B15: pad | D15: 4 | E15: 250 | F15: 150
A16: classic | B16: pad | D16: 5 | E16: 120 | F16: 290
A17: classic | B17: pad | D17: 6 | E17: 200 | F17: 290
A18: classic | B18: pad | D18: 7 | E18: 260 | F18: 290
A19: classic | B19: pad | D19: 8 | E19: 335 | F19: 290
A20: classic | B20: pad | D20: 9 | E20: 30 | F20: 430
A21: classic | B21: pad | D21: 10 | E21: 110 | F21: 430
A22: classic | B22: pad | D22: 11 | E22: 190 | F22: 430
A23: classic | B23: pad | D23: 12 | E23: 250 | F23: 430
... A25: classic | B25: pad | D25: 14 | E25: 260 | F25: 560
A26: twin | B26: path | C26: 1 | D26: 1 | E26: 60 | F26: -24
A27: twin | B27: path | C27: 1 | D27: 2 | E27: 60 | F27: 180
A28: twin | B28: path | C28: 1 | D28: 3 | E28: 140 | F28: 180
A29: twin | B29: path | C29: 1 | D29: 4 | E29: 140 | F29: 420
A30: twin | B30: path | C30: 1 | D30: 5 | E30: 60 | F30: 420
A31: twin | B31: path | C31: 1 | D31: 6 | E31: 60 | F31: 624
A32: twin | B32: path | C32: 2 | D32: 1 | E32: 300 | F32: -24
A33: twin | B33: path | C33: 2 | D33: 2 | E33: 300 | F33: 180
A34: twin | B34: path | C34: 2 | D34: 3 | E34: 220 | F34: 180
A35: twin | B35: path | C35: 2 | D35: 4 | E35: 220 | F35: 420
A36: twin | B36: path | C36: 2 | D36: 5 | E36: 300 | F36: 420
A37: twin | B37: path | C37: 2 | D37: 6 | E37: 300 | F37: 624
A38: twin | B38: pad | D38: 1 | E38: 180 | F38: 100
A39: twin | B39: pad | D39: 2 | E39: 100 | F39: 100
A40: twin | B40: pad | D40: 3 | E40: 260 | F40: 100
A41: twin | B41: pad | D41: 4 | E41: 180 | F41: 230
A42: twin | B42: pad | D42: 5 | E42: 180 | F42: 300
A43: twin | B43: pad | D43: 6 | E43: 180 | F43: 370
A44: twin | B44: pad | D44: 7 | E44: 100 | F44: 300
A45: twin | B45: pad | D45: 8 | E45: 260 | F45: 300
A46: twin | B46: pad | D46: 9 | E46: 20 | F46: 300
A47: twin | B47: pad | D47: 10 | E47: 340 | F47: 300
A48: twin | B48: pad | D48: 11 | E48: 100 | F48: 500
A49: twin | B49: pad | D49: 12 | E49: 180 | F49: 500
A50: twin | B50: pad | D50: 13 | E50: 260 | F50: 500
A51: fork | B51: path | C51: 1 | D51: 1 | E51: 180 | F51: -24
A52: fork | B52: path | C52: 1 | D52: 2 | E52: 180 | F52: 180
A53: fork | B53: path | C53: 1 | D53: 3 | E53: 60 | F53: 180
A54: fork | B54: path | C54: 1 | D54: 4 | E54: 60 | F54: 400
A55: fork | B55: path | C55: 1 | D55: 5 | E55: 140 | F55: 400
A56: fork | B56: path | C56: 1 | D56: 6 | E56: 140 | F56: 624
A57: fork | B57: path | C57: 2 | D57: 1 | E57: 180 | F57: -24
A58: fork | B58: path | C58: 2 | D58: 2 | E58: 180 | F58: 180
A59: fork | B59: path | C59: 2 | D59: 3 | E59: 300 | F59: 180
A60: fork | B60: path | C60: 2 | D60: 4 | E60: 300 | F60: 400
A61: fork | B61: path | C61: 2 | D61: 5 | E61: 220 | F61: 400
A62: fork | B62: path | C62: 2 | D62: 6 | E62: 220 | F62: 624
A63: fork | B63: pad | D63: 1 | E63: 100 | F63: 100
A64: fork | B64: pad | D64: 2 | E64: 260 | F64: 100
A65: fork | B65: pad | D65: 3 | E65: 20 | F65: 100
A66: fork | B66: pad | D66: 4 | E66: 340 | F66: 100
A67: fork | B67: pad | D67: 5 | E67: 180 | F67: 260
A68: fork | B68: pad | D68: 6 | E68: 180 | F68: 330
A69: fork | B69: pad | D69: 7 | E69: 100 | F69: 290
A70: fork | B70: pad | D70: 8 | E70: 260 | F70: 290
A71: fork | B71: pad | D71: 9 | E71: 180 | F71: 480
A72: fork | B72: pad | D72: 10 | E72: 60 | F72: 500
A73: fork | B73: pad | D73: 11 | E73: 300 | F73: 500
A74: fork | B74: pad | D74: 12 | E74: 180 | F74: 560
A75: merge | B75: path | C75: 1 | D75: 1 | E75: -24 | F75: 100
A76: merge | B76: path | C76: 1 | D76: 2 | E76: 120 | F76: 100
A77: merge | B77: path | C77: 1 | D77: 3 | E77: 120 | F77: 300
A78: merge | B78: path | C78: 1 | D78: 4 | E78: 180 | F78: 300
A79: merge | B79: path | C79: 1 | D79: 5 | E79: 180 | F79: 380
A80: merge | B80: path | C80: 1 | D80: 6 | E80: 60 | F80: 380
A81: merge | B81: path | C81: 1 | D81: 7 | E81: 60 | F81: 500
A82: merge | B82: path | C82: 1 | D82: 8 | E82: 300 | F82: 500
A83: merge | B83: path | C83: 1 | D83: 9 | E83: 300 | F83: 624
A84: merge | B84: path | C84: 2 | D84: 1 | E84: 384 | F84: 100
A85: merge | B85: path | C85: 2 | D85: 2 | E85: 240 | F85: 100
A86: merge | B86: path | C86: 2 | D86: 3 | E86: 240 | F86: 300
... A92: merge | B92: path | C92: 2 | D92: 9 | E92: 300 | F92: 624
A93: merge | B93: pad | D93: 1 | E93: 60 | F93: 200
A94: merge | B94: pad | D94: 2 | E94: 300 | F94: 200
A95: merge | B95: pad | D95: 3 | E95: 180 | F95: 200
A96: merge | B96: pad | D96: 4 | E96: 180 | F96: 40
A97: merge | B97: pad | D97: 5 | E97: 40 | F97: 40
A98: merge | B98: pad | D98: 6 | E98: 320 | F98: 40
A99: merge | B99: pad | D99: 7 | E99: 120 | F99: 440
A100: merge | B100: pad | D100: 8 | E100: 240 | F100: 440
A101: merge | B101: pad | D101: 9 | E101: 60 | F101: 300
A102: merge | B102: pad | D102: 10 | E102: 300 | F102: 300
A103: merge | B103: pad | D103: 11 | E103: 180 | F103: 560
A104: merge | B104: pad | D104: 12 | E104: 60 | F104: 570
A105: cross | B105: path | C105: 1 | D105: 1 | E105: 100 | F105: -24
A106: cross | B106: path | C106: 1 | D106: 2 | E106: 100 | F106: 200
...

Sheet 美术资源
A1: 资源编号（勿改） | B1: 类别 | C1: 说明 | D1: 优先级 | E1: 图片地址（https:// 链接，留空 = 用占位图） | F1: 游戏内宽 | G1: 游戏内高 | H1: 锚点 X（0–1） | I1: 锚点 Y（0–1） | J1: 帧数 | K1: 帧率 | L1: 盖住跑道（1/0，仅地图） | M1: 建议出图尺寸（3 倍，px）
A2: key | E2: src | F2: w | G2: h | H2: ax | I2: ay | J2: frames | K2: fps | L2: cover
A3: map.classic | B3: 地图 | C3: 蛇形跑道整张底图（草地、装饰；cover=1 时连跑道一起画，游戏就不再画跑道） | D3: P1 样板关 | F3: 360 | G3: 600 | H3: 0 | I3: 0 | J3: 1 | K3: 0 | L3: 0 | M3: =IF(J3>1,J3*F3*3&" × "&G3*3&"（"&J3&" 帧横排）",F3*3&" × "&G3*3)
A4: map.twin | B4: 地图 | C4: 双子跑道整张底图（草地、装饰；cover=1 时连跑道一起画，游戏就不再画跑道） | D4: P2 | F4: 360 | G4: 600 | H4: 0 | I4: 0 | J4: 1 | K4: 0 | L4: 0 | M4: =IF(J4>1,J4*F4*3&" × "&G4*3&"（"&J4&" 帧横排）",F4*3&" × "&G4*3)
A5: map.fork | B5: 地图 | C5: 分岔路口整张底图（草地、装饰；cover=1 时连跑道一起画，游戏就不再画跑道） | D5: P2 | F5: 360 | G5: 600 | H5: 0 | I5: 0 | J5: 1 | K5: 0 | L5: 0 | M5: =IF(J5>1,J5*F5*3&" × "&G5*3&"（"&J5&" 帧横排）",F5*3&" × "&G5*3)
A6: map.merge | B6: 地图 | C6: 汇流跑道整张底图（草地、装饰；cover=1 时连跑道一起画，游戏就不再画跑道） | D6: P2 | F6: 360 | G6: 600 | H6: 0 | I6: 0 | J6: 1 | K6: 0 | L6: 0 | M6: =IF(J6>1,J6*F6*3&" × "&G6*3&"（"&J6&" 帧横排）",F6*3&" × "&G6*3)
A7: map.cross | B7: 地图 | C7: 十字路口整张底图（草地、装饰；cover=1 时连跑道一起画，游戏就不再画跑道） | D7: P2 | F7: 360 | G7: 600 | H7: 0 | I7: 0 | J7: 1 | K7: 0 | L7: 0 | M7: =IF(J7>1,J7*F7*3&" × "&G7*3&"（"&J7&" 帧横排）",F7*3&" × "&G7*3)
A8: map.trident | B8: 地图 | C8: 三路汇聚整张底图（草地、装饰；cover=1 时连跑道一起画，游戏就不再画跑道） | D8: P2 | F8: 360 | G8: 600 | H8: 0 | I8: 0 | J8: 1 | K8: 0 | L8: 0 | M8: =IF(J8>1,J8*F8*3&" × "&G8*3&"（"&J8&" 帧横排）",F8*3&" × "&G8*3)
A9: tower.dart | B9: 装置 | C9: 易拉罐投手：操作员 + 道具，面朝右（朝左时游戏自动翻转），脚底对齐空位中心 | D9: P1 样板关 | F9: 40 | G9: 50 | H9: 0.5 | I9: 0.92 | J9: 1 | K9: 0 | L9: 0 | M9: =IF(J9>1,J9*F9*3&" × "&G9*3&"（"&J9&" 帧横排）",F9*3&" × "&G9*3)
A10: tower.bomb | B10: 装置 | C10: 香蕉皮投手：操作员 + 道具，面朝右（朝左时游戏自动翻转），脚底对齐空位中心 | D10: P1 样板关 | F10: 40 | G10: 50 | H10: 0.5 | I10: 0.92 | J10: 1 | K10: 0 | L10: 0 | M10: =IF(J10>1,J10*F10*3&" × "&G10*3&"（"&J10&" 帧横排）",F10*3&" × "&G10*3)
A11: tower.frost | B11: 装置 | C11: 洒水器：操作员 + 道具，面朝右（朝左时游戏自动翻转），脚底对齐空位中心 | D11: P2 | F11: 40 | G11: 50 | H11: 0.5 | I11: 0.92 | J11: 1 | K11: 0 | L11: 0 | M11: =IF(J11>1,J11*F11*3&" × "&G11*3&"（"&J11&" 帧横排）",F11*3&" × "&G11*3)
A12: tower.sniper | B12: 装置 | C12: 鞋盒无人机：操作员 + 道具，面朝右（朝左时游戏自动翻转），脚底对齐空位中心 | D12: P2 | F12: 40 | G12: 50 | H12: 0.5 | I12: 0.92 | J12: 1 | K12: 0 | L12: 0 | M12: =IF(J12>1,J12*F12*3&" × "&G12*3&"（"&J12&" 帧横排）",F12*3&" × "&G12*3)
A13: tower.tesla | B13: 装置 | C13: 广场舞音响：操作员 + 道具，面朝右（朝左时游戏自动翻转），脚底对齐空位中心 | D13: P2 | F13: 40 | G13: 50 | H13: 0.5 | I13: 0.92 | J13: 1 | K13: 0 | L13: 0 | M13: =IF(J13>1,J13*F13*3&" × "&G13*3&"（"&J13&" 帧横排）",F13*3&" × "&G13*3)
A14: tower.gem | B14: 装置 | C14: 宝石发射器：操作员 + 道具，面朝右（朝左时游戏自动翻转），脚底对齐空位中心 | D14: P2 | F14: 40 | G14: 50 | H14: 0.5 | I14: 0.92 | J14: 1 | K14: 0 | L14: 0 | M14: =IF(J14>1,J14*F14*3&" × "&G14*3&"（"&J14&" 帧横排）",F14*3&" × "&G14*3)
... A63: icon.score | B63: 界面图标 | C63: 顶栏「分数」图标 | D63: P2 | F63: 38 | G63: 38 | H63: 0.5 | I63: 0.5 | J63: 1 | K63: 0 | L63: 0 | M63: =IF(J63>1,J63*F63*3&" × "&G63*3&"（"&J63&" 帧横排）",F63*3&" × "&G63*3)
A65: ※ 图片地址填公开可访问的 https:// 链接（PNG / WebP，透明背景）；也可以不填，直接在游戏页面点「导入美术图片」，把文件名改成资源编号（如 tower.dart.png）一次选多张。
A66: ※ 游戏内宽高以 360 × 600 的画布为单位；出图按 3 倍像素（见最后一列），游戏会缩放到这里填的尺寸。
A67: ※ 锚点是图片里对齐游戏坐标的那一点：0,0 = 左上角，0.5,1 = 底边中点（跑者、装置用脚底中点）。
A68: ※ 帧数 > 1 时，图片是横向排开的序列帧（每帧等宽），按帧率循环播放。跑者、Boss 统一画成「侧面向右跑」，向左时游戏自动水平翻转。
A69: ※ 装置进化图（tower.xxx.p1–p3）在该路线升到 3 级以上并成为主路线时替换基础图；没给就继续用基础图。
A70: ※ 优先级：P1 样板关（先画这些就能完整玩一张图）→ P2 → P3。

Sheet 界面文字
A1: 原文（id，勿改） | B1: 中文 | C1: English | D1: Français
A2: key | B2: zh | C2: en | D2: fr
A3: +30%（满天赋） | B3: +30%（满天赋） | C3: +30% (max talents) | D3: +30 % (talents au max)
A4: 0%（新玩家） | B4: 0%（新玩家） | C4: 0% (new player) | D4: 0 % (nouveau joueur)
A5: 1× 速度 | B5: 1× 速度 | C5: 1× speed | D5: Vitesse 1×
A6: 2× 速度 | B6: 2× 速度 | C6: 2× speed | D6: Vitesse 2×
A7: 3 个 Boss 波每局从 6 位传奇跑者里随机抽：Nox（九命复活）、Aurum（召唤金甲跑者）、Slimo（黏液加速）、Rocco（铁头冲刺）、Chuckles（大笑让装置停工）、Datto（对常用装置产生抗性）。 | B7: 3 个 Boss 波每局从 6 位传奇跑者里随机抽：Nox（九命复活）、Aurum（召唤金甲跑者）、Slimo（黏液加速）、Rocco（铁头冲刺）、Chuckles（大笑让装置停工）、Datto（对常用装置产生抗性）。 | C7: Each run draws 3 bosses from 6 legendary runners: Nox (nine lives), Aurum (summons golden runners), Slimo (slime boost), Rocco (headstrong dash), Chuckles (laughter jams devices), Datto (adapts to your most-used device). | D7: Chaque partie tire 3 boss parmi 6 coureurs légendaires : Nox (neuf vies), Aurum (invoque des coureurs dorés), Slimo (bave accélérante), Rocco (charge tête baissée), Chuckles (son rire bloque les dispositifs), Datto (s’adapte à ton dispositif favori).
A8: 6 种装置：易拉罐投手（单体）、香蕉皮投手（范围滑倒）、洒水器（减速、冻结）、鞋盒无人机（全图空投）、广场舞音响（神曲连锁传播）、宝石发射器（红黄蓝三种宝石）。每种 3 条路线、每条 5 级；主路线可升满，次路线最多 2 级。 | B8: 6 种装置：易拉罐投手（单体）、香蕉皮投手（范围滑倒）、洒水器（减速、冻结）、鞋盒无人机（全图空投）、广场舞音响（神曲连锁传播）、宝石发射器（红黄蓝三种宝石）。每种 3 条路线、每条 5 级；主路线可升满，次路线最多 2 级。 | C8: 6 devices: Can Thrower (single target), Banana Peeler (area slip), Sprinkler (slow, freeze), Shoebox Drone (map-wide drop), Dance Speaker (chain earworm), Gem Launcher (ruby, topaz, sapphire). Each has 3 paths of 5 tiers; the main path can max out, the secondary stops at tier 2. | D8: 6 dispositifs : Lanceur de canettes (cible unique), Lanceur de peaux de banane (glissade de zone), Arroseur (ralentit, gèle), Drone à boîtes (largage sur toute la carte), Enceinte de danse (tube viral en chaîne), Lance-gemmes (rubis, topaze, saphir). Chacun a 3 voies de 5 niveaux ; la voie principale peut être maximisée, la secondaire s’arrête au niveau 2.
A9: Boss 波 | B9: Boss 波 | C9: Boss wave | D9: Vague de boss
A10: Boss：{n}（{t}） | B10: Boss：{n}（{t}） | C10: Boss: {n} ({t}) | D10: Boss : {n} ({t})
A11: Nox 九命 | B11: Nox 九命 | C11: Nox: Nine Lives | D11: Nox : neuf vies
A12: {n} 名跑者 | B12: {n} 名跑者 | C12: {n} runners | D12: {n} coureurs
... A282: 对{x}无效 | B282: 对{x}无效 | C282: No effect on {x} | D282: Sans effet sur {x}
A284: ※ 花括号里的 {n}、{x} 等是占位符，翻译时要原样保留。

Sheet 效果语法
A1: 写法 / 属性 | B1: 说明
A3: 写法 | B3: 多个效果用分号隔开，例如：dmg+=2; armor=1
A4: += | B4: 增加：dmg+=1
A5: *= | B5: 乘以：rate*=0.8（出手间隔 ×0.8，即变快 20%）
A6: = | B6: 设为：stun=0.6
A7: >= | B7: 至少为：armor>=0.6
A9: 属性 | B9: 含义
A10: dmg | B10: 效果（伤害）
A11: rate | B11: 出手间隔（秒，越小越快）
A12: range | B12: 射程
A13: rad | B13: 香蕉皮范围半径
A14: slow | B14: 减速比例
... A54: heat | B54: 矿机热风每秒效果

Sheet 数值体检·波次
A1: 波次 | B1: 总人数 | C1: 有效总体力 | D1: 本波劝退可得 GST | E1: 开打前累计可用 GST | F1: 预计时长（秒） | G1: 需要的输出（HP/秒） | H1: 预计可用输出（HP/秒） | I1: 压力系数 = 需要 ÷ 可用 | J1: 较上一波
M2: 假设参数（蓝字可改）
A3: =波次!A3 | B3: =波次!M3 | C3: =波次!B3*波次!D3+波次!C3*波次!E3*$N$3+波次!F3*波次!G3+(波次!I3*INDEX(全局!$B:$B,MATCH("hpRain",全局!$A:$A,0))+波次!J3*INDEX(全局!$B:$B,MATCH("hpHop",全局!$A:$A,0))+波次!K3*INDEX(全局!$B:$B,MATCH("hpPhones",全局!$A:$A,0)))*波次!D3+波次!L3*波次!E3*INDEX(全局!$B:$B,MATCH("hpWhale",全局!$A:$A,0))*$N$4 | D3: =波次!B3*INDEX(敌人!$G:$G,MATCH("norm",敌人!$A:$A,0))+波次!C3*INDEX(敌人!$G:$G,MATCH("arm",敌人!$A:$A,0))+波次!F3*INDEX(敌人!$G:$G,MATCH("boss",敌人!$A:$A,0))+波次!I3*INDEX(敌人!$G:$G,MATCH("rain",敌人!$A:$A,0))+波次!J3*INDEX(敌人!$G:$G,MATCH("hop",敌人!$A:$A,0))+波次!K3*INDEX(敌人!$G:$G,MATCH("phones",敌人!$A:$A,0))+波次!L3*INDEX(敌人!$G:$G,MATCH("whale",敌人!$A:$A,0)) | E3: =INDEX(全局!$B:$B,MATCH("startGold",全局!$A:$A,0)) | F3: =B3*MAX(INDEX(全局!$B:$B,MATCH("spawnMin",全局!$A:$A,0)),INDEX(全局!$B:$B,MATCH("spawnBase",全局!$A:$A,0))-A3*INDEX(全局!$B:$B,MATCH("spawnPerWave",全局!$A:$A,0)))+$N$5/$N$6 | G3: =C3/F3 | H3: =E3*$N$7 | I3: =G3/H3 | M3: 耐力跑者体力折算 | N3: 1.6 | O3: 耐力跑者对大多数装置有减免，按 ×1.6 算有效体力
A4: =波次!A4 | B4: =波次!M4 | C4: =波次!B4*波次!D4+波次!C4*波次!E4*$N$3+波次!F4*波次!G4+(波次!I4*INDEX(全局!$B:$B,MATCH("hpRain",全局!$A:$A,0))+波次!J4*INDEX(全局!$B:$B,MATCH("hpHop",全局!$A:$A,0))+波次!K4*INDEX(全局!$B:$B,MATCH("hpPhones",全局!$A:$A,0)))*波次!D4+波次!L4*波次!E4*INDEX(全局!$B:$B,MATCH("hpWhale",全局!$A:$A,0))*$N$4 | D4: =波次!B4*INDEX(敌人!$G:$G,MATCH("norm",敌人!$A:$A,0))+波次!C4*INDEX(敌人!$G:$G,MATCH("arm",敌人!$A:$A,0))+波次!F4*INDEX(敌人!$G:$G,MATCH("boss",敌人!$A:$A,0))+波次!I4*INDEX(敌人!$G:$G,MATCH("rain",敌人!$A:$A,0))+波次!J4*INDEX(敌人!$G:$G,MATCH("hop",敌人!$A:$A,0))+波次!K4*INDEX(敌人!$G:$G,MATCH("phones",敌人!$A:$A,0))+波次!L4*INDEX(敌人!$G:$G,MATCH("whale",敌人!$A:$A,0)) | E4: =E3+D3+INDEX(全局!$B:$B,MATCH("waveReward",全局!$A:$A,0)) | F4: =B4*MAX(INDEX(全局!$B:$B,MATCH("spawnMin",全局!$A:$A,0)),INDEX(全局!$B:$B,MATCH("spawnBase",全局!$A:$A,0))-A4*INDEX(全局!$B:$B,MATCH("spawnPerWave",全局!$A:$A,0)))+$N$5/$N$6 | G4: =C4/F4 | H4: =E4*$N$7 | I4: =G4/H4 | J4: =I4/I3-1 | M4: 巨鲸体力折算 | N4: 1.5 | O4: 巨鲸削弱小伤害，按 ×1.5 算有效体力
A5: =波次!A5 | B5: =波次!M5 | C5: =波次!B5*波次!D5+波次!C5*波次!E5*$N$3+波次!F5*波次!G5+(波次!I5*INDEX(全局!$B:$B,MATCH("hpRain",全局!$A:$A,0))+波次!J5*INDEX(全局!$B:$B,MATCH("hpHop",全局!$A:$A,0))+波次!K5*INDEX(全局!$B:$B,MATCH("hpPhones",全局!$A:$A,0)))*波次!D5+波次!L5*波次!E5*INDEX(全局!$B:$B,MATCH("hpWhale",全局!$A:$A,0))*$N$4 | D5: =波次!B5*INDEX(敌人!$G:$G,MATCH("norm",敌人!$A:$A,0))+波次!C5*INDEX(敌人!$G:$G,MATCH("arm",敌人!$A:$A,0))+波次!F5*INDEX(敌人!$G:$G,MATCH("boss",敌人!$A:$A,0))+波次!I5*INDEX(敌人!$G:$G,MATCH("rain",敌人!$A:$A,0))+波次!J5*INDEX(敌人!$G:$G,MATCH("hop",敌人!$A:$A,0))+波次!K5*INDEX(敌人!$G:$G,MATCH("phones",敌人!$A:$A,0))+波次!L5*INDEX(敌人!$G:$G,MATCH("whale",敌人!$A:$A,0)) | E5: =E4+D4+INDEX(全局!$B:$B,MATCH("waveReward",全局!$A:$A,0)) | F5: =B5*MAX(INDEX(全局!$B:$B,MATCH("spawnMin",全局!$A:$A,0)),INDEX(全局!$B:$B,MATCH("spawnBase",全局!$A:$A,0))-A5*INDEX(全局!$B:$B,MATCH("spawnPerWave",全局!$A:$A,0)))+$N$5/$N$6 | G5: =C5/F5 | H5: =E5*$N$7 | I5: =G5/H5 | J5: =I5/I4-1 | M5: 跑道长度（像素） | N5: 1500 | O5: 经典跑道大约 1500
A6: =波次!A6 | B6: =波次!M6 | C6: =波次!B6*波次!D6+波次!C6*波次!E6*$N$3+波次!F6*波次!G6+(波次!I6*INDEX(全局!$B:$B,MATCH("hpRain",全局!$A:$A,0))+波次!J6*INDEX(全局!$B:$B,MATCH("hpHop",全局!$A:$A,0))+波次!K6*INDEX(全局!$B:$B,MATCH("hpPhones",全局!$A:$A,0)))*波次!D6+波次!L6*波次!E6*INDEX(全局!$B:$B,MATCH("hpWhale",全局!$A:$A,0))*$N$4 | D6: =波次!B6*INDEX(敌人!$G:$G,MATCH("norm",敌人!$A:$A,0))+波次!C6*INDEX(敌人!$G:$G,MATCH("arm",敌人!$A:$A,0))+波次!F6*INDEX(敌人!$G:$G,MATCH("boss",敌人!$A:$A,0))+波次!I6*INDEX(敌人!$G:$G,MATCH("rain",敌人!$A:$A,0))+波次!J6*INDEX(敌人!$G:$G,MATCH("hop",敌人!$A:$A,0))+波次!K6*INDEX(敌人!$G:$G,MATCH("phones",敌人!$A:$A,0))+波次!L6*INDEX(敌人!$G:$G,MATCH("whale",敌人!$A:$A,0)) | E6: =E5+D5+INDEX(全局!$B:$B,MATCH("waveReward",全局!$A:$A,0)) | F6: =B6*MAX(INDEX(全局!$B:$B,MATCH("spawnMin",全局!$A:$A,0)),INDEX(全局!$B:$B,MATCH("spawnBase",全局!$A:$A,0))-A6*INDEX(全局!$B:$B,MATCH("spawnPerWave",全局!$A:$A,0)))+$N$5/$N$6 | G6: =C6/F6 | H6: =E6*$N$7 | I6: =G6/H6 | J6: =I6/I5-1 | M6: 平均移速 | N6: =INDEX(敌人!$F:$F,MATCH("norm",敌人!$A:$A,0)) | O6: 取慢跑者移速
A7: =波次!A7 | B7: =波次!M7 | C7: =波次!B7*波次!D7+波次!C7*波次!E7*$N$3+波次!F7*波次!G7+(波次!I7*INDEX(全局!$B:$B,MATCH("hpRain",全局!$A:$A,0))+波次!J7*INDEX(全局!$B:$B,MATCH("hpHop",全局!$A:$A,0))+波次!K7*INDEX(全局!$B:$B,MATCH("hpPhones",全局!$A:$A,0)))*波次!D7+波次!L7*波次!E7*INDEX(全局!$B:$B,MATCH("hpWhale",全局!$A:$A,0))*$N$4 | D7: =波次!B7*INDEX(敌人!$G:$G,MATCH("norm",敌人!$A:$A,0))+波次!C7*INDEX(敌人!$G:$G,MATCH("arm",敌人!$A:$A,0))+波次!F7*INDEX(敌人!$G:$G,MATCH("boss",敌人!$A:$A,0))+波次!I7*INDEX(敌人!$G:$G,MATCH("rain",敌人!$A:$A,0))+波次!J7*INDEX(敌人!$G:$G,MATCH("hop",敌人!$A:$A,0))+波次!K7*INDEX(敌人!$G:$G,MATCH("phones",敌人!$A:$A,0))+波次!L7*INDEX(敌人!$G:$G,MATCH("whale",敌人!$A:$A,0)) | E7: =E6+D6+INDEX(全局!$B:$B,MATCH("waveReward",全局!$A:$A,0)) | F7: =B7*MAX(INDEX(全局!$B:$B,MATCH("spawnMin",全局!$A:$A,0)),INDEX(全局!$B:$B,MATCH("spawnBase",全局!$A:$A,0))-A7*INDEX(全局!$B:$B,MATCH("spawnPerWave",全局!$A:$A,0)))+$N$5/$N$6 | G7: =C7/F7 | H7: =E7*$N$7 | I7: =G7/H7 | J7: =I7/I6-1 | M7: 每 GST 可换来的输出（HP/秒） | N7: 0.025 | O7: 用「数值体检·装置」里基础装置的平均值粗估；投入越多、越靠后的升级越不划算
A8: =波次!A8 | B8: =波次!M8 | C8: =波次!B8*波次!D8+波次!C8*波次!E8*$N$3+波次!F8*波次!G8+(波次!I8*INDEX(全局!$B:$B,MATCH("hpRain",全局!$A:$A,0))+波次!J8*INDEX(全局!$B:$B,MATCH("hpHop",全局!$A:$A,0))+波次!K8*INDEX(全局!$B:$B,MATCH("hpPhones",全局!$A:$A,0)))*波次!D8+波次!L8*波次!E8*INDEX(全局!$B:$B,MATCH("hpWhale",全局!$A:$A,0))*$N$4 | D8: =波次!B8*INDEX(敌人!$G:$G,MATCH("norm",敌人!$A:$A,0))+波次!C8*INDEX(敌人!$G:$G,MATCH("arm",敌人!$A:$A,0))+波次!F8*INDEX(敌人!$G:$G,MATCH("boss",敌人!$A:$A,0))+波次!I8*INDEX(敌人!$G:$G,MATCH("rain",敌人!$A:$A,0))+波次!J8*INDEX(敌人!$G:$G,MATCH("hop",敌人!$A:$A,0))+波次!K8*INDEX(敌人!$G:$G,MATCH("phones",敌人!$A:$A,0))+波次!L8*INDEX(敌人!$G:$G,MATCH("whale",敌人!$A:$A,0)) | E8: =E7+D7+INDEX(全局!$B:$B,MATCH("waveReward",全局!$A:$A,0)) | F8: =B8*MAX(INDEX(全局!$B:$B,MATCH("spawnMin",全局!$A:$A,0)),INDEX(全局!$B:$B,MATCH("spawnBase",全局!$A:$A,0))-A8*INDEX(全局!$B:$B,MATCH("spawnPerWave",全局!$A:$A,0)))+$N$5/$N$6 | G8: =C8/F8 | H8: =E8*$N$7 | I8: =G8/H8 | J8: =I8/I7-1 | M8: 压力系数：上限 | N8: 0.85 | O8: 超过就标红（按机器人实测校准：现有 15 波在 1.4 倍体力下仍能通关）
A9: =波次!A9 | B9: =波次!M9 | C9: =波次!B9*波次!D9+波次!C9*波次!E9*$N$3+波次!F9*波次!G9+(波次!I9*INDEX(全局!$B:$B,MATCH("hpRain",全局!$A:$A,0))+波次!J9*INDEX(全局!$B:$B,MATCH("hpHop",全局!$A:$A,0))+波次!K9*INDEX(全局!$B:$B,MATCH("hpPhones",全局!$A:$A,0)))*波次!D9+波次!L9*波次!E9*INDEX(全局!$B:$B,MATCH("hpWhale",全局!$A:$A,0))*$N$4 | D9: =波次!B9*INDEX(敌人!$G:$G,MATCH("norm",敌人!$A:$A,0))+波次!C9*INDEX(敌人!$G:$G,MATCH("arm",敌人!$A:$A,0))+波次!F9*INDEX(敌人!$G:$G,MATCH("boss",敌人!$A:$A,0))+波次!I9*INDEX(敌人!$G:$G,MATCH("rain",敌人!$A:$A,0))+波次!J9*INDEX(敌人!$G:$G,MATCH("hop",敌人!$A:$A,0))+波次!K9*INDEX(敌人!$G:$G,MATCH("phones",敌人!$A:$A,0))+波次!L9*INDEX(敌人!$G:$G,MATCH("whale",敌人!$A:$A,0)) | E9: =E8+D8+INDEX(全局!$B:$B,MATCH("waveReward",全局!$A:$A,0)) | F9: =B9*MAX(INDEX(全局!$B:$B,MATCH("spawnMin",全局!$A:$A,0)),INDEX(全局!$B:$B,MATCH("spawnBase",全局!$A:$A,0))-A9*INDEX(全局!$B:$B,MATCH("spawnPerWave",全局!$A:$A,0)))+$N$5/$N$6 | G9: =C9/F9 | H9: =E9*$N$7 | I9: =G9/H9 | J9: =I9/I8-1 | M9: 压力系数：下限 | N9: 0.25 | O9: 低于就标黄，太轻松
A10: =波次!A10 | B10: =波次!M10 | C10: =波次!B10*波次!D10+波次!C10*波次!E10*$N$3+波次!F10*波次!G10+(波次!I10*INDEX(全局!$B:$B,MATCH("hpRain",全局!$A:$A,0))+波次!J10*INDEX(全局!$B:$B,MATCH("hpHop",全局!$A:$A,0))+波次!K10*INDEX(全局!$B:$B,MATCH("hpPhones",全局!$A:$A,0)))*波次!D10+波次!L10*波次!E10*INDEX(全局!$B:$B,MATCH("hpWhale",全局!$A:$A,0))*$N$4 | D10: =波次!B10*INDEX(敌人!$G:$G,MATCH("norm",敌人!$A:$A,0))+波次!C10*INDEX(敌人!$G:$G,MATCH("arm",敌人!$A:$A,0))+波次!F10*INDEX(敌人!$G:$G,MATCH("boss",敌人!$A:$A,0))+波次!I10*INDEX(敌人!$G:$G,MATCH("rain",敌人!$A:$A,0))+波次!J10*INDEX(敌人!$G:$G,MATCH("hop",敌人!$A:$A,0))+波次!K10*INDEX(敌人!$G:$G,MATCH("phones",敌人!$A:$A,0))+波次!L10*INDEX(敌人!$G:$G,MATCH("whale",敌人!$A:$A,0)) | E10: =E9+D9+INDEX(全局!$B:$B,MATCH("waveReward",全局!$A:$A,0)) | F10: =B10*MAX(INDEX(全局!$B:$B,MATCH("spawnMin",全局!$A:$A,0)),INDEX(全局!$B:$B,MATCH("spawnBase",全局!$A:$A,0))-A10*INDEX(全局!$B:$B,MATCH("spawnPerWave",全局!$A:$A,0)))+$N$5/$N$6 | G10: =C10/F10 | H10: =E10*$N$7 | I10: =G10/H10 | J10: =I10/I9-1
A11: =波次!A11 | B11: =波次!M11 | C11: =波次!B11*波次!D11+波次!C11*波次!E11*$N$3+波次!F11*波次!G11+(波次!I11*INDEX(全局!$B:$B,MATCH("hpRain",全局!$A:$A,0))+波次!J11*INDEX(全局!$B:$B,MATCH("hpHop",全局!$A:$A,0))+波次!K11*INDEX(全局!$B:$B,MATCH("hpPhones",全局!$A:$A,0)))*波次!D11+波次!L11*波次!E11*INDEX(全局!$B:$B,MATCH("hpWhale",全局!$A:$A,0))*$N$4 | D11: =波次!B11*INDEX(敌人!$G:$G,MATCH("norm",敌人!$A:$A,0))+波次!C11*INDEX(敌人!$G:$G,MATCH("arm",敌人!$A:$A,0))+波次!F11*INDEX(敌人!$G:$G,MATCH("boss",敌人!$A:$A,0))+波次!I11*INDEX(敌人!$G:$G,MATCH("rain",敌人!$A:$A,0))+波次!J11*INDEX(敌人!$G:$G,MATCH("hop",敌人!$A:$A,0))+波次!K11*INDEX(敌人!$G:$G,MATCH("phones",敌人!$A:$A,0))+波次!L11*INDEX(敌人!$G:$G,MATCH("whale",敌人!$A:$A,0)) | E11: =E10+D10+INDEX(全局!$B:$B,MATCH("waveReward",全局!$A:$A,0)) | F11: =B11*MAX(INDEX(全局!$B:$B,MATCH("spawnMin",全局!$A:$A,0)),INDEX(全局!$B:$B,MATCH("spawnBase",全局!$A:$A,0))-A11*INDEX(全局!$B:$B,MATCH("spawnPerWave",全局!$A:$A,0)))+$N$5/$N$6 | G11: =C11/F11 | H11: =E11*$N$7 | I11: =G11/H11 | J11: =I11/I10-1
A12: =波次!A12 | B12: =波次!M12 | C12: =波次!B12*波次!D12+波次!C12*波次!E12*$N$3+波次!F12*波次!G12+(波次!I12*INDEX(全局!$B:$B,MATCH("hpRain",全局!$A:$A,0))+波次!J12*INDEX(全局!$B:$B,MATCH("hpHop",全局!$A:$A,0))+波次!K12*INDEX(全局!$B:$B,MATCH("hpPhones",全局!$A:$A,0)))*波次!D12+波次!L12*波次!E12*INDEX(全局!$B:$B,MATCH("hpWhale",全局!$A:$A,0))*$N$4 | D12: =波次!B12*INDEX(敌人!$G:$G,MATCH("norm",敌人!$A:$A,0))+波次!C12*INDEX(敌人!$G:$G,MATCH("arm",敌人!$A:$A,0))+波次!F12*INDEX(敌人!$G:$G,MATCH("boss",敌人!$A:$A,0))+波次!I12*INDEX(敌人!$G:$G,MATCH("rain",敌人!$A:$A,0))+波次!J12*INDEX(敌人!$G:$G,MATCH("hop",敌人!$A:$A,0))+波次!K12*INDEX(敌人!$G:$G,MATCH("phones",敌人!$A:$A,0))+波次!L12*INDEX(敌人!$G:$G,MATCH("whale",敌人!$A:$A,0)) | E12: =E11+D11+INDEX(全局!$B:$B,MATCH("waveReward",全局!$A:$A,0)) | F12: =B12*MAX(INDEX(全局!$B:$B,MATCH("spawnMin",全局!$A:$A,0)),INDEX(全局!$B:$B,MATCH("spawnBase",全局!$A:$A,0))-A12*INDEX(全局!$B:$B,MATCH("spawnPerWave",全局!$A:$A,0)))+$N$5/$N$6 | G12: =C12/F12 | H12: =E12*$N$7 | I12: =G12/H12 | J12: =I12/I11-1
A13: =波次!A13 | B13: =波次!M13 | C13: =波次!B13*波次!D13+波次!C13*波次!E13*$N$3+波次!F13*波次!G13+(波次!I13*INDEX(全局!$B:$B,MATCH("hpRain",全局!$A:$A,0))+波次!J13*INDEX(全局!$B:$B,MATCH("hpHop",全局!$A:$A,0))+波次!K13*INDEX(全局!$B:$B,MATCH("hpPhones",全局!$A:$A,0)))*波次!D13+波次!L13*波次!E13*INDEX(全局!$B:$B,MATCH("hpWhale",全局!$A:$A,0))*$N$4 | D13: =波次!B13*INDEX(敌人!$G:$G,MATCH("norm",敌人!$A:$A,0))+波次!C13*INDEX(敌人!$G:$G,MATCH("arm",敌人!$A:$A,0))+波次!F13*INDEX(敌人!$G:$G,MATCH("boss",敌人!$A:$A,0))+波次!I13*INDEX(敌人!$G:$G,MATCH("rain",敌人!$A:$A,0))+波次!J13*INDEX(敌人!$G:$G,MATCH("hop",敌人!$A:$A,0))+波次!K13*INDEX(敌人!$G:$G,MATCH("phones",敌人!$A:$A,0))+波次!L13*INDEX(敌人!$G:$G,MATCH("whale",敌人!$A:$A,0)) | E13: =E12+D12+INDEX(全局!$B:$B,MATCH("waveReward",全局!$A:$A,0)) | F13: =B13*MAX(INDEX(全局!$B:$B,MATCH("spawnMin",全局!$A:$A,0)),INDEX(全局!$B:$B,MATCH("spawnBase",全局!$A:$A,0))-A13*INDEX(全局!$B:$B,MATCH("spawnPerWave",全局!$A:$A,0)))+$N$5/$N$6 | G13: =C13/F13 | H13: =E13*$N$7 | I13: =G13/H13 | J13: =I13/I12-1
A14: =波次!A14 | B14: =波次!M14 | C14: =波次!B14*波次!D14+波次!C14*波次!E14*$N$3+波次!F14*波次!G14+(波次!I14*INDEX(全局!$B:$B,MATCH("hpRain",全局!$A:$A,0))+波次!J14*INDEX(全局!$B:$B,MATCH("hpHop",全局!$A:$A,0))+波次!K14*INDEX(全局!$B:$B,MATCH("hpPhones",全局!$A:$A,0)))*波次!D14+波次!L14*波次!E14*INDEX(全局!$B:$B,MATCH("hpWhale",全局!$A:$A,0))*$N$4 | D14: =波次!B14*INDEX(敌人!$G:$G,MATCH("norm",敌人!$A:$A,0))+波次!C14*INDEX(敌人!$G:$G,MATCH("arm",敌人!$A:$A,0))+波次!F14*INDEX(敌人!$G:$G,MATCH("boss",敌人!$A:$A,0))+波次!I14*INDEX(敌人!$G:$G,MATCH("rain",敌人!$A:$A,0))+波次!J14*INDEX(敌人!$G:$G,MATCH("hop",敌人!$A:$A,0))+波次!K14*INDEX(敌人!$G:$G,MATCH("phones",敌人!$A:$A,0))+波次!L14*INDEX(敌人!$G:$G,MATCH("whale",敌人!$A:$A,0)) | E14: =E13+D13+INDEX(全局!$B:$B,MATCH("waveReward",全局!$A:$A,0)) | F14: =B14*MAX(INDEX(全局!$B:$B,MATCH("spawnMin",全局!$A:$A,0)),INDEX(全局!$B:$B,MATCH("spawnBase",全局!$A:$A,0))-A14*INDEX(全局!$B:$B,MATCH("spawnPerWave",全局!$A:$A,0)))+$N$5/$N$6 | G14: =C14/F14 | H14: =E14*$N$7 | I14: =G14/H14 | J14: =I14/I13-1
A15: =波次!A15 | B15: =波次!M15 | C15: =波次!B15*波次!D15+波次!C15*波次!E15*$N$3+波次!F15*波次!G15+(波次!I15*INDEX(全局!$B:$B,MATCH("hpRain",全局!$A:$A,0))+波次!J15*INDEX(全局!$B:$B,MATCH("hpHop",全局!$A:$A,0))+波次!K15*INDEX(全局!$B:$B,MATCH("hpPhones",全局!$A:$A,0)))*波次!D15+波次!L15*波次!E15*INDEX(全局!$B:$B,MATCH("hpWhale",全局!$A:$A,0))*$N$4 | D15: =波次!B15*INDEX(敌人!$G:$G,MATCH("norm",敌人!$A:$A,0))+波次!C15*INDEX(敌人!$G:$G,MATCH("arm",敌人!$A:$A,0))+波次!F15*INDEX(敌人!$G:$G,MATCH("boss",敌人!$A:$A,0))+波次!I15*INDEX(敌人!$G:$G,MATCH("rain",敌人!$A:$A,0))+波次!J15*INDEX(敌人!$G:$G,MATCH("hop",敌人!$A:$A,0))+波次!K15*INDEX(敌人!$G:$G,MATCH("phones",敌人!$A:$A,0))+波次!L15*INDEX(敌人!$G:$G,MATCH("whale",敌人!$A:$A,0)) | E15: =E14+D14+INDEX(全局!$B:$B,MATCH("waveReward",全局!$A:$A,0)) | F15: =B15*MAX(INDEX(全局!$B:$B,MATCH("spawnMin",全局!$A:$A,0)),INDEX(全局!$B:$B,MATCH("spawnBase",全局!$A:$A,0))-A15*INDEX(全局!$B:$B,MATCH("spawnPerWave",全局!$A:$A,0)))+$N$5/$N$6 | G15: =C15/F15 | H15: =E15*$N$7 | I15: =G15/H15 | J15: =I15/I14-1
A16: =波次!A16 | B16: =波次!M16 | C16: =波次!B16*波次!D16+波次!C16*波次!E16*$N$3+波次!F16*波次!G16+(波次!I16*INDEX(全局!$B:$B,MATCH("hpRain",全局!$A:$A,0))+波次!J16*INDEX(全局!$B:$B,MATCH("hpHop",全局!$A:$A,0))+波次!K16*INDEX(全局!$B:$B,MATCH("hpPhones",全局!$A:$A,0)))*波次!D16+波次!L16*波次!E16*INDEX(全局!$B:$B,MATCH("hpWhale",全局!$A:$A,0))*$N$4 | D16: =波次!B16*INDEX(敌人!$G:$G,MATCH("norm",敌人!$A:$A,0))+波次!C16*INDEX(敌人!$G:$G,MATCH("arm",敌人!$A:$A,0))+波次!F16*INDEX(敌人!$G:$G,MATCH("boss",敌人!$A:$A,0))+波次!I16*INDEX(敌人!$G:$G,MATCH("rain",敌人!$A:$A,0))+波次!J16*INDEX(敌人!$G:$G,MATCH("hop",敌人!$A:$A,0))+波次!K16*INDEX(敌人!$G:$G,MATCH("phones",敌人!$A:$A,0))+波次!L16*INDEX(敌人!$G:$G,MATCH("whale",敌人!$A:$A,0)) | E16: =E15+D15+INDEX(全局!$B:$B,MATCH("waveReward",全局!$A:$A,0)) | F16: =B16*MAX(INDEX(全局!$B:$B,MATCH("spawnMin",全局!$A:$A,0)),INDEX(全局!$B:$B,MATCH("spawnBase",全局!$A:$A,0))-A16*INDEX(全局!$B:$B,MATCH("spawnPerWave",全局!$A:$A,0)))+$N$5/$N$6 | G16: =C16/F16 | H16: =E16*$N$7 | I16: =G16/H16 | J16: =I16/I15-1
A17: =波次!A17 | B17: =波次!M17 | C17: =波次!B17*波次!D17+波次!C17*波次!E17*$N$3+波次!F17*波次!G17+(波次!I17*INDEX(全局!$B:$B,MATCH("hpRain",全局!$A:$A,0))+波次!J17*INDEX(全局!$B:$B,MATCH("hpHop",全局!$A:$A,0))+波次!K17*INDEX(全局!$B:$B,MATCH("hpPhones",全局!$A:$A,0)))*波次!D17+波次!L17*波次!E17*INDEX(全局!$B:$B,MATCH("hpWhale",全局!$A:$A,0))*$N$4 | D17: =波次!B17*INDEX(敌人!$G:$G,MATCH("norm",敌人!$A:$A,0))+波次!C17*INDEX(敌人!$G:$G,MATCH("arm",敌人!$A:$A,0))+波次!F17*INDEX(敌人!$G:$G,MATCH("boss",敌人!$A:$A,0))+波次!I17*INDEX(敌人!$G:$G,MATCH("rain",敌人!$A:$A,0))+波次!J17*INDEX(敌人!$G:$G,MATCH("hop",敌人!$A:$A,0))+波次!K17*INDEX(敌人!$G:$G,MATCH("phones",敌人!$A:$A,0))+波次!L17*INDEX(敌人!$G:$G,MATCH("whale",敌人!$A:$A,0)) | E17: =E16+D16+INDEX(全局!$B:$B,MATCH("waveReward",全局!$A:$A,0)) | F17: =B17*MAX(INDEX(全局!$B:$B,MATCH("spawnMin",全局!$A:$A,0)),INDEX(全局!$B:$B,MATCH("spawnBase",全局!$A:$A,0))-A17*INDEX(全局!$B:$B,MATCH("spawnPerWave",全局!$A:$A,0)))+$N$5/$N$6 | G17: =C17/F17 | H17: =E17*$N$7 | I17: =G17/H17 | J17: =I17/I16-1
A19: 怎么看：压力系数 = 这一波需要的输出 ÷ 按累计 GST 估出来的可用输出。绿色在目标区间，红色太难，黄色太轻松。
A20: 理想曲线：前几波偏低让玩家站稳，之后缓慢上升；「较上一波」超过 +30% 会标红，代表难度突然跳一大截。
A21: 这是粗估：没算神秘箱卡牌、组合和矿机，所以只看相对走势，不看绝对值。改了「波次」「敌人」「全局」表，这里会自动重算。

Sheet 数值体检·装置
A1: 装置 | B1: 路线（0=基础） | C1: 等级 | D1: 名称 | E1: 本级价格 | F1: 累计花费 | G1: 估算输出（HP/秒） | H1: 每 100 GST 输出 | I1: 比同价多买基础塔（估算） | J1: 本级边际性价比 | K1: 实测：本配置清除体力比例 | L1: 实测：同价基础塔清除比例 | M1: 实测比值 | N1: 功能型效果 | O1: 结论
A3: dart | B3: 0 | C3: 0 | D3: 基础 | E3: 100 | F3: 100 | G3: 2.24 | H3: =G3/F3*100 | I3: =IFERROR((G3/F3)/(SUMIFS($G$3:$G$98,$A$3:$A$98,A3,$B$3:$B$98,0)/SUMIFS($F$3:$F$98,$A$3:$A$98,A3,$B$3:$B$98,0)),"") | J3: =IF(B3=0,1,IF(C3<=1,G3-SUMIFS($G$3:$G$98,$A$3:$A$98,A3,$B$3:$B$98,0),G3-G2)/E3/(SUMIFS($G$3:$G$98,$A$3:$A$98,A3,$B$3:$B$98,0)/SUMIFS($F$3:$F$98,$A$3:$A$98,A3,$B$3:$B$98,0))) | M3: =IF(OR(K3="",L3="",L3=0),"",K3/L3) | O3: =IF(B3=0,"基准",IF(AND(N3<>"",I3<0.85),"功能型：单看输出偏低属正常",IF(I3>=0.85,"划算",IF(I3>=0.65,"略亏：空位紧张时仍值得","偏亏：建议降价或加强"))))
A4: dart | B4: 1 | C4: 1 | D4: 加料汽水罐 | E4: 70 | F4: 170 | G4: 4.48 | H4: =G4/F4*100 | I4: =IFERROR((G4/F4)/(SUMIFS($G$3:$G$98,$A$3:$A$98,A4,$B$3:$B$98,0)/SUMIFS($F$3:$F$98,$A$3:$A$98,A4,$B$3:$B$98,0)),"") | J4: =IF(B4=0,1,IF(C4<=1,G4-SUMIFS($G$3:$G$98,$A$3:$A$98,A4,$B$3:$B$98,0),G4-G3)/E4/(SUMIFS($G$3:$G$98,$A$3:$A$98,A4,$B$3:$B$98,0)/SUMIFS($F$3:$F$98,$A$3:$A$98,A4,$B$3:$B$98,0))) | K4: 0.449 | L4: 0.36 | M4: =IF(OR(K4="",L4="",L4=0),"",K4/L4) | O4: =IF(B4=0,"基准",IF(AND(N4<>"",I4<0.85),"功能型：单看输出偏低属正常",IF(I4>=0.85,"划算",IF(I4>=0.65,"略亏：空位紧张时仍值得","偏亏：建议降价或加强"))))
A5: dart | B5: 1 | C5: 2 | D5: 铁皮罐 | E5: 120 | F5: 290 | G5: 4.48 | H5: =G5/F5*100 | I5: =IFERROR((G5/F5)/(SUMIFS($G$3:$G$98,$A$3:$A$98,A5,$B$3:$B$98,0)/SUMIFS($F$3:$F$98,$A$3:$A$98,A5,$B$3:$B$98,0)),"") | J5: =IF(B5=0,1,IF(C5<=1,G5-SUMIFS($G$3:$G$98,$A$3:$A$98,A5,$B$3:$B$98,0),G5-G4)/E5/(SUMIFS($G$3:$G$98,$A$3:$A$98,A5,$B$3:$B$98,0)/SUMIFS($F$3:$F$98,$A$3:$A$98,A5,$B$3:$B$98,0))) | K5: 0.456 | L5: 0.565 | M5: =IF(OR(K5="",L5="",L5=0),"",K5/L5) | N5: 破甲 | O5: =IF(B5=0,"基准",IF(AND(N5<>"",I5<0.85),"功能型：单看输出偏低属正常",IF(I5>=0.85,"划算",IF(I5>=0.65,"略亏：空位紧张时仍值得","偏亏：建议降价或加强"))))
A6: dart | B6: 1 | C6: 3 | D6: 实心铁罐 | E6: 260 | F6: 550 | G6: 11.2 | H6: =G6/F6*100 | I6: =IFERROR((G6/F6)/(SUMIFS($G$3:$G$98,$A$3:$A$98,A6,$B$3:$B$98,0)/SUMIFS($F$3:$F$98,$A$3:$A$98,A6,$B$3:$B$98,0)),"") | J6: =IF(B6=0,1,IF(C6<=1,G6-SUMIFS($G$3:$G$98,$A$3:$A$98,A6,$B$3:$B$98,0),G6-G5)/E6/(SUMIFS($G$3:$G$98,$A$3:$A$98,A6,$B$3:$B$98,0)/SUMIFS($F$3:$F$98,$A$3:$A$98,A6,$B$3:$B$98,0))) | K6: 0.785 | L6: 0.795 | M6: =IF(OR(K6="",L6="",L6=0),"",K6/L6) | N6: 破甲 | O6: =IF(B6=0,"基准",IF(AND(N6<>"",I6<0.85),"功能型：单看输出偏低属正常",IF(I6>=0.85,"划算",IF(I6>=0.65,"略亏：空位紧张时仍值得","偏亏：建议降价或加强"))))
A7: dart | B7: 1 | C7: 4 | D7: 罐头炮 | E7: 600 | F7: 1150 | G7: 22.4 | H7: =G7/F7*100 | I7: =IFERROR((G7/F7)/(SUMIFS($G$3:$G$98,$A$3:$A$98,A7,$B$3:$B$98,0)/SUMIFS($F$3:$F$98,$A$3:$A$98,A7,$B$3:$B$98,0)),"") | J7: =IF(B7=0,1,IF(C7<=1,G7-SUMIFS($G$3:$G$98,$A$3:$A$98,A7,$B$3:$B$98,0),G7-G6)/E7/(SUMIFS($G$3:$G$98,$A$3:$A$98,A7,$B$3:$B$98,0)/SUMIFS($F$3:$F$98,$A$3:$A$98,A7,$B$3:$B$98,0))) | K7: 1 | L7: 1 | M7: =IF(OR(K7="",L7="",L7=0),"",K7/L7) | N7: 对 Boss | O7: =IF(B7=0,"基准",IF(AND(N7<>"",I7<0.85),"功能型：单看输出偏低属正常",IF(I7>=0.85,"划算",IF(I7>=0.65,"略亏：空位紧张时仍值得","偏亏：建议降价或加强"))))
A8: dart | B8: 1 | C8: 5 | D8: 大桶可乐 | E8: 1400 | F8: 2550 | G8: 53.76 | H8: =G8/F8*100 | I8: =IFERROR((G8/F8)/(SUMIFS($G$3:$G$98,$A$3:$A$98,A8,$B$3:$B$98,0)/SUMIFS($F$3:$F$98,$A$3:$A$98,A8,$B$3:$B$98,0)),"") | J8: =IF(B8=0,1,IF(C8<=1,G8-SUMIFS($G$3:$G$98,$A$3:$A$98,A8,$B$3:$B$98,0),G8-G7)/E8/(SUMIFS($G$3:$G$98,$A$3:$A$98,A8,$B$3:$B$98,0)/SUMIFS($F$3:$F$98,$A$3:$A$98,A8,$B$3:$B$98,0))) | M8: =IF(OR(K8="",L8="",L8=0),"",K8/L8) | O8: =IF(B8=0,"基准",IF(AND(N8<>"",I8<0.85),"功能型：单看输出偏低属正常",IF(I8>=0.85,"划算",IF(I8>=0.65,"略亏：空位紧张时仍值得","偏亏：建议降价或加强"))))
A9: dart | B9: 2 | C9: 1 | D9: 快手 | E9: 40 | F9: 140 | G9: 2.99 | H9: =G9/F9*100 | I9: =IFERROR((G9/F9)/(SUMIFS($G$3:$G$98,$A$3:$A$98,A9,$B$3:$B$98,0)/SUMIFS($F$3:$F$98,$A$3:$A$98,A9,$B$3:$B$98,0)),"") | J9: =IF(B9=0,1,IF(C9<=1,G9-SUMIFS($G$3:$G$98,$A$3:$A$98,A9,$B$3:$B$98,0),G9-G8)/E9/(SUMIFS($G$3:$G$98,$A$3:$A$98,A9,$B$3:$B$98,0)/SUMIFS($F$3:$F$98,$A$3:$A$98,A9,$B$3:$B$98,0))) | K9: 0.255 | L9: 0.306 | M9: =IF(OR(K9="",L9="",L9=0),"",K9/L9) | O9: =IF(B9=0,"基准",IF(AND(N9<>"",I9<0.85),"功能型：单看输出偏低属正常",IF(I9>=0.85,"划算",IF(I9>=0.65,"略亏：空位紧张时仍值得","偏亏：建议降价或加强"))))
A10: dart | B10: 2 | C10: 2 | D10: 双手投 | E10: 70 | F10: 210 | G10: 3.98 | H10: =G10/F10*100 | I10: =IFERROR((G10/F10)/(SUMIFS($G$3:$G$98,$A$3:$A$98,A10,$B$3:$B$98,0)/SUMIFS($F$3:$F$98,$A$3:$A$98,A10,$B$3:$B$98,0)),"") | J10: =IF(B10=0,1,IF(C10<=1,G10-SUMIFS($G$3:$G$98,$A$3:$A$98,A10,$B$3:$B$98,0),G10-G9)/E10/(SUMIFS($G$3:$G$98,$A$3:$A$98,A10,$B$3:$B$98,0)/SUMIFS($F$3:$F$98,$A$3:$A$98,A10,$B$3:$B$98,0))) | K10: 0.296 | L10: 0.43 | M10: =IF(OR(K10="",L10="",L10=0),"",K10/L10) | O10: =IF(B10=0,"基准",IF(AND(N10<>"",I10<0.85),"功能型：单看输出偏低属正常",IF(I10>=0.85,"划算",IF(I10>=0.65,"略亏：空位紧张时仍值得","偏亏：建议降价或加强"))))
A11: dart | B11: 2 | C11: 3 | D11: 三连投 | E11: 280 | F11: 490 | G11: 11.95 | H11: =G11/F11*100 | I11: =IFERROR((G11/F11)/(SUMIFS($G$3:$G$98,$A$3:$A$98,A11,$B$3:$B$98,0)/SUMIFS($F$3:$F$98,$A$3:$A$98,A11,$B$3:$B$98,0)),"") | J11: =IF(B11=0,1,IF(C11<=1,G11-SUMIFS($G$3:$G$98,$A$3:$A$98,A11,$B$3:$B$98,0),G11-G10)/E11/(SUMIFS($G$3:$G$98,$A$3:$A$98,A11,$B$3:$B$98,0)/SUMIFS($F$3:$F$98,$A$3:$A$98,A11,$B$3:$B$98,0))) | K11: 0.772 | L11: 0.763 | M11: =IF(OR(K11="",L11="",L11=0),"",K11/L11) | O11: =IF(B11=0,"基准",IF(AND(N11<>"",I11<0.85),"功能型：单看输出偏低属正常",IF(I11>=0.85,"划算",IF(I11>=0.65,"略亏：空位紧张时仍值得","偏亏：建议降价或加强"))))
A12: dart | B12: 2 | C12: 4 | D12: 自动投罐机 | E12: 650 | F12: 1140 | G12: 23.89 | H12: =G12/F12*100 | I12: =IFERROR((G12/F12)/(SUMIFS($G$3:$G$98,$A$3:$A$98,A12,$B$3:$B$98,0)/SUMIFS($F$3:$F$98,$A$3:$A$98,A12,$B$3:$B$98,0)),"") | J12: =IF(B12=0,1,IF(C12<=1,G12-SUMIFS($G$3:$G$98,$A$3:$A$98,A12,$B$3:$B$98,0),G12-G11)/E12/(SUMIFS($G$3:$G$98,$A$3:$A$98,A12,$B$3:$B$98,0)/SUMIFS($F$3:$F$98,$A$3:$A$98,A12,$B$3:$B$98,0))) | K12: 0.921 | L12: 1 | M12: =IF(OR(K12="",L12="",L12=0),"",K12/L12) | O12: =IF(B12=0,"基准",IF(AND(N12<>"",I12<0.85),"功能型：单看输出偏低属正常",IF(I12>=0.85,"划算",IF(I12>=0.65,"略亏：空位紧张时仍值得","偏亏：建议降价或加强"))))
A13: dart | B13: 2 | C13: 5 | D13: 罐头暴雨 | E13: 1500 | F13: 2640 | G13: 66.52 | H13: =G13/F13*100 | I13: =IFERROR((G13/F13)/(SUMIFS($G$3:$G$98,$A$3:$A$98,A13,$B$3:$B$98,0)/SUMIFS($F$3:$F$98,$A$3:$A$98,A13,$B$3:$B$98,0)),"") | J13: =IF(B13=0,1,IF(C13<=1,G13-SUMIFS($G$3:$G$98,$A$3:$A$98,A13,$B$3:$B$98,0),G13-G12)/E13/(SUMIFS($G$3:$G$98,$A$3:$A$98,A13,$B$3:$B$98,0)/SUMIFS($F$3:$F$98,$A$3:$A$98,A13,$B$3:$B$98,0))) | M13: =IF(OR(K13="",L13="",L13=0),"",K13/L13) | O13: =IF(B13=0,"基准",IF(AND(N13<>"",I13<0.85),"功能型：单看输出偏低属正常",IF(I13>=0.85,"划算",IF(I13>=0.65,"略亏：空位紧张时仍值得","偏亏：建议降价或加强"))))
A14: dart | B14: 3 | C14: 1 | D14: 远投 | E14: 50 | F14: 150 | G14: 2.24 | H14: =G14/F14*100 | I14: =IFERROR((G14/F14)/(SUMIFS($G$3:$G$98,$A$3:$A$98,A14,$B$3:$B$98,0)/SUMIFS($F$3:$F$98,$A$3:$A$98,A14,$B$3:$B$98,0)),"") | J14: =IF(B14=0,1,IF(C14<=1,G14-SUMIFS($G$3:$G$98,$A$3:$A$98,A14,$B$3:$B$98,0),G14-G13)/E14/(SUMIFS($G$3:$G$98,$A$3:$A$98,A14,$B$3:$B$98,0)/SUMIFS($F$3:$F$98,$A$3:$A$98,A14,$B$3:$B$98,0))) | K14: 0.201 | L14: 0.324 | M14: =IF(OR(K14="",L14="",L14=0),"",K14/L14) | O14: =IF(B14=0,"基准",IF(AND(N14<>"",I14<0.85),"功能型：单看输出偏低属正常",IF(I14>=0.85,"划算",IF(I14>=0.65,"略亏：空位紧张时仍值得","偏亏：建议降价或加强"))))
A15: dart | B15: 3 | C15: 2 | D15: 精准 | E15: 100 | F15: 250 | G15: 2.54 | H15: =G15/F15*100 | I15: =IFERROR((G15/F15)/(SUMIFS($G$3:$G$98,$A$3:$A$98,A15,$B$3:$B$98,0)/SUMIFS($F$3:$F$98,$A$3:$A$98,A15,$B$3:$B$98,0)),"") | J15: =IF(B15=0,1,IF(C15<=1,G15-SUMIFS($G$3:$G$98,$A$3:$A$98,A15,$B$3:$B$98,0),G15-G14)/E15/(SUMIFS($G$3:$G$98,$A$3:$A$98,A15,$B$3:$B$98,0)/SUMIFS($F$3:$F$98,$A$3:$A$98,A15,$B$3:$B$98,0))) | K15: 0.281 | L15: 0.497 | M15: =IF(OR(K15="",L15="",L15=0),"",K15/L15) | O15: =IF(B15=0,"基准",IF(AND(N15<>"",I15<0.85),"功能型：单看输出偏低属正常",IF(I15>=0.85,"划算",IF(I15>=0.65,"略亏：空位紧张时仍值得","偏亏：建议降价或加强"))))
A16: dart | B16: 3 | C16: 3 | D16: 汽水黏鞋 | E16: 300 | F16: 550 | G16: 2.54 | H16: =G16/F16*100 | I16: =IFERROR((G16/F16)/(SUMIFS($G$3:$G$98,$A$3:$A$98,A16,$B$3:$B$98,0)/SUMIFS($F$3:$F$98,$A$3:$A$98,A16,$B$3:$B$98,0)),"") | J16: =IF(B16=0,1,IF(C16<=1,G16-SUMIFS($G$3:$G$98,$A$3:$A$98,A16,$B$3:$B$98,0),G16-G15)/E16/(SUMIFS($G$3:$G$98,$A$3:$A$98,A16,$B$3:$B$98,0)/SUMIFS($F$3:$F$98,$A$3:$A$98,A16,$B$3:$B$98,0))) | K16: 0.271 | L16: 0.795 | M16: =IF(OR(K16="",L16="",L16=0),"",K16/L16) | N16: 标记增伤 | O16: =IF(B16=0,"基准",IF(AND(N16<>"",I16<0.85),"功能型：单看输出偏低属正常",IF(I16>=0.85,"划算",IF(I16>=0.65,"略亏：空位紧张时仍值得","偏亏：建议降价或加强"))))
A17: dart | B17: 3 | C17: 4 | D17: 远程狙罐 | E17: 700 | F17: 1250 | G17: 3.08 | H17: =G17/F17*100 | I17: =IFERROR((G17/F17)/(SUMIFS($G$3:$G$98,$A$3:$A$98,A17,$B$3:$B$98,0)/SUMIFS($F$3:$F$98,$A$3:$A$98,A17,$B$3:$B$98,0)),"") | J17: =IF(B17=0,1,IF(C17<=1,G17-SUMIFS($G$3:$G$98,$A$3:$A$98,A17,$B$3:$B$98,0),G17-G16)/E17/(SUMIFS($G$3:$G$98,$A$3:$A$98,A17,$B$3:$B$98,0)/SUMIFS($F$3:$F$98,$A$3:$A$98,A17,$B$3:$B$98,0))) | K17: 0.36 | L17: 1 | M17: =IF(OR(K17="",L17="",L17=0),"",K17/L17) | O17: =IF(B17=0,"基准",IF(AND(N17<>"",I17<0.85),"功能型：单看输出偏低属正常",IF(I17>=0.85,"划算",IF(I17>=0.65,"略亏：空位紧张时仍值得","偏亏：建议降价或加强"))))
A18: dart | B18: 3 | C18: 5 | D18: 补给站站长 | E18: 1300 | F18: 2550 | G18: 3.08 | H18: =G18/F18*100 | I18: =IFERROR((G18/F18)/(SUMIFS($G$3:$G$98,$A$3:$A$98,A18,$B$3:$B$98,0)/SUMIFS($F$3:$F$98,$A$3:$A$98,A18,$B$3:$B$98,0)),"") | J18: =IF(B18=0,1,IF(C18<=1,G18-SUMIFS($G$3:$G$98,$A$3:$A$98,A18,$B$3:$B$98,0),G18-G17)/E18/(SUMIFS($G$3:$G$98,$A$3:$A$98,A18,$B$3:$B$98,0)/SUMIFS($F$3:$F$98,$A$3:$A$98,A18,$B$3:$B$98,0))) | M18: =IF(OR(K18="",L18="",L18=0),"",K18/L18) | N18: 光环 | O18: =IF(B18=0,"基准",IF(AND(N18<>"",I18<0.85),"功能型：单看输出偏低属正常",IF(I18>=0.85,"划算",IF(I18>=0.65,"略亏：空位紧张时仍值得","偏亏：建议降价或加强"))))
A19: bomb | B19: 0 | C19: 0 | D19: 基础 | E19: 160 | F19: 160 | G19: 10.54 | H19: =G19/F19*100 | I19: =IFERROR((G19/F19)/(SUMIFS($G$3:$G$98,$A$3:$A$98,A19,$B$3:$B$98,0)/SUMIFS($F$3:$F$98,$A$3:$A$98,A19,$B$3:$B$98,0)),"") | J19: =IF(B19=0,1,IF(C19<=1,G19-SUMIFS($G$3:$G$98,$A$3:$A$98,A19,$B$3:$B$98,0),G19-G18)/E19/(SUMIFS($G$3:$G$98,$A$3:$A$98,A19,$B$3:$B$98,0)/SUMIFS($F$3:$F$98,$A$3:$A$98,A19,$B$3:$B$98,0))) | M19: =IF(OR(K19="",L19="",L19=0),"",K19/L19) | O19: =IF(B19=0,"基准",IF(AND(N19<>"",I19<0.85),"功能型：单看输出偏低属正常",IF(I19>=0.85,"划算",IF(I19>=0.65,"略亏：空位紧张时仍值得","偏亏：建议降价或加强"))))
A20: bomb | B20: 1 | C20: 1 | D20: 大片香蕉皮 | E20: 70 | F20: 230 | G20: 12.53 | H20: =G20/F20*100 | I20: =IFERROR((G20/F20)/(SUMIFS($G$3:$G$98,$A$3:$A$98,A20,$B$3:$B$98,0)/SUMIFS($F$3:$F$98,$A$3:$A$98,A20,$B$3:$B$98,0)),"") | J20: =IF(B20=0,1,IF(C20<=1,G20-SUMIFS($G$3:$G$98,$A$3:$A$98,A20,$B$3:$B$98,0),G20-G19)/E20/(SUMIFS($G$3:$G$98,$A$3:$A$98,A20,$B$3:$B$98,0)/SUMIFS($F$3:$F$98,$A$3:$A$98,A20,$B$3:$B$98,0))) | K20: 0.394 | L20: 0.301 | M20: =IF(OR(K20="",L20="",L20=0),"",K20/L20) | O20: =IF(B20=0,"基准",IF(AND(N20<>"",I20<0.85),"功能型：单看输出偏低属正常",IF(I20>=0.85,"划算",IF(I20>=0.65,"略亏：空位紧张时仍值得","偏亏：建议降价或加强"))))
A21: bomb | B21: 1 | C21: 2 | D21: 熟透香蕉 | E21: 150 | F21: 380 | G21: 25.05 | H21: =G21/F21*100 | I21: =IFERROR((G21/F21)/(SUMIFS($G$3:$G$98,$A$3:$A$98,A21,$B$3:$B$98,0)/SUMIFS($F$3:$F$98,$A$3:$A$98,A21,$B$3:$B$98,0)),"") | J21: =IF(B21=0,1,IF(C21<=1,G21-SUMIFS($G$3:$G$98,$A$3:$A$98,A21,$B$3:$B$98,0),G21-G20)/E21/(SUMIFS($G$3:$G$98,$A$3:$A$98,A21,$B$3:$B$98,0)/SUMIFS($F$3:$F$98,$A$3:$A$98,A21,$B$3:$B$98,0))) | K21: 0.452 | L21: 0.489 | M21: =IF(OR(K21="",L21="",L21=0),"",K21/L21) | O21: =IF(B21=0,"基准",IF(AND(N21<>"",I21<0.85),"功能型：单看输出偏低属正常",IF(I21>=0.85,"划算",IF(I21>=0.65,"略亏：空位紧张时仍值得","偏亏：建议降价或加强"))))
A22: bomb | B22: 1 | C22: 3 | D22: 四脚朝天 | E22: 330 | F22: 710 | G22: 25.05 | H22: =G22/F22*100 | I22: =IFERROR((G22/F22)/(SUMIFS($G$3:$G$98,$A$3:$A$98,A22,$B$3:$B$98,0)/SUMIFS($F$3:$F$98,$A$3:$A$98,A22,$B$3:$B$98,0)),"") | J22: =IF(B22=0,1,IF(C22<=1,G22-SUMIFS($G$3:$G$98,$A$3:$A$98,A22,$B$3:$B$98,0),G22-G21)/E22/(SUMIFS($G$3:$G$98,$A$3:$A$98,A22,$B$3:$B$98,0)/SUMIFS($F$3:$F$98,$A$3:$A$98,A22,$B$3:$B$98,0))) | K22: 0.821 | L22: 0.852 | M22: =IF(OR(K22="",L22="",L22=0),"",K22/L22) | N22: 眩晕 | O22: =IF(B22=0,"基准",IF(AND(N22<>"",I22<0.85),"功能型：单看输出偏低属正常",IF(I22>=0.85,"划算",IF(I22>=0.65,"略亏：空位紧张时仍值得","偏亏：建议降价或加强"))))
A23: bomb | B23: 1 | C23: 4 | D23: 香蕉船 | E23: 750 | F23: 1460 | G23: 25.05 | H23: =G23/F23*100 | I23: =IFERROR((G23/F23)/(SUMIFS($G$3:$G$98,$A$3:$A$98,A23,$B$3:$B$98,0)/SUMIFS($F$3:$F$98,$A$3:$A$98,A23,$B$3:$B$98,0)),"") | J23: =IF(B23=0,1,IF(C23<=1,G23-SUMIFS($G$3:$G$98,$A$3:$A$98,A23,$B$3:$B$98,0),G23-G22)/E23/(SUMIFS($G$3:$G$98,$A$3:$A$98,A23,$B$3:$B$98,0)/SUMIFS($F$3:$F$98,$A$3:$A$98,A23,$B$3:$B$98,0))) | K23: 0.826 | L23: 1 | M23: =IF(OR(K23="",L23="",L23=0),"",K23/L23) | N23: 对 Boss | O23: =IF(B23=0,"基准",IF(AND(N23<>"",I23<0.85),"功能型：单看输出偏低属正常",IF(I23>=0.85,"划算",IF(I23>=0.65,"略亏：空位紧张时仍值得","偏亏：建议降价或加强"))))
A24: bomb | B24: 1 | C24: 5 | D24: 香蕉海啸 | E24: 1400 | F24: 2860 | G24: 156.51 | H24: =G24/F24*100 | I24: =IFERROR((G24/F24)/(SUMIFS($G$3:$G$98,$A$3:$A$98,A24,$B$3:$B$98,0)/SUMIFS($F$3:$F$98,$A$3:$A$98,A24,$B$3:$B$98,0)),"") | J24: =IF(B24=0,1,IF(C24<=1,G24-SUMIFS($G$3:$G$98,$A$3:$A$98,A24,$B$3:$B$98,0),G24-G23)/E24/(SUMIFS($G$3:$G$98,$A$3:$A$98,A24,$B$3:$B$98,0)/SUMIFS($F$3:$F$98,$A$3:$A$98,A24,$B$3:$B$98,0))) | M24: =IF(OR(K24="",L24="",L24=0),"",K24/L24) | O24: =IF(B24=0,"基准",IF(AND(N24<>"",I24<0.85),"功能型：单看输出偏低属正常",IF(I24>=0.85,"划算",IF(I24>=0.65,"略亏：空位紧张时仍值得","偏亏：建议降价或加强"))))
A25: bomb | B25: 2 | C25: 1 | D25: 双发香蕉 | E25: 100 | F25: 260 | G25: 21.07 | H25: =G25/F25*100 | I25: =IFERROR((G25/F25)/(SUMIFS($G$3:$G$98,$A$3:$A$98,A25,$B$3:$B$98,0)/SUMIFS($F$3:$F$98,$A$3:$A$98,A25,$B$3:$B$98,0)),"") | J25: =IF(B25=0,1,IF(C25<=1,G25-SUMIFS($G$3:$G$98,$A$3:$A$98,A25,$B$3:$B$98,0),G25-G24)/E25/(SUMIFS($G$3:$G$98,$A$3:$A$98,A25,$B$3:$B$98,0)/SUMIFS($F$3:$F$98,$A$3:$A$98,A25,$B$3:$B$98,0))) | K25: 0.413 | L25: 0.337 | M25: =IF(OR(K25="",L25="",L25=0),"",K25/L25) | O25: =IF(B25=0,"基准",IF(AND(N25<>"",I25<0.85),"功能型：单看输出偏低属正常",IF(I25>=0.85,"划算",IF(I25>=0.65,"略亏：空位紧张时仍值得","偏亏：建议降价或加强"))))
A26: bomb | B26: 2 | C26: 2 | D26: 香蕉碎片 | E26: 160 | F26: 420 | G26: 23.84 | H26: =G26/F26*100 | I26: =IFERROR((G26/F26)/(SUMIFS($G$3:$G$98,$A$3:$A$98,A26,$B$3:$B$98,0)/SUMIFS($F$3:$F$98,$A$3:$A$98,A26,$B$3:$B$98,0)),"") | J26: =IF(B26=0,1,IF(C26<=1,G26-SUMIFS($G$3:$G$98,$A$3:$A$98,A26,$B$3:$B$98,0),G26-G25)/E26/(SUMIFS($G$3:$G$98,$A$3:$A$98,A26,$B$3:$B$98,0)/SUMIFS($F$3:$F$98,$A$3:$A$98,A26,$B$3:$B$98,0))) | K26: 0.634 | L26: 0.542 | M26: =IF(OR(K26="",L26="",L26=0),"",K26/L26) | O26: =IF(B26=0,"基准",IF(AND(N26<>"",I26<0.85),"功能型：单看输出偏低属正常",IF(I26>=0.85,"划算",IF(I26>=0.65,"略亏：空位紧张时仍值得","偏亏：建议降价或加强"))))
A27: bomb | B27: 2 | C27: 3 | D27: 一串香蕉 | E27: 220 | F27: 640 | G27: 30.05 | H27: =G27/F27*100 | I27: =IFERROR((G27/F27)/(SUMIFS($G$3:$G$98,$A$3:$A$98,A27,$B$3:$B$98,0)/SUMIFS($F$3:$F$98,$A$3:$A$98,A27,$B$3:$B$98,0)),"") | J27: =IF(B27=0,1,IF(C27<=1,G27-SUMIFS($G$3:$G$98,$A$3:$A$98,A27,$B$3:$B$98,0),G27-G26)/E27/(SUMIFS($G$3:$G$98,$A$3:$A$98,A27,$B$3:$B$98,0)/SUMIFS($F$3:$F$98,$A$3:$A$98,A27,$B$3:$B$98,0))) | K27: 0.788 | L27: 0.817 | M27: =IF(OR(K27="",L27="",L27=0),"",K27/L27) | O27: =IF(B27=0,"基准",IF(AND(N27<>"",I27<0.85),"功能型：单看输出偏低属正常",IF(I27>=0.85,"划算",IF(I27>=0.65,"略亏：空位紧张时仍值得","偏亏：建议降价或加强"))))
A28: bomb | B28: 2 | C28: 4 | D28: 香蕉连环 | E28: 480 | F28: 1120 | G28: 36.26 | H28: =G28/F28*100 | I28: =IFERROR((G28/F28)/(SUMIFS($G$3:$G$98,$A$3:$A$98,A28,$B$3:$B$98,0)/SUMIFS($F$3:$F$98,$A$3:$A$98,A28,$B$3:$B$98,0)),"") | J28: =IF(B28=0,1,IF(C28<=1,G28-SUMIFS($G$3:$G$98,$A$3:$A$98,A28,$B$3:$B$98,0),G28-G27)/E28/(SUMIFS($G$3:$G$98,$A$3:$A$98,A28,$B$3:$B$98,0)/SUMIFS($F$3:$F$98,$A$3:$A$98,A28,$B$3:$B$98,0))) | K28: 0.919 | L28: 1 | M28: =IF(OR(K28="",L28="",L28=0),"",K28/L28) | O28: =IF(B28=0,"基准",IF(AND(N28<>"",I28<0.85),"功能型：单看输出偏低属正常",IF(I28>=0.85,"划算",IF(I28>=0.65,"略亏：空位紧张时仍值得","偏亏：建议降价或加强"))))
A29: bomb | B29: 2 | C29: 5 | D29: 香蕉雨 | E29: 1500 | F29: 2620 | G29: 90.66 | H29: =G29/F29*100 | I29: =IFERROR((G29/F29)/(SUMIFS($G$3:$G$98,$A$3:$A$98,A29,$B$3:$B$98,0)/SUMIFS($F$3:$F$98,$A$3:$A$98,A29,$B$3:$B$98,0)),"") | J29: =IF(B29=0,1,IF(C29<=1,G29-SUMIFS($G$3:$G$98,$A$3:$A$98,A29,$B$3:$B$98,0),G29-G28)/E29/(SUMIFS($G$3:$G$98,$A$3:$A$98,A29,$B$3:$B$98,0)/SUMIFS($F$3:$F$98,$A$3:$A$98,A29,$B$3:$B$98,0))) | M29: =IF(OR(K29="",L29="",L29=0),"",K29/L29) | O29: =IF(B29=0,"基准",IF(AND(N29<>"",I29<0.85),"功能型：单看输出偏低属正常",IF(I29>=0.85,"划算",IF(I29>=0.65,"略亏：空位紧张时仍值得","偏亏：建议降价或加强"))))
A30: bomb | B30: 3 | C30: 1 | D30: 辣椒粉 | E30: 80 | F30: 240 | G30: 15.24 | H30: =G30/F30*100 | I30: =IFERROR((G30/F30)/(SUMIFS($G$3:$G$98,$A$3:$A$98,A30,$B$3:$B$98,0)/SUMIFS($F$3:$F$98,$A$3:$A$98,A30,$B$3:$B$98,0)),"") | J30: =IF(B30=0,1,IF(C30<=1,G30-SUMIFS($G$3:$G$98,$A$3:$A$98,A30,$B$3:$B$98,0),G30-G29)/E30/(SUMIFS($G$3:$G$98,$A$3:$A$98,A30,$B$3:$B$98,0)/SUMIFS($F$3:$F$98,$A$3:$A$98,A30,$B$3:$B$98,0))) | K30: 0.338 | L30: 0.313 | M30: =IF(OR(K30="",L30="",L30=0),"",K30/L30) | O30: =IF(B30=0,"基准",IF(AND(N30<>"",I30<0.85),"功能型：单看输出偏低属正常",IF(I30>=0.85,"划算",IF(I30>=0.65,"略亏：空位紧张时仍值得","偏亏：建议降价或加强"))))
A31: bomb | B31: 3 | C31: 2 | D31: 魔鬼椒 | E31: 140 | F31: 380 | G31: 20.42 | H31: =G31/F31*100 | I31: =IFERROR((G31/F31)/(SUMIFS($G$3:$G$98,$A$3:$A$98,A31,$B$3:$B$98,0)/SUMIFS($F$3:$F$98,$A$3:$A$98,A31,$B$3:$B$98,0)),"") | J31: =IF(B31=0,1,IF(C31<=1,G31-SUMIFS($G$3:$G$98,$A$3:$A$98,A31,$B$3:$B$98,0),G31-G30)/E31/(SUMIFS($G$3:$G$98,$A$3:$A$98,A31,$B$3:$B$98,0)/SUMIFS($F$3:$F$98,$A$3:$A$98,A31,$B$3:$B$98,0))) | K31: 0.361 | L31: 0.489 | M31: =IF(OR(K31="",L31="",L31=0),"",K31/L31) | O31: =IF(B31=0,"基准",IF(AND(N31<>"",I31<0.85),"功能型：单看输出偏低属正常",IF(I31>=0.85,"划算",IF(I31>=0.65,"略亏：空位紧张时仍值得","偏亏：建议降价或加强"))))
A32: bomb | B32: 3 | C32: 3 | D32: 辣油泼地 | E32: 260 | F32: 640 | G32: 27.19 | H32: =G32/F32*100 | I32: =IFERROR((G32/F32)/(SUMIFS($G$3:$G$98,$A$3:$A$98,A32,$B$3:$B$98,0)/SUMIFS($F$3:$F$98,$A$3:$A$98,A32,$B$3:$B$98,0)),"") | J32: =IF(B32=0,1,IF(C32<=1,G32-SUMIFS($G$3:$G$98,$A$3:$A$98,A32,$B$3:$B$98,0),G32-G31)/E32/(SUMIFS($G$3:$G$98,$A$3:$A$98,A32,$B$3:$B$98,0)/SUMIFS($F$3:$F$98,$A$3:$A$98,A32,$B$3:$B$98,0))) | K32: 0.526 | L32: 0.817 | M32: =IF(OR(K32="",L32="",L32=0),"",K32/L32) | O32: =IF(B32=0,"基准",IF(AND(N32<>"",I32<0.85),"功能型：单看输出偏低属正常",IF(I32>=0.85,"划算",IF(I32>=0.65,"略亏：空位紧张时仍值得","偏亏：建议降价或加强"))))
A33: bomb | B33: 3 | C33: 4 | D33: 变态辣 | E33: 560 | F33: 1200 | G33: 42.01 | H33: =G33/F33*100 | I33: =IFERROR((G33/F33)/(SUMIFS($G$3:$G$98,$A$3:$A$98,A33,$B$3:$B$98,0)/SUMIFS($F$3:$F$98,$A$3:$A$98,A33,$B$3:$B$98,0)),"") | J33: =IF(B33=0,1,IF(C33<=1,G33-SUMIFS($G$3:$G$98,$A$3:$A$98,A33,$B$3:$B$98,0),G33-G32)/E33/(SUMIFS($G$3:$G$98,$A$3:$A$98,A33,$B$3:$B$98,0)/SUMIFS($F$3:$F$98,$A$3:$A$98,A33,$B$3:$B$98,0))) | K33: 0.701 | L33: 1 | M33: =IF(OR(K33="",L33="",L33=0),"",K33/L33) | O33: =IF(B33=0,"基准",IF(AND(N33<>"",I33<0.85),"功能型：单看输出偏低属正常",IF(I33>=0.85,"划算",IF(I33>=0.65,"略亏：空位紧张时仍值得","偏亏：建议降价或加强"))))
A34: bomb | B34: 3 | C34: 5 | D34: 火锅底料 | E34: 1600 | F34: 2800 | G34: 42.01 | H34: =G34/F34*100 | I34: =IFERROR((G34/F34)/(SUMIFS($G$3:$G$98,$A$3:$A$98,A34,$B$3:$B$98,0)/SUMIFS($F$3:$F$98,$A$3:$A$98,A34,$B$3:$B$98,0)),"") | J34: =IF(B34=0,1,IF(C34<=1,G34-SUMIFS($G$3:$G$98,$A$3:$A$98,A34,$B$3:$B$98,0),G34-G33)/E34/(SUMIFS($G$3:$G$98,$A$3:$A$98,A34,$B$3:$B$98,0)/SUMIFS($F$3:$F$98,$A$3:$A$98,A34,$B$3:$B$98,0))) | M34: =IF(OR(K34="",L34="",L34=0),"",K34/L34) | N34: 连锁爆燃 | O34: =IF(B34=0,"基准",IF(AND(N34<>"",I34<0.85),"功能型：单看输出偏低属正常",IF(I34>=0.85,"划算",IF(I34>=0.65,"略亏：空位紧张时仍值得","偏亏：建议降价或加强"))))
A35: frost | B35: 0 | C35: 0 | D35: 基础 | E35: 120 | F35: 120 | G35: 2.26 | H35: =G35/F35*100 | I35: =IFERROR((G35/F35)/(SUMIFS($G$3:$G$98,$A$3:$A$98,A35,$B$3:$B$98,0)/SUMIFS($F$3:$F$98,$A$3:$A$98,A35,$B$3:$B$98,0)),"") | J35: =IF(B35=0,1,IF(C35<=1,G35-SUMIFS($G$3:$G$98,$A$3:$A$98,A35,$B$3:$B$98,0),G35-G34)/E35/(SUMIFS($G$3:$G$98,$A$3:$A$98,A35,$B$3:$B$98,0)/SUMIFS($F$3:$F$98,$A$3:$A$98,A35,$B$3:$B$98,0))) | M35: =IF(OR(K35="",L35="",L35=0),"",K35/L35) | O35: =IF(B35=0,"基准",IF(AND(N35<>"",I35<0.85),"功能型：单看输出偏低属正常",IF(I35>=0.85,"划算",IF(I35>=0.65,"略亏：空位紧张时仍值得","偏亏：建议降价或加强"))))
A36: frost | B36: 1 | C36: 1 | D36: 凉水 | E36: 60 | F36: 180 | G36: 2.26 | H36: =G36/F36*100 | I36: =IFERROR((G36/F36)/(SUMIFS($G$3:$G$98,$A$3:$A$98,A36,$B$3:$B$98,0)/SUMIFS($F$3:$F$98,$A$3:$A$98,A36,$B$3:$B$98,0)),"") | J36: =IF(B36=0,1,IF(C36<=1,G36-SUMIFS($G$3:$G$98,$A$3:$A$98,A36,$B$3:$B$98,0),G36-G35)/E36/(SUMIFS($G$3:$G$98,$A$3:$A$98,A36,$B$3:$B$98,0)/SUMIFS($F$3:$F$98,$A$3:$A$98,A36,$B$3:$B$98,0))) | K36: 0.232 | L36: 0.298 | M36: =IF(OR(K36="",L36="",L36=0),"",K36/L36) | N36: 减速 | O36: =IF(B36=0,"基准",IF(AND(N36<>"",I36<0.85),"功能型：单看输出偏低属正常",IF(I36>=0.85,"划算",IF(I36>=0.65,"略亏：空位紧张时仍值得","偏亏：建议降价或加强"))))
A37: frost | B37: 1 | C37: 2 | D37: 持续喷淋 | E37: 90 | F37: 270 | G37: 2.26 | H37: =G37/F37*100 | I37: =IFERROR((G37/F37)/(SUMIFS($G$3:$G$98,$A$3:$A$98,A37,$B$3:$B$98,0)/SUMIFS($F$3:$F$98,$A$3:$A$98,A37,$B$3:$B$98,0)),"") | J37: =IF(B37=0,1,IF(C37<=1,G37-SUMIFS($G$3:$G$98,$A$3:$A$98,A37,$B$3:$B$98,0),G37-G36)/E37/(SUMIFS($G$3:$G$98,$A$3:$A$98,A37,$B$3:$B$98,0)/SUMIFS($F$3:$F$98,$A$3:$A$98,A37,$B$3:$B$98,0))) | K37: 0.259 | L37: 0.452 | M37: =IF(OR(K37="",L37="",L37=0),"",K37/L37) | N37: 减速 | O37: =IF(B37=0,"基准",IF(AND(N37<>"",I37<0.85),"功能型：单看输出偏低属正常",IF(I37>=0.85,"划算",IF(I37>=0.65,"略亏：空位紧张时仍值得","偏亏：建议降价或加强"))))
A38: frost | B38: 1 | C38: 3 | D38: 冰水 | E38: 300 | F38: 570 | G38: 2.26 | H38: =G38/F38*100 | I38: =IFERROR((G38/F38)/(SUMIFS($G$3:$G$98,$A$3:$A$98,A38,$B$3:$B$98,0)/SUMIFS($F$3:$F$98,$A$3:$A$98,A38,$B$3:$B$98,0)),"") | J38: =IF(B38=0,1,IF(C38<=1,G38-SUMIFS($G$3:$G$98,$A$3:$A$98,A38,$B$3:$B$98,0),G38-G37)/E38/(SUMIFS($G$3:$G$98,$A$3:$A$98,A38,$B$3:$B$98,0)/SUMIFS($F$3:$F$98,$A$3:$A$98,A38,$B$3:$B$98,0))) | K38: 0.861 | L38: 0.761 | M38: =IF(OR(K38="",L38="",L38=0),"",K38/L38) | N38: 冻结 | O38: =IF(B38=0,"基准",IF(AND(N38<>"",I38<0.85),"功能型：单看输出偏低属正常",IF(I38>=0.85,"划算",IF(I38>=0.65,"略亏：空位紧张时仍值得","偏亏：建议降价或加强"))))
A39: frost | B39: 1 | C39: 4 | D39: 冰桶挑战 | E39: 750 | F39: 1320 | G39: 2.26 | H39: =G39/F39*100 | I39: =IFERROR((G39/F39)/(SUMIFS($G$3:$G$98,$A$3:$A$98,A39,$B$3:$B$98,0)/SUMIFS($F$3:$F$98,$A$3:$A$98,A39,$B$3:$B$98,0)),"") | J39: =IF(B39=0,1,IF(C39<=1,G39-SUMIFS($G$3:$G$98,$A$3:$A$98,A39,$B$3:$B$98,0),G39-G38)/E39/(SUMIFS($G$3:$G$98,$A$3:$A$98,A39,$B$3:$B$98,0)/SUMIFS($F$3:$F$98,$A$3:$A$98,A39,$B$3:$B$98,0))) | K39: 0.99 | L39: 1 | M39: =IF(OR(K39="",L39="",L39=0),"",K39/L39) | N39: 冻结、对 Boss | O39: =IF(B39=0,"基准",IF(AND(N39<>"",I39<0.85),"功能型：单看输出偏低属正常",IF(I39>=0.85,"划算",IF(I39>=0.65,"略亏：空位紧张时仍值得","偏亏：建议降价或加强"))))
A40: frost | B40: 1 | C40: 5 | D40: 人工降雪 | E40: 1600 | F40: 2920 | G40: 2.26 | H40: =G40/F40*100 | I40: =IFERROR((G40/F40)/(SUMIFS($G$3:$G$98,$A$3:$A$98,A40,$B$3:$B$98,0)/SUMIFS($F$3:$F$98,$A$3:$A$98,A40,$B$3:$B$98,0)),"") | J40: =IF(B40=0,1,IF(C40<=1,G40-SUMIFS($G$3:$G$98,$A$3:$A$98,A40,$B$3:$B$98,0),G40-G39)/E40/(SUMIFS($G$3:$G$98,$A$3:$A$98,A40,$B$3:$B$98,0)/SUMIFS($F$3:$F$98,$A$3:$A$98,A40,$B$3:$B$98,0))) | M40: =IF(OR(K40="",L40="",L40=0),"",K40/L40) | N40: 全场冻结 | O40: =IF(B40=0,"基准",IF(AND(N40<>"",I40<0.85),"功能型：单看输出偏低属正常",IF(I40>=0.85,"划算",IF(I40>=0.65,"略亏：空位紧张时仍值得","偏亏：建议降价或加强"))))
A41: frost | B41: 2 | C41: 1 | D41: 加压 | E41: 70 | F41: 190 | G41: 4.51 | H41: =G41/F41*100 | I41: =IFERROR((G41/F41)/(SUMIFS($G$3:$G$98,$A$3:$A$98,A41,$B$3:$B$98,0)/SUMIFS($F$3:$F$98,$A$3:$A$98,A41,$B$3:$B$98,0)),"") | J41: =IF(B41=0,1,IF(C41<=1,G41-SUMIFS($G$3:$G$98,$A$3:$A$98,A41,$B$3:$B$98,0),G41-G40)/E41/(SUMIFS($G$3:$G$98,$A$3:$A$98,A41,$B$3:$B$98,0)/SUMIFS($F$3:$F$98,$A$3:$A$98,A41,$B$3:$B$98,0))) | K41: 0.387 | L41: 0.314 | M41: =IF(OR(K41="",L41="",L41=0),"",K41/L41) | O41: =IF(B41=0,"基准",IF(AND(N41<>"",I41<0.85),"功能型：单看输出偏低属正常",IF(I41>=0.85,"划算",IF(I41>=0.65,"略亏：空位紧张时仍值得","偏亏：建议降价或加强"))))
A42: frost | B42: 2 | C42: 2 | D42: 湿身 | E42: 130 | F42: 320 | G42: 4.51 | H42: =G42/F42*100 | I42: =IFERROR((G42/F42)/(SUMIFS($G$3:$G$98,$A$3:$A$98,A42,$B$3:$B$98,0)/SUMIFS($F$3:$F$98,$A$3:$A$98,A42,$B$3:$B$98,0)),"") | J42: =IF(B42=0,1,IF(C42<=1,G42-SUMIFS($G$3:$G$98,$A$3:$A$98,A42,$B$3:$B$98,0),G42-G41)/E42/(SUMIFS($G$3:$G$98,$A$3:$A$98,A42,$B$3:$B$98,0)/SUMIFS($F$3:$F$98,$A$3:$A$98,A42,$B$3:$B$98,0))) | K42: 0.473 | L42: 0.551 | M42: =IF(OR(K42="",L42="",L42=0),"",K42/L42) | N42: 易伤 | O42: =IF(B42=0,"基准",IF(AND(N42<>"",I42<0.85),"功能型：单看输出偏低属正常",IF(I42>=0.85,"划算",IF(I42>=0.65,"略亏：空位紧张时仍值得","偏亏：建议降价或加强"))))
A43: frost | B43: 2 | C43: 3 | D43: 高压水柱 | E43: 320 | F43: 640 | G43: 9.02 | H43: =G43/F43*100 | I43: =IFERROR((G43/F43)/(SUMIFS($G$3:$G$98,$A$3:$A$98,A43,$B$3:$B$98,0)/SUMIFS($F$3:$F$98,$A$3:$A$98,A43,$B$3:$B$98,0)),"") | J43: =IF(B43=0,1,IF(C43<=1,G43-SUMIFS($G$3:$G$98,$A$3:$A$98,A43,$B$3:$B$98,0),G43-G42)/E43/(SUMIFS($G$3:$G$98,$A$3:$A$98,A43,$B$3:$B$98,0)/SUMIFS($F$3:$F$98,$A$3:$A$98,A43,$B$3:$B$98,0))) | K43: 0.837 | L43: 0.798 | M43: =IF(OR(K43="",L43="",L43=0),"",K43/L43) | O43: =IF(B43=0,"基准",IF(AND(N43<>"",I43<0.85),"功能型：单看输出偏低属正常",IF(I43>=0.85,"划算",IF(I43>=0.65,"略亏：空位紧张时仍值得","偏亏：建议降价或加强"))))
A44: frost | B44: 2 | C44: 4 | D44: 冰面 | E44: 680 | F44: 1320 | G44: 9.02 | H44: =G44/F44*100 | I44: =IFERROR((G44/F44)/(SUMIFS($G$3:$G$98,$A$3:$A$98,A44,$B$3:$B$98,0)/SUMIFS($F$3:$F$98,$A$3:$A$98,A44,$B$3:$B$98,0)),"") | J44: =IF(B44=0,1,IF(C44<=1,G44-SUMIFS($G$3:$G$98,$A$3:$A$98,A44,$B$3:$B$98,0),G44-G43)/E44/(SUMIFS($G$3:$G$98,$A$3:$A$98,A44,$B$3:$B$98,0)/SUMIFS($F$3:$F$98,$A$3:$A$98,A44,$B$3:$B$98,0))) | K44: 0.856 | L44: 1 | M44: =IF(OR(K44="",L44="",L44=0),"",K44/L44) | N44: 易伤 | O44: =IF(B44=0,"基准",IF(AND(N44<>"",I44<0.85),"功能型：单看输出偏低属正常",IF(I44>=0.85,"划算",IF(I44>=0.65,"略亏：空位紧张时仍值得","偏亏：建议降价或加强"))))
A45: frost | B45: 2 | C45: 5 | D45: 消防水炮 | E45: 1500 | F45: 2820 | G45: 56.14 | H45: =G45/F45*100 | I45: =IFERROR((G45/F45)/(SUMIFS($G$3:$G$98,$A$3:$A$98,A45,$B$3:$B$98,0)/SUMIFS($F$3:$F$98,$A$3:$A$98,A45,$B$3:$B$98,0)),"") | J45: =IF(B45=0,1,IF(C45<=1,G45-SUMIFS($G$3:$G$98,$A$3:$A$98,A45,$B$3:$B$98,0),G45-G44)/E45/(SUMIFS($G$3:$G$98,$A$3:$A$98,A45,$B$3:$B$98,0)/SUMIFS($F$3:$F$98,$A$3:$A$98,A45,$B$3:$B$98,0))) | M45: =IF(OR(K45="",L45="",L45=0),"",K45/L45) | O45: =IF(B45=0,"基准",IF(AND(N45<>"",I45<0.85),"功能型：单看输出偏低属正常",IF(I45>=0.85,"划算",IF(I45>=0.65,"略亏：空位紧张时仍值得","偏亏：建议降价或加强"))))
A46: frost | B46: 3 | C46: 1 | D46: 喷头扩展 | E46: 60 | F46: 180 | G46: 2.88 | H46: =G46/F46*100 | I46: =IFERROR((G46/F46)/(SUMIFS($G$3:$G$98,$A$3:$A$98,A46,$B$3:$B$98,0)/SUMIFS($F$3:$F$98,$A$3:$A$98,A46,$B$3:$B$98,0)),"") | J46: =IF(B46=0,1,IF(C46<=1,G46-SUMIFS($G$3:$G$98,$A$3:$A$98,A46,$B$3:$B$98,0),G46-G45)/E46/(SUMIFS($G$3:$G$98,$A$3:$A$98,A46,$B$3:$B$98,0)/SUMIFS($F$3:$F$98,$A$3:$A$98,A46,$B$3:$B$98,0))) | K46: 0.347 | L46: 0.298 | M46: =IF(OR(K46="",L46="",L46=0),"",K46/L46) | O46: =IF(B46=0,"基准",IF(AND(N46<>"",I46<0.85),"功能型：单看输出偏低属正常",IF(I46>=0.85,"划算",IF(I46>=0.65,"略亏：空位紧张时仍值得","偏亏：建议降价或加强"))))
A47: frost | B47: 3 | C47: 2 | D47: 快速喷淋 | E47: 110 | F47: 290 | G47: 3.6 | H47: =G47/F47*100 | I47: =IFERROR((G47/F47)/(SUMIFS($G$3:$G$98,$A$3:$A$98,A47,$B$3:$B$98,0)/SUMIFS($F$3:$F$98,$A$3:$A$98,A47,$B$3:$B$98,0)),"") | J47: =IF(B47=0,1,IF(C47<=1,G47-SUMIFS($G$3:$G$98,$A$3:$A$98,A47,$B$3:$B$98,0),G47-G46)/E47/(SUMIFS($G$3:$G$98,$A$3:$A$98,A47,$B$3:$B$98,0)/SUMIFS($F$3:$F$98,$A$3:$A$98,A47,$B$3:$B$98,0))) | K47: 0.44 | L47: 0.492 | M47: =IF(OR(K47="",L47="",L47=0),"",K47/L47) | O47: =IF(B47=0,"基准",IF(AND(N47<>"",I47<0.85),"功能型：单看输出偏低属正常",IF(I47>=0.85,"划算",IF(I47>=0.65,"略亏：空位紧张时仍值得","偏亏：建议降价或加强"))))
A48: frost | B48: 3 | C48: 3 | D48: 泡水鞋 | E48: 260 | F48: 550 | G48: 3.6 | H48: =G48/F48*100 | I48: =IFERROR((G48/F48)/(SUMIFS($G$3:$G$98,$A$3:$A$98,A48,$B$3:$B$98,0)/SUMIFS($F$3:$F$98,$A$3:$A$98,A48,$B$3:$B$98,0)),"") | J48: =IF(B48=0,1,IF(C48<=1,G48-SUMIFS($G$3:$G$98,$A$3:$A$98,A48,$B$3:$B$98,0),G48-G47)/E48/(SUMIFS($G$3:$G$98,$A$3:$A$98,A48,$B$3:$B$98,0)/SUMIFS($F$3:$F$98,$A$3:$A$98,A48,$B$3:$B$98,0))) | K48: 0.483 | L48: 0.751 | M48: =IF(OR(K48="",L48="",L48=0),"",K48/L48) | N48: 破甲 | O48: =IF(B48=0,"基准",IF(AND(N48<>"",I48<0.85),"功能型：单看输出偏低属正常",IF(I48>=0.85,"划算",IF(I48>=0.65,"略亏：空位紧张时仍值得","偏亏：建议降价或加强"))))
A49: frost | B49: 3 | C49: 4 | D49: 补水光环 | E49: 600 | F49: 1150 | G49: 3.6 | H49: =G49/F49*100 | I49: =IFERROR((G49/F49)/(SUMIFS($G$3:$G$98,$A$3:$A$98,A49,$B$3:$B$98,0)/SUMIFS($F$3:$F$98,$A$3:$A$98,A49,$B$3:$B$98,0)),"") | J49: =IF(B49=0,1,IF(C49<=1,G49-SUMIFS($G$3:$G$98,$A$3:$A$98,A49,$B$3:$B$98,0),G49-G48)/E49/(SUMIFS($G$3:$G$98,$A$3:$A$98,A49,$B$3:$B$98,0)/SUMIFS($F$3:$F$98,$A$3:$A$98,A49,$B$3:$B$98,0))) | K49: 0.479 | L49: 1 | M49: =IF(OR(K49="",L49="",L49=0),"",K49/L49) | N49: 光环 | O49: =IF(B49=0,"基准",IF(AND(N49<>"",I49<0.85),"功能型：单看输出偏低属正常",IF(I49>=0.85,"划算",IF(I49>=0.65,"略亏：空位紧张时仍值得","偏亏：建议降价或加强"))))
A50: frost | B50: 3 | C50: 5 | D50: 能量饮料站 | E50: 1300 | F50: 2450 | G50: 3.6 | H50: =G50/F50*100 | I50: =IFERROR((G50/F50)/(SUMIFS($G$3:$G$98,$A$3:$A$98,A50,$B$3:$B$98,0)/SUMIFS($F$3:$F$98,$A$3:$A$98,A50,$B$3:$B$98,0)),"") | J50: =IF(B50=0,1,IF(C50<=1,G50-SUMIFS($G$3:$G$98,$A$3:$A$98,A50,$B$3:$B$98,0),G50-G49)/E50/(SUMIFS($G$3:$G$98,$A$3:$A$98,A50,$B$3:$B$98,0)/SUMIFS($F$3:$F$98,$A$3:$A$98,A50,$B$3:$B$98,0))) | M50: =IF(OR(K50="",L50="",L50=0),"",K50/L50) | N50: 光环 | O50: =IF(B50=0,"基准",IF(AND(N50<>"",I50<0.85),"功能型：单看输出偏低属正常",IF(I50>=0.85,"划算",IF(I50>=0.65,"略亏：空位紧张时仍值得","偏亏：建议降价或加强"))))
A51: sniper | B51: 0 | C51: 0 | D51: 基础 | E51: 180 | F51: 180 | G51: 3.95 | H51: =G51/F51*100 | I51: =IFERROR((G51/F51)/(SUMIFS($G$3:$G$98,$A$3:$A$98,A51,$B$3:$B$98,0)/SUMIFS($F$3:$F$98,$A$3:$A$98,A51,$B$3:$B$98,0)),"") | J51: =IF(B51=0,1,IF(C51<=1,G51-SUMIFS($G$3:$G$98,$A$3:$A$98,A51,$B$3:$B$98,0),G51-G50)/E51/(SUMIFS($G$3:$G$98,$A$3:$A$98,A51,$B$3:$B$98,0)/SUMIFS($F$3:$F$98,$A$3:$A$98,A51,$B$3:$B$98,0))) | M51: =IF(OR(K51="",L51="",L51=0),"",K51/L51) | O51: =IF(B51=0,"基准",IF(AND(N51<>"",I51<0.85),"功能型：单看输出偏低属正常",IF(I51>=0.85,"划算",IF(I51>=0.65,"略亏：空位紧张时仍值得","偏亏：建议降价或加强"))))
A52: sniper | B52: 1 | C52: 1 | D52: 加重鞋盒 | E52: 100 | F52: 280 | G52: 6.59 | H52: =G52/F52*100 | I52: =IFERROR((G52/F52)/(SUMIFS($G$3:$G$98,$A$3:$A$98,A52,$B$3:$B$98,0)/SUMIFS($F$3:$F$98,$A$3:$A$98,A52,$B$3:$B$98,0)),"") | J52: =IF(B52=0,1,IF(C52<=1,G52-SUMIFS($G$3:$G$98,$A$3:$A$98,A52,$B$3:$B$98,0),G52-G51)/E52/(SUMIFS($G$3:$G$98,$A$3:$A$98,A52,$B$3:$B$98,0)/SUMIFS($F$3:$F$98,$A$3:$A$98,A52,$B$3:$B$98,0))) | K52: 0.619 | L52: 0.524 | M52: =IF(OR(K52="",L52="",L52=0),"",K52/L52) | O52: =IF(B52=0,"基准",IF(AND(N52<>"",I52<0.85),"功能型：单看输出偏低属正常",IF(I52>=0.85,"划算",IF(I52>=0.65,"略亏：空位紧张时仍值得","偏亏：建议降价或加强"))))
A53: sniper | B53: 1 | C53: 2 | D53: 大号鞋盒 | E53: 180 | F53: 460 | G53: 10.54 | H53: =G53/F53*100 | I53: =IFERROR((G53/F53)/(SUMIFS($G$3:$G$98,$A$3:$A$98,A53,$B$3:$B$98,0)/SUMIFS($F$3:$F$98,$A$3:$A$98,A53,$B$3:$B$98,0)),"") | J53: =IF(B53=0,1,IF(C53<=1,G53-SUMIFS($G$3:$G$98,$A$3:$A$98,A53,$B$3:$B$98,0),G53-G52)/E53/(SUMIFS($G$3:$G$98,$A$3:$A$98,A53,$B$3:$B$98,0)/SUMIFS($F$3:$F$98,$A$3:$A$98,A53,$B$3:$B$98,0))) | K53: 0.726 | L53: 0.793 | M53: =IF(OR(K53="",L53="",L53=0),"",K53/L53) | O53: =IF(B53=0,"基准",IF(AND(N53<>"",I53<0.85),"功能型：单看输出偏低属正常",IF(I53>=0.85,"划算",IF(I53>=0.65,"略亏：空位紧张时仍值得","偏亏：建议降价或加强"))))
A54: sniper | B54: 1 | C54: 3 | D54: 退赛通知 | E54: 400 | F54: 860 | G54: 10.54 | H54: =G54/F54*100 | I54: =IFERROR((G54/F54)/(SUMIFS($G$3:$G$98,$A$3:$A$98,A54,$B$3:$B$98,0)/SUMIFS($F$3:$F$98,$A$3:$A$98,A54,$B$3:$B$98,0)),"") | J54: =IF(B54=0,1,IF(C54<=1,G54-SUMIFS($G$3:$G$98,$A$3:$A$98,A54,$B$3:$B$98,0),G54-G53)/E54/(SUMIFS($G$3:$G$98,$A$3:$A$98,A54,$B$3:$B$98,0)/SUMIFS($F$3:$F$98,$A$3:$A$98,A54,$B$3:$B$98,0))) | K54: 0.757 | L54: 1 | M54: =IF(OR(K54="",L54="",L54=0),"",K54/L54) | N54: 处决 | O54: =IF(B54=0,"基准",IF(AND(N54<>"",I54<0.85),"功能型：单看输出偏低属正常",IF(I54>=0.85,"划算",IF(I54>=0.65,"略亏：空位紧张时仍值得","偏亏：建议降价或加强"))))
A55: sniper | B55: 1 | C55: 4 | D55: 创世鞋盒 | E55: 750 | F55: 1610 | G55: 21.08 | H55: =G55/F55*100 | I55: =IFERROR((G55/F55)/(SUMIFS($G$3:$G$98,$A$3:$A$98,A55,$B$3:$B$98,0)/SUMIFS($F$3:$F$98,$A$3:$A$98,A55,$B$3:$B$98,0)),"") | J55: =IF(B55=0,1,IF(C55<=1,G55-SUMIFS($G$3:$G$98,$A$3:$A$98,A55,$B$3:$B$98,0),G55-G54)/E55/(SUMIFS($G$3:$G$98,$A$3:$A$98,A55,$B$3:$B$98,0)/SUMIFS($F$3:$F$98,$A$3:$A$98,A55,$B$3:$B$98,0))) | K55: 0.833 | L55: 1 | M55: =IF(OR(K55="",L55="",L55=0),"",K55/L55) | N55: 对 Boss | O55: =IF(B55=0,"基准",IF(AND(N55<>"",I55<0.85),"功能型：单看输出偏低属正常",IF(I55>=0.85,"划算",IF(I55>=0.65,"略亏：空位紧张时仍值得","偏亏：建议降价或加强"))))
A56: sniper | B56: 1 | C56: 5 | D56: 神秘箱轰炸 | E56: 2000 | F56: 3610 | G56: 21.08 | H56: =G56/F56*100 | I56: =IFERROR((G56/F56)/(SUMIFS($G$3:$G$98,$A$3:$A$98,A56,$B$3:$B$98,0)/SUMIFS($F$3:$F$98,$A$3:$A$98,A56,$B$3:$B$98,0)),"") | J56: =IF(B56=0,1,IF(C56<=1,G56-SUMIFS($G$3:$G$98,$A$3:$A$98,A56,$B$3:$B$98,0),G56-G55)/E56/(SUMIFS($G$3:$G$98,$A$3:$A$98,A56,$B$3:$B$98,0)/SUMIFS($F$3:$F$98,$A$3:$A$98,A56,$B$3:$B$98,0))) | M56: =IF(OR(K56="",L56="",L56=0),"",K56/L56) | N56: 处决 | O56: =IF(B56=0,"基准",IF(AND(N56<>"",I56<0.85),"功能型：单看输出偏低属正常",IF(I56>=0.85,"划算",IF(I56>=0.65,"略亏：空位紧张时仍值得","偏亏：建议降价或加强"))))
A57: sniper | B57: 2 | C57: 1 | D57: 夜航 | E57: 80 | F57: 260 | G57: 4.66 | H57: =G57/F57*100 | I57: =IFERROR((G57/F57)/(SUMIFS($G$3:$G$98,$A$3:$A$98,A57,$B$3:$B$98,0)/SUMIFS($F$3:$F$98,$A$3:$A$98,A57,$B$3:$B$98,0)),"") | J57: =IF(B57=0,1,IF(C57<=1,G57-SUMIFS($G$3:$G$98,$A$3:$A$98,A57,$B$3:$B$98,0),G57-G56)/E57/(SUMIFS($G$3:$G$98,$A$3:$A$98,A57,$B$3:$B$98,0)/SUMIFS($F$3:$F$98,$A$3:$A$98,A57,$B$3:$B$98,0))) | K57: 0.422 | L57: 0.498 | M57: =IF(OR(K57="",L57="",L57=0),"",K57/L57) | O57: =IF(B57=0,"基准",IF(AND(N57<>"",I57<0.85),"功能型：单看输出偏低属正常",IF(I57>=0.85,"划算",IF(I57>=0.65,"略亏：空位紧张时仍值得","偏亏：建议降价或加强"))))
A58: sniper | B58: 2 | C58: 2 | D58: 快速装填 | E58: 100 | F58: 360 | G58: 5.82 | H58: =G58/F58*100 | I58: =IFERROR((G58/F58)/(SUMIFS($G$3:$G$98,$A$3:$A$98,A58,$B$3:$B$98,0)/SUMIFS($F$3:$F$98,$A$3:$A$98,A58,$B$3:$B$98,0)),"") | J58: =IF(B58=0,1,IF(C58<=1,G58-SUMIFS($G$3:$G$98,$A$3:$A$98,A58,$B$3:$B$98,0),G58-G57)/E58/(SUMIFS($G$3:$G$98,$A$3:$A$98,A58,$B$3:$B$98,0)/SUMIFS($F$3:$F$98,$A$3:$A$98,A58,$B$3:$B$98,0))) | K58: 0.594 | L58: 0.628 | M58: =IF(OR(K58="",L58="",L58=0),"",K58/L58) | O58: =IF(B58=0,"基准",IF(AND(N58<>"",I58<0.85),"功能型：单看输出偏低属正常",IF(I58>=0.85,"划算",IF(I58>=0.65,"略亏：空位紧张时仍值得","偏亏：建议降价或加强"))))
A59: sniper | B59: 2 | C59: 3 | D59: 双桨无人机 | E59: 300 | F59: 660 | G59: 11.65 | H59: =G59/F59*100 | I59: =IFERROR((G59/F59)/(SUMIFS($G$3:$G$98,$A$3:$A$98,A59,$B$3:$B$98,0)/SUMIFS($F$3:$F$98,$A$3:$A$98,A59,$B$3:$B$98,0)),"") | J59: =IF(B59=0,1,IF(C59<=1,G59-SUMIFS($G$3:$G$98,$A$3:$A$98,A59,$B$3:$B$98,0),G59-G58)/E59/(SUMIFS($G$3:$G$98,$A$3:$A$98,A59,$B$3:$B$98,0)/SUMIFS($F$3:$F$98,$A$3:$A$98,A59,$B$3:$B$98,0))) | K59: 0.897 | L59: 0.975 | M59: =IF(OR(K59="",L59="",L59=0),"",K59/L59) | O59: =IF(B59=0,"基准",IF(AND(N59<>"",I59<0.85),"功能型：单看输出偏低属正常",IF(I59>=0.85,"划算",IF(I59>=0.65,"略亏：空位紧张时仍值得","偏亏：建议降价或加强"))))
A60: sniper | B60: 2 | C60: 4 | D60: 无人机群 | E60: 650 | F60: 1310 | G60: 19.41 | H60: =G60/F60*100 | I60: =IFERROR((G60/F60)/(SUMIFS($G$3:$G$98,$A$3:$A$98,A60,$B$3:$B$98,0)/SUMIFS($F$3:$F$98,$A$3:$A$98,A60,$B$3:$B$98,0)),"") | J60: =IF(B60=0,1,IF(C60<=1,G60-SUMIFS($G$3:$G$98,$A$3:$A$98,A60,$B$3:$B$98,0),G60-G59)/E60/(SUMIFS($G$3:$G$98,$A$3:$A$98,A60,$B$3:$B$98,0)/SUMIFS($F$3:$F$98,$A$3:$A$98,A60,$B$3:$B$98,0))) | K60: 1 | L60: 1 | M60: =IF(OR(K60="",L60="",L60=0),"",K60/L60) | O60: =IF(B60=0,"基准",IF(AND(N60<>"",I60<0.85),"功能型：单看输出偏低属正常",IF(I60>=0.85,"划算",IF(I60>=0.65,"略亏：空位紧张时仍值得","偏亏：建议降价或加强"))))
A61: sniper | B61: 2 | C61: 5 | D61: 当日达 | E61: 1900 | F61: 3210 | G61: 73.95 | H61: =G61/F61*100 | I61: =IFERROR((G61/F61)/(SUMIFS($G$3:$G$98,$A$3:$A$98,A61,$B$3:$B$98,0)/SUMIFS($F$3:$F$98,$A$3:$A$98,A61,$B$3:$B$98,0)),"") | J61: =IF(B61=0,1,IF(C61<=1,G61-SUMIFS($G$3:$G$98,$A$3:$A$98,A61,$B$3:$B$98,0),G61-G60)/E61/(SUMIFS($G$3:$G$98,$A$3:$A$98,A61,$B$3:$B$98,0)/SUMIFS($F$3:$F$98,$A$3:$A$98,A61,$B$3:$B$98,0))) | M61: =IF(OR(K61="",L61="",L61=0),"",K61/L61) | O61: =IF(B61=0,"基准",IF(AND(N61<>"",I61<0.85),"功能型：单看输出偏低属正常",IF(I61>=0.85,"划算",IF(I61>=0.65,"略亏：空位紧张时仍值得","偏亏：建议降价或加强"))))
A62: sniper | B62: 3 | C62: 1 | D62: 震地 | E62: 90 | F62: 270 | G62: 3.95 | H62: =G62/F62*100 | I62: =IFERROR((G62/F62)/(SUMIFS($G$3:$G$98,$A$3:$A$98,A62,$B$3:$B$98,0)/SUMIFS($F$3:$F$98,$A$3:$A$98,A62,$B$3:$B$98,0)),"") | J62: =IF(B62=0,1,IF(C62<=1,G62-SUMIFS($G$3:$G$98,$A$3:$A$98,A62,$B$3:$B$98,0),G62-G61)/E62/(SUMIFS($G$3:$G$98,$A$3:$A$98,A62,$B$3:$B$98,0)/SUMIFS($F$3:$F$98,$A$3:$A$98,A62,$B$3:$B$98,0))) | K62: 0.372 | L62: 0.511 | M62: =IF(OR(K62="",L62="",L62=0),"",K62/L62) | N62: 眩晕 | O62: =IF(B62=0,"基准",IF(AND(N62<>"",I62<0.85),"功能型：单看输出偏低属正常",IF(I62>=0.85,"划算",IF(I62>=0.65,"略亏：空位紧张时仍值得","偏亏：建议降价或加强"))))
A63: sniper | B63: 3 | C63: 2 | D63: 弹跳鞋盒 | E63: 150 | F63: 420 | G63: 7.91 | H63: =G63/F63*100 | I63: =IFERROR((G63/F63)/(SUMIFS($G$3:$G$98,$A$3:$A$98,A63,$B$3:$B$98,0)/SUMIFS($F$3:$F$98,$A$3:$A$98,A63,$B$3:$B$98,0)),"") | J63: =IF(B63=0,1,IF(C63<=1,G63-SUMIFS($G$3:$G$98,$A$3:$A$98,A63,$B$3:$B$98,0),G63-G62)/E63/(SUMIFS($G$3:$G$98,$A$3:$A$98,A63,$B$3:$B$98,0)/SUMIFS($F$3:$F$98,$A$3:$A$98,A63,$B$3:$B$98,0))) | K63: 0.703 | L63: 0.727 | M63: =IF(OR(K63="",L63="",L63=0),"",K63/L63) | O63: =IF(B63=0,"基准",IF(AND(N63<>"",I63<0.85),"功能型：单看输出偏低属正常",IF(I63>=0.85,"划算",IF(I63>=0.65,"略亏：空位紧张时仍值得","偏亏：建议降价或加强"))))
A64: sniper | B64: 3 | C64: 3 | D64: GST 补给 | E64: 360 | F64: 780 | G64: 7.91 | H64: =G64/F64*100 | I64: =IFERROR((G64/F64)/(SUMIFS($G$3:$G$98,$A$3:$A$98,A64,$B$3:$B$98,0)/SUMIFS($F$3:$F$98,$A$3:$A$98,A64,$B$3:$B$98,0)),"") | J64: =IF(B64=0,1,IF(C64<=1,G64-SUMIFS($G$3:$G$98,$A$3:$A$98,A64,$B$3:$B$98,0),G64-G63)/E64/(SUMIFS($G$3:$G$98,$A$3:$A$98,A64,$B$3:$B$98,0)/SUMIFS($F$3:$F$98,$A$3:$A$98,A64,$B$3:$B$98,0))) | K64: 0.724 | L64: 1 | M64: =IF(OR(K64="",L64="",L64=0),"",K64/L64) | N64: 经济 | O64: =IF(B64=0,"基准",IF(AND(N64<>"",I64<0.85),"功能型：单看输出偏低属正常",IF(I64>=0.85,"划算",IF(I64>=0.65,"略亏：空位紧张时仍值得","偏亏：建议降价或加强"))))
A65: sniper | B65: 3 | C65: 4 | D65: GST 空投 | E65: 700 | F65: 1480 | G65: 7.91 | H65: =G65/F65*100 | I65: =IFERROR((G65/F65)/(SUMIFS($G$3:$G$98,$A$3:$A$98,A65,$B$3:$B$98,0)/SUMIFS($F$3:$F$98,$A$3:$A$98,A65,$B$3:$B$98,0)),"") | J65: =IF(B65=0,1,IF(C65<=1,G65-SUMIFS($G$3:$G$98,$A$3:$A$98,A65,$B$3:$B$98,0),G65-G64)/E65/(SUMIFS($G$3:$G$98,$A$3:$A$98,A65,$B$3:$B$98,0)/SUMIFS($F$3:$F$98,$A$3:$A$98,A65,$B$3:$B$98,0))) | K65: 0.669 | L65: 1 | M65: =IF(OR(K65="",L65="",L65=0),"",K65/L65) | N65: 经济 | O65: =IF(B65=0,"基准",IF(AND(N65<>"",I65<0.85),"功能型：单看输出偏低属正常",IF(I65>=0.85,"划算",IF(I65>=0.65,"略亏：空位紧张时仍值得","偏亏：建议降价或加强"))))
A66: sniper | B66: 3 | C66: 5 | D66: 空中支援 | E66: 1500 | F66: 2980 | G66: 7.91 | H66: =G66/F66*100 | I66: =IFERROR((G66/F66)/(SUMIFS($G$3:$G$98,$A$3:$A$98,A66,$B$3:$B$98,0)/SUMIFS($F$3:$F$98,$A$3:$A$98,A66,$B$3:$B$98,0)),"") | J66: =IF(B66=0,1,IF(C66<=1,G66-SUMIFS($G$3:$G$98,$A$3:$A$98,A66,$B$3:$B$98,0),G66-G65)/E66/(SUMIFS($G$3:$G$98,$A$3:$A$98,A66,$B$3:$B$98,0)/SUMIFS($F$3:$F$98,$A$3:$A$98,A66,$B$3:$B$98,0))) | M66: =IF(OR(K66="",L66="",L66=0),"",K66/L66) | N66: 全局增伤 | O66: =IF(B66=0,"基准",IF(AND(N66<>"",I66<0.85),"功能型：单看输出偏低属正常",IF(I66>=0.85,"划算",IF(I66>=0.65,"略亏：空位紧张时仍值得","偏亏：建议降价或加强"))))
A67: tesla | B67: 0 | C67: 0 | D67: 基础 | E67: 150 | F67: 150 | G67: 6.4 | H67: =G67/F67*100 | I67: =IFERROR((G67/F67)/(SUMIFS($G$3:$G$98,$A$3:$A$98,A67,$B$3:$B$98,0)/SUMIFS($F$3:$F$98,$A$3:$A$98,A67,$B$3:$B$98,0)),"") | J67: =IF(B67=0,1,IF(C67<=1,G67-SUMIFS($G$3:$G$98,$A$3:$A$98,A67,$B$3:$B$98,0),G67-G66)/E67/(SUMIFS($G$3:$G$98,$A$3:$A$98,A67,$B$3:$B$98,0)/SUMIFS($F$3:$F$98,$A$3:$A$98,A67,$B$3:$B$98,0))) | M67: =IF(OR(K67="",L67="",L67=0),"",K67/L67) | O67: =IF(B67=0,"基准",IF(AND(N67<>"",I67<0.85),"功能型：单看输出偏低属正常",IF(I67>=0.85,"划算",IF(I67>=0.65,"略亏：空位紧张时仍值得","偏亏：建议降价或加强"))))
A68: tesla | B68: 1 | C68: 1 | D68: 小音箱 | E68: 50 | F68: 200 | G68: 7.93 | H68: =G68/F68*100 | I68: =IFERROR((G68/F68)/(SUMIFS($G$3:$G$98,$A$3:$A$98,A68,$B$3:$B$98,0)/SUMIFS($F$3:$F$98,$A$3:$A$98,A68,$B$3:$B$98,0)),"") | J68: =IF(B68=0,1,IF(C68<=1,G68-SUMIFS($G$3:$G$98,$A$3:$A$98,A68,$B$3:$B$98,0),G68-G67)/E68/(SUMIFS($G$3:$G$98,$A$3:$A$98,A68,$B$3:$B$98,0)/SUMIFS($F$3:$F$98,$A$3:$A$98,A68,$B$3:$B$98,0))) | K68: 0.285 | L68: 0.292 | M68: =IF(OR(K68="",L68="",L68=0),"",K68/L68) | O68: =IF(B68=0,"基准",IF(AND(N68<>"",I68<0.85),"功能型：单看输出偏低属正常",IF(I68>=0.85,"划算",IF(I68>=0.65,"略亏：空位紧张时仍值得","偏亏：建议降价或加强"))))
A69: tesla | B69: 1 | C69: 2 | D69: 蓝牙串联 | E69: 90 | F69: 290 | G69: 10.33 | H69: =G69/F69*100 | I69: =IFERROR((G69/F69)/(SUMIFS($G$3:$G$98,$A$3:$A$98,A69,$B$3:$B$98,0)/SUMIFS($F$3:$F$98,$A$3:$A$98,A69,$B$3:$B$98,0)),"") | J69: =IF(B69=0,1,IF(C69<=1,G69-SUMIFS($G$3:$G$98,$A$3:$A$98,A69,$B$3:$B$98,0),G69-G68)/E69/(SUMIFS($G$3:$G$98,$A$3:$A$98,A69,$B$3:$B$98,0)/SUMIFS($F$3:$F$98,$A$3:$A$98,A69,$B$3:$B$98,0))) | K69: 0.357 | L69: 0.386 | M69: =IF(OR(K69="",L69="",L69=0),"",K69/L69) | O69: =IF(B69=0,"基准",IF(AND(N69<>"",I69<0.85),"功能型：单看输出偏低属正常",IF(I69>=0.85,"划算",IF(I69>=0.65,"略亏：空位紧张时仍值得","偏亏：建议降价或加强"))))
A70: tesla | B70: 1 | C70: 3 | D70: 无损音质 | E70: 320 | F70: 610 | G70: 22.4 | H70: =G70/F70*100 | I70: =IFERROR((G70/F70)/(SUMIFS($G$3:$G$98,$A$3:$A$98,A70,$B$3:$B$98,0)/SUMIFS($F$3:$F$98,$A$3:$A$98,A70,$B$3:$B$98,0)),"") | J70: =IF(B70=0,1,IF(C70<=1,G70-SUMIFS($G$3:$G$98,$A$3:$A$98,A70,$B$3:$B$98,0),G70-G69)/E70/(SUMIFS($G$3:$G$98,$A$3:$A$98,A70,$B$3:$B$98,0)/SUMIFS($F$3:$F$98,$A$3:$A$98,A70,$B$3:$B$98,0))) | K70: 0.651 | L70: 0.69 | M70: =IF(OR(K70="",L70="",L70=0),"",K70/L70) | O70: =IF(B70=0,"基准",IF(AND(N70<>"",I70<0.85),"功能型：单看输出偏低属正常",IF(I70>=0.85,"划算",IF(I70>=0.65,"略亏：空位紧张时仍值得","偏亏：建议降价或加强"))))
A71: tesla | B71: 1 | C71: 4 | D71: 双声道 | E71: 750 | F71: 1360 | G71: 44.8 | H71: =G71/F71*100 | I71: =IFERROR((G71/F71)/(SUMIFS($G$3:$G$98,$A$3:$A$98,A71,$B$3:$B$98,0)/SUMIFS($F$3:$F$98,$A$3:$A$98,A71,$B$3:$B$98,0)),"") | J71: =IF(B71=0,1,IF(C71<=1,G71-SUMIFS($G$3:$G$98,$A$3:$A$98,A71,$B$3:$B$98,0),G71-G70)/E71/(SUMIFS($G$3:$G$98,$A$3:$A$98,A71,$B$3:$B$98,0)/SUMIFS($F$3:$F$98,$A$3:$A$98,A71,$B$3:$B$98,0))) | K71: 0.724 | L71: 1 | M71: =IF(OR(K71="",L71="",L71=0),"",K71/L71) | O71: =IF(B71=0,"基准",IF(AND(N71<>"",I71<0.85),"功能型：单看输出偏低属正常",IF(I71>=0.85,"划算",IF(I71>=0.65,"略亏：空位紧张时仍值得","偏亏：建议降价或加强"))))
A72: tesla | B72: 1 | C72: 5 | D72: 全城广场舞 | E72: 1700 | F72: 3060 | G72: 179.2 | H72: =G72/F72*100 | I72: =IFERROR((G72/F72)/(SUMIFS($G$3:$G$98,$A$3:$A$98,A72,$B$3:$B$98,0)/SUMIFS($F$3:$F$98,$A$3:$A$98,A72,$B$3:$B$98,0)),"") | J72: =IF(B72=0,1,IF(C72<=1,G72-SUMIFS($G$3:$G$98,$A$3:$A$98,A72,$B$3:$B$98,0),G72-G71)/E72/(SUMIFS($G$3:$G$98,$A$3:$A$98,A72,$B$3:$B$98,0)/SUMIFS($F$3:$F$98,$A$3:$A$98,A72,$B$3:$B$98,0))) | M72: =IF(OR(K72="",L72="",L72=0),"",K72/L72) | O72: =IF(B72=0,"基准",IF(AND(N72<>"",I72<0.85),"功能型：单看输出偏低属正常",IF(I72>=0.85,"划算",IF(I72>=0.65,"略亏：空位紧张时仍值得","偏亏：建议降价或加强"))))
A73: tesla | B73: 2 | C73: 1 | D73: 低音炮 | E73: 90 | F73: 240 | G73: 11.2 | H73: =G73/F73*100 | I73: =IFERROR((G73/F73)/(SUMIFS($G$3:$G$98,$A$3:$A$98,A73,$B$3:$B$98,0)/SUMIFS($F$3:$F$98,$A$3:$A$98,A73,$B$3:$B$98,0)),"") | J73: =IF(B73=0,1,IF(C73<=1,G73-SUMIFS($G$3:$G$98,$A$3:$A$98,A73,$B$3:$B$98,0),G73-G72)/E73/(SUMIFS($G$3:$G$98,$A$3:$A$98,A73,$B$3:$B$98,0)/SUMIFS($F$3:$F$98,$A$3:$A$98,A73,$B$3:$B$98,0))) | K73: 0.321 | L73: 0.334 | M73: =IF(OR(K73="",L73="",L73=0),"",K73/L73) | O73: =IF(B73=0,"基准",IF(AND(N73<>"",I73<0.85),"功能型：单看输出偏低属正常",IF(I73>=0.85,"划算",IF(I73>=0.65,"略亏：空位紧张时仍值得","偏亏：建议降价或加强"))))
A74: tesla | B74: 2 | C74: 2 | D74: 大功率 | E74: 150 | F74: 390 | G74: 17.61 | H74: =G74/F74*100 | I74: =IFERROR((G74/F74)/(SUMIFS($G$3:$G$98,$A$3:$A$98,A74,$B$3:$B$98,0)/SUMIFS($F$3:$F$98,$A$3:$A$98,A74,$B$3:$B$98,0)),"") | J74: =IF(B74=0,1,IF(C74<=1,G74-SUMIFS($G$3:$G$98,$A$3:$A$98,A74,$B$3:$B$98,0),G74-G73)/E74/(SUMIFS($G$3:$G$98,$A$3:$A$98,A74,$B$3:$B$98,0)/SUMIFS($F$3:$F$98,$A$3:$A$98,A74,$B$3:$B$98,0))) | K74: 0.6 | L74: 0.466 | M74: =IF(OR(K74="",L74="",L74=0),"",K74/L74) | O74: =IF(B74=0,"基准",IF(AND(N74<>"",I74<0.85),"功能型：单看输出偏低属正常",IF(I74>=0.85,"划算",IF(I74>=0.65,"略亏：空位紧张时仍值得","偏亏：建议降价或加强"))))
A75: tesla | B75: 2 | C75: 3 | D75: 重低音 | E75: 380 | F75: 770 | G75: 26.41 | H75: =G75/F75*100 | I75: =IFERROR((G75/F75)/(SUMIFS($G$3:$G$98,$A$3:$A$98,A75,$B$3:$B$98,0)/SUMIFS($F$3:$F$98,$A$3:$A$98,A75,$B$3:$B$98,0)),"") | J75: =IF(B75=0,1,IF(C75<=1,G75-SUMIFS($G$3:$G$98,$A$3:$A$98,A75,$B$3:$B$98,0),G75-G74)/E75/(SUMIFS($G$3:$G$98,$A$3:$A$98,A75,$B$3:$B$98,0)/SUMIFS($F$3:$F$98,$A$3:$A$98,A75,$B$3:$B$98,0))) | K75: 0.621 | L75: 0.808 | M75: =IF(OR(K75="",L75="",L75=0),"",K75/L75) | O75: =IF(B75=0,"基准",IF(AND(N75<>"",I75<0.85),"功能型：单看输出偏低属正常",IF(I75>=0.85,"划算",IF(I75>=0.65,"略亏：空位紧张时仍值得","偏亏：建议降价或加强"))))
A76: tesla | B76: 2 | C76: 4 | D76: 炸街 | E76: 800 | F76: 1570 | G76: 52.82 | H76: =G76/F76*100 | I76: =IFERROR((G76/F76)/(SUMIFS($G$3:$G$98,$A$3:$A$98,A76,$B$3:$B$98,0)/SUMIFS($F$3:$F$98,$A$3:$A$98,A76,$B$3:$B$98,0)),"") | J76: =IF(B76=0,1,IF(C76<=1,G76-SUMIFS($G$3:$G$98,$A$3:$A$98,A76,$B$3:$B$98,0),G76-G75)/E76/(SUMIFS($G$3:$G$98,$A$3:$A$98,A76,$B$3:$B$98,0)/SUMIFS($F$3:$F$98,$A$3:$A$98,A76,$B$3:$B$98,0))) | K76: 1 | L76: 1 | M76: =IF(OR(K76="",L76="",L76=0),"",K76/L76) | O76: =IF(B76=0,"基准",IF(AND(N76<>"",I76<0.85),"功能型：单看输出偏低属正常",IF(I76>=0.85,"划算",IF(I76>=0.65,"略亏：空位紧张时仍值得","偏亏：建议降价或加强"))))
A77: tesla | B77: 2 | C77: 5 | D77: 地动山摇 | E77: 1500 | F77: 3070 | G77: 96.84 | H77: =G77/F77*100 | I77: =IFERROR((G77/F77)/(SUMIFS($G$3:$G$98,$A$3:$A$98,A77,$B$3:$B$98,0)/SUMIFS($F$3:$F$98,$A$3:$A$98,A77,$B$3:$B$98,0)),"") | J77: =IF(B77=0,1,IF(C77<=1,G77-SUMIFS($G$3:$G$98,$A$3:$A$98,A77,$B$3:$B$98,0),G77-G76)/E77/(SUMIFS($G$3:$G$98,$A$3:$A$98,A77,$B$3:$B$98,0)/SUMIFS($F$3:$F$98,$A$3:$A$98,A77,$B$3:$B$98,0))) | M77: =IF(OR(K77="",L77="",L77=0),"",K77/L77) | O77: =IF(B77=0,"基准",IF(AND(N77<>"",I77<0.85),"功能型：单看输出偏低属正常",IF(I77>=0.85,"划算",IF(I77>=0.65,"略亏：空位紧张时仍值得","偏亏：建议降价或加强"))))
A78: tesla | B78: 3 | C78: 1 | D78: 扩音 | E78: 70 | F78: 220 | G78: 6.4 | H78: =G78/F78*100 | I78: =IFERROR((G78/F78)/(SUMIFS($G$3:$G$98,$A$3:$A$98,A78,$B$3:$B$98,0)/SUMIFS($F$3:$F$98,$A$3:$A$98,A78,$B$3:$B$98,0)),"") | J78: =IF(B78=0,1,IF(C78<=1,G78-SUMIFS($G$3:$G$98,$A$3:$A$98,A78,$B$3:$B$98,0),G78-G77)/E78/(SUMIFS($G$3:$G$98,$A$3:$A$98,A78,$B$3:$B$98,0)/SUMIFS($F$3:$F$98,$A$3:$A$98,A78,$B$3:$B$98,0))) | K78: 0.238 | L78: 0.313 | M78: =IF(OR(K78="",L78="",L78=0),"",K78/L78) | O78: =IF(B78=0,"基准",IF(AND(N78<>"",I78<0.85),"功能型：单看输出偏低属正常",IF(I78>=0.85,"划算",IF(I78>=0.65,"略亏：空位紧张时仍值得","偏亏：建议降价或加强"))))
A79: tesla | B79: 3 | C79: 2 | D79: 跟着跳 | E79: 130 | F79: 350 | G79: 6.4 | H79: =G79/F79*100 | I79: =IFERROR((G79/F79)/(SUMIFS($G$3:$G$98,$A$3:$A$98,A79,$B$3:$B$98,0)/SUMIFS($F$3:$F$98,$A$3:$A$98,A79,$B$3:$B$98,0)),"") | J79: =IF(B79=0,1,IF(C79<=1,G79-SUMIFS($G$3:$G$98,$A$3:$A$98,A79,$B$3:$B$98,0),G79-G78)/E79/(SUMIFS($G$3:$G$98,$A$3:$A$98,A79,$B$3:$B$98,0)/SUMIFS($F$3:$F$98,$A$3:$A$98,A79,$B$3:$B$98,0))) | K79: 0.248 | L79: 0.435 | M79: =IF(OR(K79="",L79="",L79=0),"",K79/L79) | N79: 眩晕 | O79: =IF(B79=0,"基准",IF(AND(N79<>"",I79<0.85),"功能型：单看输出偏低属正常",IF(I79>=0.85,"划算",IF(I79>=0.65,"略亏：空位紧张时仍值得","偏亏：建议降价或加强"))))
A80: tesla | B80: 3 | C80: 3 | D80: 震碎能量盾 | E80: 330 | F80: 680 | G80: 6.4 | H80: =G80/F80*100 | I80: =IFERROR((G80/F80)/(SUMIFS($G$3:$G$98,$A$3:$A$98,A80,$B$3:$B$98,0)/SUMIFS($F$3:$F$98,$A$3:$A$98,A80,$B$3:$B$98,0)),"") | J80: =IF(B80=0,1,IF(C80<=1,G80-SUMIFS($G$3:$G$98,$A$3:$A$98,A80,$B$3:$B$98,0),G80-G79)/E80/(SUMIFS($G$3:$G$98,$A$3:$A$98,A80,$B$3:$B$98,0)/SUMIFS($F$3:$F$98,$A$3:$A$98,A80,$B$3:$B$98,0))) | K80: 0.268 | L80: 0.742 | M80: =IF(OR(K80="",L80="",L80=0),"",K80/L80) | N80: 破盾 | O80: =IF(B80=0,"基准",IF(AND(N80<>"",I80<0.85),"功能型：单看输出偏低属正常",IF(I80>=0.85,"划算",IF(I80>=0.65,"略亏：空位紧张时仍值得","偏亏：建议降价或加强"))))
A81: tesla | B81: 3 | C81: 4 | D81: 魔性旋律 | E81: 700 | F81: 1380 | G81: 26.34 | H81: =G81/F81*100 | I81: =IFERROR((G81/F81)/(SUMIFS($G$3:$G$98,$A$3:$A$98,A81,$B$3:$B$98,0)/SUMIFS($F$3:$F$98,$A$3:$A$98,A81,$B$3:$B$98,0)),"") | J81: =IF(B81=0,1,IF(C81<=1,G81-SUMIFS($G$3:$G$98,$A$3:$A$98,A81,$B$3:$B$98,0),G81-G80)/E81/(SUMIFS($G$3:$G$98,$A$3:$A$98,A81,$B$3:$B$98,0)/SUMIFS($F$3:$F$98,$A$3:$A$98,A81,$B$3:$B$98,0))) | K81: 1 | L81: 1 | M81: =IF(OR(K81="",L81="",L81=0),"",K81/L81) | O81: =IF(B81=0,"基准",IF(AND(N81<>"",I81<0.85),"功能型：单看输出偏低属正常",IF(I81>=0.85,"划算",IF(I81>=0.65,"略亏：空位紧张时仍值得","偏亏：建议降价或加强"))))
A82: tesla | B82: 3 | C82: 5 | D82: 广场舞女王 | E82: 1600 | F82: 2980 | G82: 34.7 | H82: =G82/F82*100 | I82: =IFERROR((G82/F82)/(SUMIFS($G$3:$G$98,$A$3:$A$98,A82,$B$3:$B$98,0)/SUMIFS($F$3:$F$98,$A$3:$A$98,A82,$B$3:$B$98,0)),"") | J82: =IF(B82=0,1,IF(C82<=1,G82-SUMIFS($G$3:$G$98,$A$3:$A$98,A82,$B$3:$B$98,0),G82-G81)/E82/(SUMIFS($G$3:$G$98,$A$3:$A$98,A82,$B$3:$B$98,0)/SUMIFS($F$3:$F$98,$A$3:$A$98,A82,$B$3:$B$98,0))) | M82: =IF(OR(K82="",L82="",L82=0),"",K82/L82) | O82: =IF(B82=0,"基准",IF(AND(N82<>"",I82<0.85),"功能型：单看输出偏低属正常",IF(I82>=0.85,"划算",IF(I82>=0.65,"略亏：空位紧张时仍值得","偏亏：建议降价或加强"))))
A83: gem | B83: 0 | C83: 0 | D83: 基础 | E83: 140 | F83: 140 | G83: 2.4 | H83: =G83/F83*100 | I83: =IFERROR((G83/F83)/(SUMIFS($G$3:$G$98,$A$3:$A$98,A83,$B$3:$B$98,0)/SUMIFS($F$3:$F$98,$A$3:$A$98,A83,$B$3:$B$98,0)),"") | J83: =IF(B83=0,1,IF(C83<=1,G83-SUMIFS($G$3:$G$98,$A$3:$A$98,A83,$B$3:$B$98,0),G83-G82)/E83/(SUMIFS($G$3:$G$98,$A$3:$A$98,A83,$B$3:$B$98,0)/SUMIFS($F$3:$F$98,$A$3:$A$98,A83,$B$3:$B$98,0))) | M83: =IF(OR(K83="",L83="",L83=0),"",K83/L83) | O83: =IF(B83=0,"基准",IF(AND(N83<>"",I83<0.85),"功能型：单看输出偏低属正常",IF(I83>=0.85,"划算",IF(I83>=0.65,"略亏：空位紧张时仍值得","偏亏：建议降价或加强"))))
A84: gem | B84: 1 | C84: 1 | D84: 打磨红宝石 | E84: 80 | F84: 220 | G84: 4 | H84: =G84/F84*100 | I84: =IFERROR((G84/F84)/(SUMIFS($G$3:$G$98,$A$3:$A$98,A84,$B$3:$B$98,0)/SUMIFS($F$3:$F$98,$A$3:$A$98,A84,$B$3:$B$98,0)),"") | J84: =IF(B84=0,1,IF(C84<=1,G84-SUMIFS($G$3:$G$98,$A$3:$A$98,A84,$B$3:$B$98,0),G84-G83)/E84/(SUMIFS($G$3:$G$98,$A$3:$A$98,A84,$B$3:$B$98,0)/SUMIFS($F$3:$F$98,$A$3:$A$98,A84,$B$3:$B$98,0))) | K84: 0.357 | L84: 0.3 | M84: =IF(OR(K84="",L84="",L84=0),"",K84/L84) | O84: =IF(B84=0,"基准",IF(AND(N84<>"",I84<0.85),"功能型：单看输出偏低属正常",IF(I84>=0.85,"划算",IF(I84>=0.65,"略亏：空位紧张时仍值得","偏亏：建议降价或加强"))))
A85: gem | B85: 1 | C85: 2 | D85: 鸽血红 | E85: 90 | F85: 310 | G85: 4.71 | H85: =G85/F85*100 | I85: =IFERROR((G85/F85)/(SUMIFS($G$3:$G$98,$A$3:$A$98,A85,$B$3:$B$98,0)/SUMIFS($F$3:$F$98,$A$3:$A$98,A85,$B$3:$B$98,0)),"") | J85: =IF(B85=0,1,IF(C85<=1,G85-SUMIFS($G$3:$G$98,$A$3:$A$98,A85,$B$3:$B$98,0),G85-G84)/E85/(SUMIFS($G$3:$G$98,$A$3:$A$98,A85,$B$3:$B$98,0)/SUMIFS($F$3:$F$98,$A$3:$A$98,A85,$B$3:$B$98,0))) | K85: 0.373 | L85: 0.404 | M85: =IF(OR(K85="",L85="",L85=0),"",K85/L85) | O85: =IF(B85=0,"基准",IF(AND(N85<>"",I85<0.85),"功能型：单看输出偏低属正常",IF(I85>=0.85,"划算",IF(I85>=0.65,"略亏：空位紧张时仍值得","偏亏：建议降价或加强"))))
A86: gem | B86: 1 | C86: 3 | D86: 红宝石切面 | E86: 200 | F86: 510 | G86: 5.86 | H86: =G86/F86*100 | I86: =IFERROR((G86/F86)/(SUMIFS($G$3:$G$98,$A$3:$A$98,A86,$B$3:$B$98,0)/SUMIFS($F$3:$F$98,$A$3:$A$98,A86,$B$3:$B$98,0)),"") | J86: =IF(B86=0,1,IF(C86<=1,G86-SUMIFS($G$3:$G$98,$A$3:$A$98,A86,$B$3:$B$98,0),G86-G85)/E86/(SUMIFS($G$3:$G$98,$A$3:$A$98,A86,$B$3:$B$98,0)/SUMIFS($F$3:$F$98,$A$3:$A$98,A86,$B$3:$B$98,0))) | K86: 0.506 | L86: 0.687 | M86: =IF(OR(K86="",L86="",L86=0),"",K86/L86) | N86: 破甲 | O86: =IF(B86=0,"基准",IF(AND(N86<>"",I86<0.85),"功能型：单看输出偏低属正常",IF(I86>=0.85,"划算",IF(I86>=0.65,"略亏：空位紧张时仍值得","偏亏：建议降价或加强"))))
A87: gem | B87: 1 | C87: 4 | D87: 炽红核心 | E87: 450 | F87: 960 | G87: 11.71 | H87: =G87/F87*100 | I87: =IFERROR((G87/F87)/(SUMIFS($G$3:$G$98,$A$3:$A$98,A87,$B$3:$B$98,0)/SUMIFS($F$3:$F$98,$A$3:$A$98,A87,$B$3:$B$98,0)),"") | J87: =IF(B87=0,1,IF(C87<=1,G87-SUMIFS($G$3:$G$98,$A$3:$A$98,A87,$B$3:$B$98,0),G87-G86)/E87/(SUMIFS($G$3:$G$98,$A$3:$A$98,A87,$B$3:$B$98,0)/SUMIFS($F$3:$F$98,$A$3:$A$98,A87,$B$3:$B$98,0))) | K87: 0.698 | L87: 1 | M87: =IF(OR(K87="",L87="",L87=0),"",K87/L87) | N87: 对 Boss | O87: =IF(B87=0,"基准",IF(AND(N87<>"",I87<0.85),"功能型：单看输出偏低属正常",IF(I87>=0.85,"划算",IF(I87>=0.65,"略亏：空位紧张时仍值得","偏亏：建议降价或加强"))))
A88: gem | B88: 1 | C88: 5 | D88: 红宝石之心 | E88: 1700 | F88: 2660 | G88: 49.54 | H88: =G88/F88*100 | I88: =IFERROR((G88/F88)/(SUMIFS($G$3:$G$98,$A$3:$A$98,A88,$B$3:$B$98,0)/SUMIFS($F$3:$F$98,$A$3:$A$98,A88,$B$3:$B$98,0)),"") | J88: =IF(B88=0,1,IF(C88<=1,G88-SUMIFS($G$3:$G$98,$A$3:$A$98,A88,$B$3:$B$98,0),G88-G87)/E88/(SUMIFS($G$3:$G$98,$A$3:$A$98,A88,$B$3:$B$98,0)/SUMIFS($F$3:$F$98,$A$3:$A$98,A88,$B$3:$B$98,0))) | M88: =IF(OR(K88="",L88="",L88=0),"",K88/L88) | O88: =IF(B88=0,"基准",IF(AND(N88<>"",I88<0.85),"功能型：单看输出偏低属正常",IF(I88>=0.85,"划算",IF(I88>=0.65,"略亏：空位紧张时仍值得","偏亏：建议降价或加强"))))
A89: gem | B89: 2 | C89: 1 | D89: 黄晶碎片 | E89: 50 | F89: 190 | G89: 3 | H89: =G89/F89*100 | I89: =IFERROR((G89/F89)/(SUMIFS($G$3:$G$98,$A$3:$A$98,A89,$B$3:$B$98,0)/SUMIFS($F$3:$F$98,$A$3:$A$98,A89,$B$3:$B$98,0)),"") | J89: =IF(B89=0,1,IF(C89<=1,G89-SUMIFS($G$3:$G$98,$A$3:$A$98,A89,$B$3:$B$98,0),G89-G88)/E89/(SUMIFS($G$3:$G$98,$A$3:$A$98,A89,$B$3:$B$98,0)/SUMIFS($F$3:$F$98,$A$3:$A$98,A89,$B$3:$B$98,0))) | K89: 0.231 | L89: 0.265 | M89: =IF(OR(K89="",L89="",L89=0),"",K89/L89) | O89: =IF(B89=0,"基准",IF(AND(N89<>"",I89<0.85),"功能型：单看输出偏低属正常",IF(I89>=0.85,"划算",IF(I89>=0.65,"略亏：空位紧张时仍值得","偏亏：建议降价或加强"))))
A90: gem | B90: 2 | C90: 2 | D90: 双生黄晶 | E90: 130 | F90: 320 | G90: 6 | H90: =G90/F90*100 | I90: =IFERROR((G90/F90)/(SUMIFS($G$3:$G$98,$A$3:$A$98,A90,$B$3:$B$98,0)/SUMIFS($F$3:$F$98,$A$3:$A$98,A90,$B$3:$B$98,0)),"") | J90: =IF(B90=0,1,IF(C90<=1,G90-SUMIFS($G$3:$G$98,$A$3:$A$98,A90,$B$3:$B$98,0),G90-G89)/E90/(SUMIFS($G$3:$G$98,$A$3:$A$98,A90,$B$3:$B$98,0)/SUMIFS($F$3:$F$98,$A$3:$A$98,A90,$B$3:$B$98,0))) | K90: 0.454 | L90: 0.415 | M90: =IF(OR(K90="",L90="",L90=0),"",K90/L90) | O90: =IF(B90=0,"基准",IF(AND(N90<>"",I90<0.85),"功能型：单看输出偏低属正常",IF(I90>=0.85,"划算",IF(I90>=0.65,"略亏：空位紧张时仍值得","偏亏：建议降价或加强"))))
A91: gem | B91: 2 | C91: 3 | D91: 黄晶矿脉 | E91: 300 | F91: 620 | G91: 6 | H91: =G91/F91*100 | I91: =IFERROR((G91/F91)/(SUMIFS($G$3:$G$98,$A$3:$A$98,A91,$B$3:$B$98,0)/SUMIFS($F$3:$F$98,$A$3:$A$98,A91,$B$3:$B$98,0)),"") | J91: =IF(B91=0,1,IF(C91<=1,G91-SUMIFS($G$3:$G$98,$A$3:$A$98,A91,$B$3:$B$98,0),G91-G90)/E91/(SUMIFS($G$3:$G$98,$A$3:$A$98,A91,$B$3:$B$98,0)/SUMIFS($F$3:$F$98,$A$3:$A$98,A91,$B$3:$B$98,0))) | K91: 0.47 | L91: 0.822 | M91: =IF(OR(K91="",L91="",L91=0),"",K91/L91) | N91: 经济 | O91: =IF(B91=0,"基准",IF(AND(N91<>"",I91<0.85),"功能型：单看输出偏低属正常",IF(I91>=0.85,"划算",IF(I91>=0.65,"略亏：空位紧张时仍值得","偏亏：建议降价或加强"))))
A92: gem | B92: 2 | C92: 4 | D92: 黄晶棱镜 | E92: 560 | F92: 1180 | G92: 16 | H92: =G92/F92*100 | I92: =IFERROR((G92/F92)/(SUMIFS($G$3:$G$98,$A$3:$A$98,A92,$B$3:$B$98,0)/SUMIFS($F$3:$F$98,$A$3:$A$98,A92,$B$3:$B$98,0)),"") | J92: =IF(B92=0,1,IF(C92<=1,G92-SUMIFS($G$3:$G$98,$A$3:$A$98,A92,$B$3:$B$98,0),G92-G91)/E92/(SUMIFS($G$3:$G$98,$A$3:$A$98,A92,$B$3:$B$98,0)/SUMIFS($F$3:$F$98,$A$3:$A$98,A92,$B$3:$B$98,0))) | K92: 0.97 | L92: 1 | M92: =IF(OR(K92="",L92="",L92=0),"",K92/L92) | O92: =IF(B92=0,"基准",IF(AND(N92<>"",I92<0.85),"功能型：单看输出偏低属正常",IF(I92>=0.85,"划算",IF(I92>=0.65,"略亏：空位紧张时仍值得","偏亏：建议降价或加强"))))
A93: gem | B93: 2 | C93: 5 | D93: GST 金矿 | E93: 1600 | F93: 2780 | G93: 32 | H93: =G93/F93*100 | I93: =IFERROR((G93/F93)/(SUMIFS($G$3:$G$98,$A$3:$A$98,A93,$B$3:$B$98,0)/SUMIFS($F$3:$F$98,$A$3:$A$98,A93,$B$3:$B$98,0)),"") | J93: =IF(B93=0,1,IF(C93<=1,G93-SUMIFS($G$3:$G$98,$A$3:$A$98,A93,$B$3:$B$98,0),G93-G92)/E93/(SUMIFS($G$3:$G$98,$A$3:$A$98,A93,$B$3:$B$98,0)/SUMIFS($F$3:$F$98,$A$3:$A$98,A93,$B$3:$B$98,0))) | M93: =IF(OR(K93="",L93="",L93=0),"",K93/L93) | N93: 经济 | O93: =IF(B93=0,"基准",IF(AND(N93<>"",I93<0.85),"功能型：单看输出偏低属正常",IF(I93>=0.85,"划算",IF(I93>=0.65,"略亏：空位紧张时仍值得","偏亏：建议降价或加强"))))
A94: gem | B94: 3 | C94: 1 | D94: 冰蓝切片 | E94: 60 | F94: 200 | G94: 2.4 | H94: =G94/F94*100 | I94: =IFERROR((G94/F94)/(SUMIFS($G$3:$G$98,$A$3:$A$98,A94,$B$3:$B$98,0)/SUMIFS($F$3:$F$98,$A$3:$A$98,A94,$B$3:$B$98,0)),"") | J94: =IF(B94=0,1,IF(C94<=1,G94-SUMIFS($G$3:$G$98,$A$3:$A$98,A94,$B$3:$B$98,0),G94-G93)/E94/(SUMIFS($G$3:$G$98,$A$3:$A$98,A94,$B$3:$B$98,0)/SUMIFS($F$3:$F$98,$A$3:$A$98,A94,$B$3:$B$98,0))) | K94: 0.216 | L94: 0.276 | M94: =IF(OR(K94="",L94="",L94=0),"",K94/L94) | N94: 减速 | O94: =IF(B94=0,"基准",IF(AND(N94<>"",I94<0.85),"功能型：单看输出偏低属正常",IF(I94>=0.85,"划算",IF(I94>=0.65,"略亏：空位紧张时仍值得","偏亏：建议降价或加强"))))
A95: gem | B95: 3 | C95: 2 | D95: 深海蓝 | E95: 120 | F95: 320 | G95: 2.4 | H95: =G95/F95*100 | I95: =IFERROR((G95/F95)/(SUMIFS($G$3:$G$98,$A$3:$A$98,A95,$B$3:$B$98,0)/SUMIFS($F$3:$F$98,$A$3:$A$98,A95,$B$3:$B$98,0)),"") | J95: =IF(B95=0,1,IF(C95<=1,G95-SUMIFS($G$3:$G$98,$A$3:$A$98,A95,$B$3:$B$98,0),G95-G94)/E95/(SUMIFS($G$3:$G$98,$A$3:$A$98,A95,$B$3:$B$98,0)/SUMIFS($F$3:$F$98,$A$3:$A$98,A95,$B$3:$B$98,0))) | K95: 0.247 | L95: 0.415 | M95: =IF(OR(K95="",L95="",L95=0),"",K95/L95) | O95: =IF(B95=0,"基准",IF(AND(N95<>"",I95<0.85),"功能型：单看输出偏低属正常",IF(I95>=0.85,"划算",IF(I95>=0.65,"略亏：空位紧张时仍值得","偏亏：建议降价或加强"))))
A96: gem | B96: 3 | C96: 3 | D96: 蓝宝石冰封 | E96: 300 | F96: 620 | G96: 2.4 | H96: =G96/F96*100 | I96: =IFERROR((G96/F96)/(SUMIFS($G$3:$G$98,$A$3:$A$98,A96,$B$3:$B$98,0)/SUMIFS($F$3:$F$98,$A$3:$A$98,A96,$B$3:$B$98,0)),"") | J96: =IF(B96=0,1,IF(C96<=1,G96-SUMIFS($G$3:$G$98,$A$3:$A$98,A96,$B$3:$B$98,0),G96-G95)/E96/(SUMIFS($G$3:$G$98,$A$3:$A$98,A96,$B$3:$B$98,0)/SUMIFS($F$3:$F$98,$A$3:$A$98,A96,$B$3:$B$98,0))) | K96: 0.255 | L96: 0.822 | M96: =IF(OR(K96="",L96="",L96=0),"",K96/L96) | N96: 冻结 | O96: =IF(B96=0,"基准",IF(AND(N96<>"",I96<0.85),"功能型：单看输出偏低属正常",IF(I96>=0.85,"划算",IF(I96>=0.65,"略亏：空位紧张时仍值得","偏亏：建议降价或加强"))))
A97: gem | B97: 3 | C97: 4 | D97: 寒光 | E97: 680 | F97: 1300 | G97: 2.4 | H97: =G97/F97*100 | I97: =IFERROR((G97/F97)/(SUMIFS($G$3:$G$98,$A$3:$A$98,A97,$B$3:$B$98,0)/SUMIFS($F$3:$F$98,$A$3:$A$98,A97,$B$3:$B$98,0)),"") | J97: =IF(B97=0,1,IF(C97<=1,G97-SUMIFS($G$3:$G$98,$A$3:$A$98,A97,$B$3:$B$98,0),G97-G96)/E97/(SUMIFS($G$3:$G$98,$A$3:$A$98,A97,$B$3:$B$98,0)/SUMIFS($F$3:$F$98,$A$3:$A$98,A97,$B$3:$B$98,0))) | K97: 0.336 | L97: 1 | M97: =IF(OR(K97="",L97="",L97=0),"",K97/L97) | N97: 易伤 | O97: =IF(B97=0,"基准",IF(AND(N97<>"",I97<0.85),"功能型：单看输出偏低属正常",IF(I97>=0.85,"划算",IF(I97>=0.65,"略亏：空位紧张时仍值得","偏亏：建议降价或加强"))))
A98: gem | B98: 3 | C98: 5 | D98: 星海蓝钻 | E98: 1500 | F98: 2800 | G98: 2.4 | H98: =G98/F98*100 | I98: =IFERROR((G98/F98)/(SUMIFS($G$3:$G$98,$A$3:$A$98,A98,$B$3:$B$98,0)/SUMIFS($F$3:$F$98,$A$3:$A$98,A98,$B$3:$B$98,0)),"") | J98: =IF(B98=0,1,IF(C98<=1,G98-SUMIFS($G$3:$G$98,$A$3:$A$98,A98,$B$3:$B$98,0),G98-G97)/E98/(SUMIFS($G$3:$G$98,$A$3:$A$98,A98,$B$3:$B$98,0)/SUMIFS($F$3:$F$98,$A$3:$A$98,A98,$B$3:$B$98,0))) | M98: =IF(OR(K98="",L98="",L98=0),"",K98/L98) | N98: 冻结、减速、对 Boss | O98: =IF(B98=0,"基准",IF(AND(N98<>"",I98<0.85),"功能型：单看输出偏低属正常",IF(I98>=0.85,"划算",IF(I98>=0.65,"略亏：空位紧张时仍值得","偏亏：建议降价或加强"))))
A100: 怎么看：「比同价多买基础塔」= 这套升级每 GST 的输出 ÷ 基础装置每 GST 的输出。1.0 表示和把钱拿去多放几座基础装置一样划算；装置空位有限，所以 0.85 以上就算合格。
A101: 估算假设：跑者间距 26 像素，射程内覆盖跑道 ≈ 1.6 × 射程，射程内最多 8 人。减速、冻结、眩晕、经济、光环等功能型效果不计入输出。
A102: 实测：在经典跑道上用同一波 30 人测试，比较「一座升级装置」和「花同样 GST 放几座基础装置」各清掉多少体力（脚本 tools/sim_duel.mjs）。实测只覆盖 1–4 级。
...
